Workbook

Sheet Dashboard
A1: SmartRail — Project Dashboard
A2: Every figure is a formula. The only cell you ever edit here is the yellow start date in B3. | N2: Daily load — hours scheduled per day (amber over 9h)
A3: Project start (D1) | B3: 2026-09-29 | N3: D1 | O3: D2 | P3: D3 | Q3: D4 | R3: D5 | S3: D6 | T3: D7 | U3: D8 | V3: D9 | W3: D10 | X3: D11 | Y3: D12 | Z3: D13 | AA3: D14 | AB3: D15 | AC3: D16 | AD3: D17 | AE3: D18 | AF3: D19 | AG3: D20 | AH3: D21
A4: Today | B4: =TODAY() -> 46296 | N4: =SUMIFS(WBS!$J$5:'WBS'!$J$144,WBS!$F$5:'WBS'!$F$144,1,WBS!$B$5:'WBS'!$B$144,3) -> 10 | O4: =SUMIFS(WBS!$J$5:'WBS'!$J$144,WBS!$F$5:'WBS'!$F$144,2,WBS!$B$5:'WBS'!$B$144,3) -> 10 | P4: =SUMIFS(WBS!$J$5:'WBS'!$J$144,WBS!$F$5:'WBS'!$F$144,3,WBS!$B$5:'WBS'!$B$144,3) -> 8.5 | Q4: =SUMIFS(WBS!$J$5:'WBS'!$J$144,WBS!$F$5:'WBS'!$F$144,4,WBS!$B$5:'WBS'!$B$144,3) -> 8 | R4: =SUMIFS(WBS!$J$5:'WBS'!$J$144,WBS!$F$5:'WBS'!$F$144,5,WBS!$B$5:'WBS'!$B$144,3) -> 8 | S4: =SUMIFS(WBS!$J$5:'WBS'!$J$144,WBS!$F$5:'WBS'!$F$144,6,WBS!$B$5:'WBS'!$B$144,3) -> 9 | T4: =SUMIFS(WBS!$J$5:'WBS'!$J$144,WBS!$F$5:'WBS'!$F$144,7,WBS!$B$5:'WBS'!$B$144,3) -> 8 | U4: =SUMIFS(WBS!$J$5:'WBS'!$J$144,WBS!$F$5:'WBS'!$F$144,8,WBS!$B$5:'WBS'!$B$144,3) -> 8 | V4: =SUMIFS(WBS!$J$5:'WBS'!$J$144,WBS!$F$5:'WBS'!$F$144,9,WBS!$B$5:'WBS'!$B$144,3) -> 8 | W4: =SUMIFS(WBS!$J$5:'WBS'!$J$144,WBS!$F$5:'WBS'!$F$144,10,WBS!$B$5:'WBS'!$B$144,3) -> 8 | X4: =SUMIFS(WBS!$J$5:'WBS'!$J$144,WBS!$F$5:'WBS'!$F$144,11,WBS!$B$5:'WBS'!$B$144,3) -> 8 | Y4: =SUMIFS(WBS!$J$5:'WBS'!$J$144,WBS!$F$5:'WBS'!$F$144,12,WBS!$B$5:'WBS'!$B$144,3) -> 8 | Z4: =SUMIFS(WBS!$J$5:'WBS'!$J$144,WBS!$F$5:'WBS'!$F$144,13,WBS!$B$5:'WBS'!$B$144,3) -> 8 | AA4: =SUMIFS(WBS!$J$5:'WBS'!$J$144,WBS!$F$5:'WBS'!$F$144,14,WBS!$B$5:'WBS'!$B$144,3) -> 9.5 | AB4: =SUMIFS(WBS!$J$5:'WBS'!$J$144,WBS!$F$5:'WBS'!$F$144,15,WBS!$B$5:'WBS'!$B$144,3) -> 8 | AC4: =SUMIFS(WBS!$J$5:'WBS'!$J$144,WBS!$F$5:'WBS'!$F$144,16,WBS!$B$5:'WBS'!$B$144,3) -> 8 | AD4: =SUMIFS(WBS!$J$5:'WBS'!$J$144,WBS!$F$5:'WBS'!$F$144,17,WBS!$B$5:'WBS'!$B$144,3) -> 8 | AE4: =SUMIFS(WBS!$J$5:'WBS'!$J$144,WBS!$F$5:'WBS'!$F$144,18,WBS!$B$5:'WBS'!$B$144,3) -> 8 | AF4: =SUMIFS(WBS!$J$5:'WBS'!$J$144,WBS!$F$5:'WBS'!$F$144,19,WBS!$B$5:'WBS'!$B$144,3) -> 7.5 | AG4: =SUMIFS(WBS!$J$5:'WBS'!$J$144,WBS!$F$5:'WBS'!$F$144,20,WBS!$B$5:'WBS'!$B$144,3) -> 7 | AH4: =SUMIFS(WBS!$J$5:'WBS'!$J$144,WBS!$F$5:'WBS'!$F$144,21,WBS!$B$5:'WBS'!$B$144,3) -> 6.5
A5: Current day | B5: =MAX(0,$B$4-$B$3+1) -> 3
A6: Total days | B6: 21
A7: Days to submission | B7: =MAX(0,$B$6-$B$5) -> 18
A9: Progress | D9: Phase rollup
A10: Tasks in scope | B10: =COUNTIFS(WBS!$B$5:'WBS'!$B$144,3,WBS!$L$5:'WBS'!$L$144,"<>Deferred") -> 96 | D10: # | E10: Phase | F10: Days | G10: Est h | H10: Logged | I10: % Done
A11: Done | B11: =COUNTIFS(WBS!$B$5:'WBS'!$B$144,3,WBS!$L$5:'WBS'!$L$144,"Done") -> 2 | D11: 1 | E11: =INDEX(WBS!$D$5:$D$144,MATCH("1",WBS!$A$5:$A$144,0)) -> Discovery | F11: ="D"&INDEX(WBS!$F$5:$F$144,MATCH("1",WBS!$A$5:$A$144,0))&"-D"&INDEX(WBS!$T$5:$T$144,MATCH("1",WBS!$A$5:$A$144,0)) -> D1-D3 | G11: =INDEX(WBS!$J$5:$J$144,MATCH("1",WBS!$A$5:$A$144,0)) -> 28.5 | H11: =INDEX(WBS!$K$5:$K$144,MATCH("1",WBS!$A$5:$A$144,0)) -> 0 | I11: =INDEX(WBS!$M$5:$M$144,MATCH("1",WBS!$A$5:$A$144,0)) -> 0.10526316
A12: In progress | B12: =COUNTIFS(WBS!$B$5:'WBS'!$B$144,3,WBS!$L$5:'WBS'!$L$144,"Doing") -> 0 | D12: 2 | E12: =INDEX(WBS!$D$5:$D$144,MATCH("2",WBS!$A$5:$A$144,0)) -> Design and Decide | F12: ="D"&INDEX(WBS!$F$5:$F$144,MATCH("2",WBS!$A$5:$A$144,0))&"-D"&INDEX(WBS!$T$5:$T$144,MATCH("2",WBS!$A$5:$A$144,0)) -> D4-D5 | G12: =INDEX(WBS!$J$5:$J$144,MATCH("2",WBS!$A$5:$A$144,0)) -> 16 | H12: =INDEX(WBS!$K$5:$K$144,MATCH("2",WBS!$A$5:$A$144,0)) -> 0 | I12: =INDEX(WBS!$M$5:$M$144,MATCH("2",WBS!$A$5:$A$144,0)) -> 0
A13: Blocked | B13: =COUNTIFS(WBS!$B$5:'WBS'!$B$144,3,WBS!$L$5:'WBS'!$L$144,"Blocked") -> 0 | D13: 3 | E13: =INDEX(WBS!$D$5:$D$144,MATCH("3",WBS!$A$5:$A$144,0)) -> Backend Spine | F13: ="D"&INDEX(WBS!$F$5:$F$144,MATCH("3",WBS!$A$5:$A$144,0))&"-D"&INDEX(WBS!$T$5:$T$144,MATCH("3",WBS!$A$5:$A$144,0)) -> D6-D7 | G13: =INDEX(WBS!$J$5:$J$144,MATCH("3",WBS!$A$5:$A$144,0)) -> 17 | H13: =INDEX(WBS!$K$5:$K$144,MATCH("3",WBS!$A$5:$A$144,0)) -> 0 | I13: =INDEX(WBS!$M$5:$M$144,MATCH("3",WBS!$A$5:$A$144,0)) -> 0
A14: Not started | B14: =COUNTIFS(WBS!$B$5:'WBS'!$B$144,3,WBS!$L$5:'WBS'!$L$144,"To do") -> 94 | D14: 4 | E14: =INDEX(WBS!$D$5:$D$144,MATCH("4",WBS!$A$5:$A$144,0)) -> Live Core | F14: ="D"&INDEX(WBS!$F$5:$F$144,MATCH("4",WBS!$A$5:$A$144,0))&"-D"&INDEX(WBS!$T$5:$T$144,MATCH("4",WBS!$A$5:$A$144,0)) -> D8-D9 | G14: =INDEX(WBS!$J$5:$J$144,MATCH("4",WBS!$A$5:$A$144,0)) -> 16 | H14: =INDEX(WBS!$K$5:$K$144,MATCH("4",WBS!$A$5:$A$144,0)) -> 0 | I14: =INDEX(WBS!$M$5:$M$144,MATCH("4",WBS!$A$5:$A$144,0)) -> 0
A15: Deferred | B15: =COUNTIFS(WBS!$B$5:'WBS'!$B$144,3,WBS!$L$5:'WBS'!$L$144,"Deferred") -> 0 | D15: 5 | E15: =INDEX(WBS!$D$5:$D$144,MATCH("5",WBS!$A$5:$A$144,0)) -> Client Applications | F15: ="D"&INDEX(WBS!$F$5:$F$144,MATCH("5",WBS!$A$5:$A$144,0))&"-D"&INDEX(WBS!$T$5:$T$144,MATCH("5",WBS!$A$5:$A$144,0)) -> D10-D13 | G15: =INDEX(WBS!$J$5:$J$144,MATCH("5",WBS!$A$5:$A$144,0)) -> 32 | H15: =INDEX(WBS!$K$5:$K$144,MATCH("5",WBS!$A$5:$A$144,0)) -> 0 | I15: =INDEX(WBS!$M$5:$M$144,MATCH("5",WBS!$A$5:$A$144,0)) -> 0
A16: Overall % complete (hour weighted) | B16: =IFERROR(SUMPRODUCT((WBS!$B$5:'WBS'!$B$144=3)*(WBS!$L$5:'WBS'!$L$144<>"Deferred")*WBS!$J$5:'WBS'!$J$144*WBS!$M$5:'WBS'!$M$144)/SUMPRODUCT((WBS!$B$5:'WBS'!$B$144=3)*(WBS!$L$5:'WBS'!$L$144<>"Deferred")*WBS!$J$5:'WBS'!$J$144),0) -> 0.01744186 | D16: 6 | E16: =INDEX(WBS!$D$5:$D$144,MATCH("6",WBS!$A$5:$A$144,0)) -> External Integration | F16: ="D"&INDEX(WBS!$F$5:$F$144,MATCH("6",WBS!$A$5:$A$144,0))&"-D"&INDEX(WBS!$T$5:$T$144,MATCH("6",WBS!$A$5:$A$144,0)) -> D14-D14 | G16: =INDEX(WBS!$J$5:$J$144,MATCH("6",WBS!$A$5:$A$144,0)) -> 9.5 | H16: =INDEX(WBS!$K$5:$K$144,MATCH("6",WBS!$A$5:$A$144,0)) -> 0 | I16: =INDEX(WBS!$M$5:$M$144,MATCH("6",WBS!$A$5:$A$144,0)) -> 0
A17: Slipped tasks (past due, not done) | B17: =COUNTIFS(WBS!$B$5:'WBS'!$B$144,3,WBS!$F$5:'WBS'!$F$144,"<"&$B$5,WBS!$L$5:'WBS'!$L$144,"<>Done",WBS!$L$5:'WBS'!$L$144,"<>Deferred") -> 8 | D17: 7 | E17: =INDEX(WBS!$D$5:$D$144,MATCH("7",WBS!$A$5:$A$144,0)) -> Harden and Prove | F17: ="D"&INDEX(WBS!$F$5:$F$144,MATCH("7",WBS!$A$5:$A$144,0))&"-D"&INDEX(WBS!$T$5:$T$144,MATCH("7",WBS!$A$5:$A$144,0)) -> D15-D18 | G17: =INDEX(WBS!$J$5:$J$144,MATCH("7",WBS!$A$5:$A$144,0)) -> 32 | H17: =INDEX(WBS!$K$5:$K$144,MATCH("7",WBS!$A$5:$A$144,0)) -> 0 | I17: =INDEX(WBS!$M$5:$M$144,MATCH("7",WBS!$A$5:$A$144,0)) -> 0
A18: Estimated hours in scope | B18: =SUMPRODUCT((WBS!$B$5:'WBS'!$B$144=3)*(WBS!$L$5:'WBS'!$L$144<>"Deferred")*WBS!$J$5:'WBS'!$J$144) -> 172 | D18: 8 | E18: =INDEX(WBS!$D$5:$D$144,MATCH("8",WBS!$A$5:$A$144,0)) -> Evidence and Demo | F18: ="D"&INDEX(WBS!$F$5:$F$144,MATCH("8",WBS!$A$5:$A$144,0))&"-D"&INDEX(WBS!$T$5:$T$144,MATCH("8",WBS!$A$5:$A$144,0)) -> D19-D21 | G18: =INDEX(WBS!$J$5:$J$144,MATCH("8",WBS!$A$5:$A$144,0)) -> 21 | H18: =INDEX(WBS!$K$5:$K$144,MATCH("8",WBS!$A$5:$A$144,0)) -> 0 | I18: =INDEX(WBS!$M$5:$M$144,MATCH("8",WBS!$A$5:$A$144,0)) -> 0
A19: Hours logged | B19: =SUMPRODUCT((WBS!$B$5:'WBS'!$B$144=3)*WBS!$K$5:'WBS'!$K$144) -> 0
A20: Estimate accuracy on completed work | B20: =IFERROR(SUMPRODUCT((WBS!$B$5:'WBS'!$B$144=3)*(WBS!$L$5:'WBS'!$L$144="Done")*WBS!$K$5:'WBS'!$K$144)/SUMPRODUCT((WBS!$B$5:'WBS'!$B$144=3)*(WBS!$L$5:'WBS'!$L$144="Done")*WBS!$J$5:'WBS'!$J$144),0) -> 0
D21: Gates
D22: Gate | E22: Description | F22: Day | G22: Date | H22: Open | I22: Status
A23: AI usage | D23: G1 | E23: Requirements frozen | F23: 3 | G23: =$B$3+$F23-1 -> 46296 | H23: =COUNTIFS(WBS!$B$5:'WBS'!$B$144,3,WBS!$F$5:'WBS'!$F$144,"<="&$F23,WBS!$L$5:'WBS'!$L$144,"<>Done",WBS!$L$5:'WBS'!$L$144,"<>Deferred") -> 14 | I23: =IF($H23=0,"Cleared",IF($F23<$B$5,"MISSED","Open")) -> Open
A24: Logged AI contributions | B24: ='AI Summary'!$B$5 -> 2 | D24: G2 | E24: Spine runs and CI green | F24: 7 | G24: =$B$3+$F24-1 -> 46300 | H24: =COUNTIFS(WBS!$B$5:'WBS'!$B$144,3,WBS!$F$5:'WBS'!$F$144,"<="&$F24,WBS!$L$5:'WBS'!$L$144,"<>Done",WBS!$L$5:'WBS'!$L$144,"<>Deferred") -> 33 | I24: =IF($H24=0,"Cleared",IF($F24<$B$5,"MISSED","Open")) -> Open
A25: Challenge rate | B25: ='AI Summary'!$B$9 -> 1 | D25: G3 | E25: Feature freeze - no new features | F25: 14 | G25: =$B$3+$F25-1 -> 46307 | H25: =COUNTIFS(WBS!$B$5:'WBS'!$B$144,3,WBS!$F$5:'WBS'!$F$144,"<="&$F25,WBS!$L$5:'WBS'!$L$144,"<>Done",WBS!$L$5:'WBS'!$L$144,"<>Deferred") -> 64 | I25: =IF($H25=0,"Cleared",IF($F25<$B$5,"MISSED","Open")) -> Open
A26: AI was wrong (target 8) | B26: ='AI Summary'!$B$10 -> 2 | D26: G4 | E26: Five E2E flows green | F26: 16 | G26: =$B$3+$F26-1 -> 46309 | H26: =COUNTIFS(WBS!$B$5:'WBS'!$B$144,3,WBS!$F$5:'WBS'!$F$144,"<="&$F26,WBS!$L$5:'WBS'!$L$144,"<>Done",WBS!$L$5:'WBS'!$L$144,"<>Deferred") -> 74 | I26: =IF($H26=0,"Cleared",IF($F26<$B$5,"MISSED","Open")) -> Open
A27: Net hours from AI | B27: ='AI Summary'!$B$15 -> 0 | D27: G5 | E27: Documentation complete | F27: 19 | G27: =$B$3+$F27-1 -> 46312 | H27: =COUNTIFS(WBS!$B$5:'WBS'!$B$144,3,WBS!$F$5:'WBS'!$F$144,"<="&$F27,WBS!$L$5:'WBS'!$L$144,"<>Done",WBS!$L$5:'WBS'!$L$144,"<>Deferred") -> 87 | I27: =IF($H27=0,"Cleared",IF($F27<$B$5,"MISSED","Open")) -> Open
D28: G6 | E28: Submission | F28: 21 | G28: =$B$3+$F28-1 -> 46314 | H28: =COUNTIFS(WBS!$B$5:'WBS'!$B$144,3,WBS!$F$5:'WBS'!$F$144,"<="&$F28,WBS!$L$5:'WBS'!$L$144,"<>Done",WBS!$L$5:'WBS'!$L$144,"<>Deferred") -> 94 | I28: =IF($H28=0,"Cleared",IF($F28<$B$5,"MISSED","Open")) -> Open
D31: AI usage evidence — brief §21 coverage
D32: § | E32: What §21 asks for | F32: Evidence lives on | G32: Have | H32: Target | I32: Status
D33: 1 | E33: Which AI tools or agents you used | F33: AI Policy | G33: =COUNTA('AI Policy'!$A$9:$A$13) -> 5 | H33: 5 | I33: =IF($G33>=$H33,"Covered","Need "&($H33-$G33)&" more") -> Covered
D34: 2 | E34: What responsibilities were assigned to them | F34: AI Policy | G34: =COUNTA('AI Policy'!$A$18:$A$27) -> 10 | H34: 10 | I34: =IF($G34>=$H34,"Covered","Need "&($H34-$G34)&" more") -> Covered
D35: 3 | E35: Important prompts or workflows | F35: Prompt Library | G35: =COUNTA('Prompt Library'!$B$5:$B$84) -> 2 | H35: 10 | I35: =IF($G35>=$H35,"Covered","Need "&($H35-$G35)&" more") -> Need 8 more
D36: 4 | E36: How their output was validated | F36: AI Usage Log + AI Policy | G36: =COUNTA('AI Usage Log'!$N$5:$N$204) -> 2 | H36: ='AI Summary'!$B$5 -> 2 | I36: =IF($G36>=$H36,"Covered","Need "&($H36-$G36)&" more") -> Covered
D37: 5 | E37: Examples where AI output was incorrect or insufficient | F37: AI Failures | G37: =COUNTA('AI Failures'!$B$5:$B$44) -> 2 | H37: 8 | I37: =IF($G37>=$H37,"Covered","Need "&($H37-$G37)&" more") -> Need 6 more
D38: 6 | E38: Examples where your own judgment improved the result | F38: AI Usage Log + AI Failures | G38: ='AI Summary'!$B$7+'AI Summary'!$B$8 -> 2 | H38: 8 | I38: =IF($G38>=$H38,"Covered","Need "&($H38-$G38)&" more") -> Need 6 more
D39: 7 | E39: AI implementation you significantly modified, and why | F39: Modified Impl | G39: =COUNTA('Modified Impl'!$B$5:$B$44) -> 1 | H39: 5 | I39: =IF($G39>=$H39,"Covered","Need "&($H39-$G39)&" more") -> Need 4 more
D42: Work packages — titles and subtask progress
D43: WBS | E43: Work package (title) | F43: Phase | G43: Days | H43: Subtasks | I43: Done | J43: % Done
D44: 1.1 | E44: =TRIM(INDEX(WBS!$C$5:$C$144,MATCH($D44,WBS!$A$5:$A$144,0))) -> Brief analysis and gap discovery | F44: =INDEX(WBS!$D$5:$D$144,MATCH($D44,WBS!$A$5:$A$144,0)) -> Discovery | G44: ="D"&INDEX(WBS!$F$5:$F$144,MATCH($D44,WBS!$A$5:$A$144,0))&"-D"&INDEX(WBS!$T$5:$T$144,MATCH($D44,WBS!$A$5:$A$144,0)) -> D1-D2 | H44: =COUNTIFS(WBS!$R$5:$R$144,$D44,WBS!$B$5:$B$144,3) -> 3 | I44: =COUNTIFS(WBS!$R$5:$R$144,$D44,WBS!$B$5:$B$144,3,WBS!$L$5:$L$144,"Done") -> 0 | J44: =INDEX(WBS!$M$5:$M$144,MATCH($D44,WBS!$A$5:$A$144,0)) -> 0
D45: 1.2 | E45: =TRIM(INDEX(WBS!$C$5:$C$144,MATCH($D45,WBS!$A$5:$A$144,0))) -> Stakeholder simulation | F45: =INDEX(WBS!$D$5:$D$144,MATCH($D45,WBS!$A$5:$A$144,0)) -> Discovery | G45: ="D"&INDEX(WBS!$F$5:$F$144,MATCH($D45,WBS!$A$5:$A$144,0))&"-D"&INDEX(WBS!$T$5:$T$144,MATCH($D45,WBS!$A$5:$A$144,0)) -> D1-D3 | H45: =COUNTIFS(WBS!$R$5:$R$144,$D45,WBS!$B$5:$B$144,3) -> 4 | I45: =COUNTIFS(WBS!$R$5:$R$144,$D45,WBS!$B$5:$B$144,3,WBS!$L$5:$L$144,"Done") -> 0 | J45: =INDEX(WBS!$M$5:$M$144,MATCH($D45,WBS!$A$5:$A$144,0)) -> 0
D46: 1.3 | E46: =TRIM(INDEX(WBS!$C$5:$C$144,MATCH($D46,WBS!$A$5:$A$144,0))) -> Requirement engineering | F46: =INDEX(WBS!$D$5:$D$144,MATCH($D46,WBS!$A$5:$A$144,0)) -> Discovery | G46: ="D"&INDEX(WBS!$F$5:$F$144,MATCH($D46,WBS!$A$5:$A$144,0))&"-D"&INDEX(WBS!$T$5:$T$144,MATCH($D46,WBS!$A$5:$A$144,0)) -> D2-D3 | H46: =COUNTIFS(WBS!$R$5:$R$144,$D46,WBS!$B$5:$B$144,3) -> 4 | I46: =COUNTIFS(WBS!$R$5:$R$144,$D46,WBS!$B$5:$B$144,3,WBS!$L$5:$L$144,"Done") -> 0 | J46: =INDEX(WBS!$M$5:$M$144,MATCH($D46,WBS!$A$5:$A$144,0)) -> 0
D47: 1.4 | E47: =TRIM(INDEX(WBS!$C$5:$C$144,MATCH($D47,WBS!$A$5:$A$144,0))) -> Scope control | F47: =INDEX(WBS!$D$5:$D$144,MATCH($D47,WBS!$A$5:$A$144,0)) -> Discovery | G47: ="D"&INDEX(WBS!$F$5:$F$144,MATCH($D47,WBS!$A$5:$A$144,0))&"-D"&INDEX(WBS!$T$5:$T$144,MATCH($D47,WBS!$A$5:$A$144,0)) -> D3-D3 | H47: =COUNTIFS(WBS!$R$5:$R$144,$D47,WBS!$B$5:$B$144,3) -> 2 | I47: =COUNTIFS(WBS!$R$5:$R$144,$D47,WBS!$B$5:$B$144,3,WBS!$L$5:$L$144,"Done") -> 0 | J47: =INDEX(WBS!$M$5:$M$144,MATCH($D47,WBS!$A$5:$A$144,0)) -> 0
D48: 1.5 | E48: =TRIM(INDEX(WBS!$C$5:$C$144,MATCH($D48,WBS!$A$5:$A$144,0))) -> Project setup | F48: =INDEX(WBS!$D$5:$D$144,MATCH($D48,WBS!$A$5:$A$144,0)) -> Discovery | G48: ="D"&INDEX(WBS!$F$5:$F$144,MATCH($D48,WBS!$A$5:$A$144,0))&"-D"&INDEX(WBS!$T$5:$T$144,MATCH($D48,WBS!$A$5:$A$144,0)) -> D1-D1 | H48: =COUNTIFS(WBS!$R$5:$R$144,$D48,WBS!$B$5:$B$144,3) -> 3 | I48: =COUNTIFS(WBS!$R$5:$R$144,$D48,WBS!$B$5:$B$144,3,WBS!$L$5:$L$144,"Done") -> 2 | J48: =INDEX(WBS!$M$5:$M$144,MATCH($D48,WBS!$A$5:$A$144,0)) -> 0.75
D49: 2.1 | E49: =TRIM(INDEX(WBS!$C$5:$C$144,MATCH($D49,WBS!$A$5:$A$144,0))) -> Domain design | F49: =INDEX(WBS!$D$5:$D$144,MATCH($D49,WBS!$A$5:$A$144,0)) -> Design and Decide | G49: ="D"&INDEX(WBS!$F$5:$F$144,MATCH($D49,WBS!$A$5:$A$144,0))&"-D"&INDEX(WBS!$T$5:$T$144,MATCH($D49,WBS!$A$5:$A$144,0)) -> D4-D4 | H49: =COUNTIFS(WBS!$R$5:$R$144,$D49,WBS!$B$5:$B$144,3) -> 2 | I49: =COUNTIFS(WBS!$R$5:$R$144,$D49,WBS!$B$5:$B$144,3,WBS!$L$5:$L$144,"Done") -> 0 | J49: =INDEX(WBS!$M$5:$M$144,MATCH($D49,WBS!$A$5:$A$144,0)) -> 0
D50: 2.2 | E50: =TRIM(INDEX(WBS!$C$5:$C$144,MATCH($D50,WBS!$A$5:$A$144,0))) -> Architecture decisions | F50: =INDEX(WBS!$D$5:$D$144,MATCH($D50,WBS!$A$5:$A$144,0)) -> Design and Decide | G50: ="D"&INDEX(WBS!$F$5:$F$144,MATCH($D50,WBS!$A$5:$A$144,0))&"-D"&INDEX(WBS!$T$5:$T$144,MATCH($D50,WBS!$A$5:$A$144,0)) -> D4-D4 | H50: =COUNTIFS(WBS!$R$5:$R$144,$D50,WBS!$B$5:$B$144,3) -> 2 | I50: =COUNTIFS(WBS!$R$5:$R$144,$D50,WBS!$B$5:$B$144,3,WBS!$L$5:$L$144,"Done") -> 0 | J50: =INDEX(WBS!$M$5:$M$144,MATCH($D50,WBS!$A$5:$A$144,0)) -> 0
D51: 2.3 | E51: =TRIM(INDEX(WBS!$C$5:$C$144,MATCH($D51,WBS!$A$5:$A$144,0))) -> Security design | F51: =INDEX(WBS!$D$5:$D$144,MATCH($D51,WBS!$A$5:$A$144,0)) -> Design and Decide | G51: ="D"&INDEX(WBS!$F$5:$F$144,MATCH($D51,WBS!$A$5:$A$144,0))&"-D"&INDEX(WBS!$T$5:$T$144,MATCH($D51,WBS!$A$5:$A$144,0)) -> D5-D5 | H51: =COUNTIFS(WBS!$R$5:$R$144,$D51,WBS!$B$5:$B$144,3) -> 3 | I51: =COUNTIFS(WBS!$R$5:$R$144,$D51,WBS!$B$5:$B$144,3,WBS!$L$5:$L$144,"Done") -> 0 | J51: =INDEX(WBS!$M$5:$M$144,MATCH($D51,WBS!$A$5:$A$144,0)) -> 0
D52: 2.4 | E52: =TRIM(INDEX(WBS!$C$5:$C$144,MATCH($D52,WBS!$A$5:$A$144,0))) -> Design system | F52: =INDEX(WBS!$D$5:$D$144,MATCH($D52,WBS!$A$5:$A$144,0)) -> Design and Decide | G52: ="D"&INDEX(WBS!$F$5:$F$144,MATCH($D52,WBS!$A$5:$A$144,0))&"-D"&INDEX(WBS!$T$5:$T$144,MATCH($D52,WBS!$A$5:$A$144,0)) -> D5-D5 | H52: =COUNTIFS(WBS!$R$5:$R$144,$D52,WBS!$B$5:$B$144,3) -> 2 | I52: =COUNTIFS(WBS!$R$5:$R$144,$D52,WBS!$B$5:$B$144,3,WBS!$L$5:$L$144,"Done") -> 0 | J52: =INDEX(WBS!$M$5:$M$144,MATCH($D52,WBS!$A$5:$A$144,0)) -> 0
D53: 3.1 | E53: =TRIM(INDEX(WBS!$C$5:$C$144,MATCH($D53,WBS!$A$5:$A$144,0))) -> Solution foundation | F53: =INDEX(WBS!$D$5:$D$144,MATCH($D53,WBS!$A$5:$A$144,0)) -> Backend Spine | G53: ="D"&INDEX(WBS!$F$5:$F$144,MATCH($D53,WBS!$A$5:$A$144,0))&"-D"&INDEX(WBS!$T$5:$T$144,MATCH($D53,WBS!$A$5:$A$144,0)) -> D6-D6 | H53: =COUNTIFS(WBS!$R$5:$R$144,$D53,WBS!$B$5:$B$144,3) -> 3 | I53: =COUNTIFS(WBS!$R$5:$R$144,$D53,WBS!$B$5:$B$144,3,WBS!$L$5:$L$144,"Done") -> 0 | J53: =INDEX(WBS!$M$5:$M$144,MATCH($D53,WBS!$A$5:$A$144,0)) -> 0
D54: 3.2 | E54: =TRIM(INDEX(WBS!$C$5:$C$144,MATCH($D54,WBS!$A$5:$A$144,0))) -> Identity foundation | F54: =INDEX(WBS!$D$5:$D$144,MATCH($D54,WBS!$A$5:$A$144,0)) -> Backend Spine | G54: ="D"&INDEX(WBS!$F$5:$F$144,MATCH($D54,WBS!$A$5:$A$144,0))&"-D"&INDEX(WBS!$T$5:$T$144,MATCH($D54,WBS!$A$5:$A$144,0)) -> D6-D6 | H54: =COUNTIFS(WBS!$R$5:$R$144,$D54,WBS!$B$5:$B$144,3) -> 1 | I54: =COUNTIFS(WBS!$R$5:$R$144,$D54,WBS!$B$5:$B$144,3,WBS!$L$5:$L$144,"Done") -> 0 | J54: =INDEX(WBS!$M$5:$M$144,MATCH($D54,WBS!$A$5:$A$144,0)) -> 0
D55: 3.3 | E55: =TRIM(INDEX(WBS!$C$5:$C$144,MATCH($D55,WBS!$A$5:$A$144,0))) -> Network and Timetable module | F55: =INDEX(WBS!$D$5:$D$144,MATCH($D55,WBS!$A$5:$A$144,0)) -> Backend Spine | G55: ="D"&INDEX(WBS!$F$5:$F$144,MATCH($D55,WBS!$A$5:$A$144,0))&"-D"&INDEX(WBS!$T$5:$T$144,MATCH($D55,WBS!$A$5:$A$144,0)) -> D7-D7 | H55: =COUNTIFS(WBS!$R$5:$R$144,$D55,WBS!$B$5:$B$144,3) -> 3 | I55: =COUNTIFS(WBS!$R$5:$R$144,$D55,WBS!$B$5:$B$144,3,WBS!$L$5:$L$144,"Done") -> 0 | J55: =INDEX(WBS!$M$5:$M$144,MATCH($D55,WBS!$A$5:$A$144,0)) -> 0
... D79: 8.4 | E79: =TRIM(INDEX(WBS!$C$5:$C$144,MATCH($D79,WBS!$A$5:$A$144,0))) -> Closeout | F79: =INDEX(WBS!$D$5:$D$144,MATCH($D79,WBS!$A$5:$A$144,0)) -> Evidence and Demo | G79: ="D"&INDEX(WBS!$F$5:$F$144,MATCH($D79,WBS!$A$5:$A$144,0))&"-D"&INDEX(WBS!$T$5:$T$144,MATCH($D79,WBS!$A$5:$A$144,0)) -> D21-D21 | H79: =COUNTIFS(WBS!$R$5:$R$144,$D79,WBS!$B$5:$B$144,3) -> 3 | I79: =COUNTIFS(WBS!$R$5:$R$144,$D79,WBS!$B$5:$B$144,3,WBS!$L$5:$L$144,"Done") -> 0 | J79: =INDEX(WBS!$M$5:$M$144,MATCH($D79,WBS!$A$5:$A$144,0)) -> 0

Sheet WBS
A1: SmartRail — Work Breakdown Structure
A2: EDIT ONLY the blue columns: Day, Dur, Est h, Act h, Status, Notes. Everything black is a formula. Phase (level 1) and work-package (level 2) rows roll up automatically from their tasks.
A4: WBS | B4: Lvl | C4: Work item | D4: Phase | E4: WS | F4: Day | G4: Start | H4: End | I4: Dur | J4: Est h | K4: Act h | L4: Status | M4: % Done | N4: Gate | O4: Traces | P4: Definition of done | Q4: Notes / blocker | R4: _parent | S4: _root | T4: _endday | U4: _den | V4: _num | W4: _act | X4: _startday | Y4: _l3end
A5: 1 | B5: 1 | C5: Discovery | D5: Discovery | F5: =IFERROR(_xlfn.MINIFS($X$5:$X$144,$S$5:$S$144,$A5,$B$5:$B$144,3),"") -> 1 | G5: =IF($F5="","",Dashboard!$B$3+$F5-1) -> 46294 | H5: =IF($T5="","",Dashboard!$B$3+$T5-1) -> 46296 | I5: =IFERROR($T5-$F5+1,"") -> 3 | J5: =SUMIFS($U$5:$U$144,$S$5:$S$144,$A5,$B$5:$B$144,3) -> 28.5 | K5: =SUMIFS($W$5:$W$144,$S$5:$S$144,$A5,$B$5:$B$144,3) -> 0 | M5: =IFERROR(SUMIFS($V$5:$V$144,$S$5:$S$144,$A5,$B$5:$B$144,3)/SUMIFS($U$5:$U$144,$S$5:$S$144,$A5,$B$5:$B$144,3),0) -> 0.10526316 | T5: =IFERROR(_xlfn.MAXIFS($Y$5:$Y$144,$S$5:$S$144,$A5,$B$5:$B$144,3),"") -> 3
A6: 1.1 | B6: 2 | C6: Brief analysis and gap discovery | D6: Discovery | F6: =IFERROR(_xlfn.MINIFS($X$5:$X$144,$R$5:$R$144,$A6,$B$5:$B$144,3),"") -> 1 | G6: =IF($F6="","",Dashboard!$B$3+$F6-1) -> 46294 | H6: =IF($T6="","",Dashboard!$B$3+$T6-1) -> 46295 | I6: =IFERROR($T6-$F6+1,"") -> 2 | J6: =SUMIFS($U$5:$U$144,$R$5:$R$144,$A6,$B$5:$B$144,3) -> 6 | K6: =SUMIFS($W$5:$W$144,$R$5:$R$144,$A6,$B$5:$B$144,3) -> 0 | M6: =IFERROR(SUMIFS($V$5:$V$144,$R$5:$R$144,$A6,$B$5:$B$144,3)/SUMIFS($U$5:$U$144,$R$5:$R$144,$A6,$B$5:$B$144,3),0) -> 0 | R6: 1 | S6: 1 | T6: =IFERROR(_xlfn.MAXIFS($Y$5:$Y$144,$R$5:$R$144,$A6,$B$5:$B$144,3),"") -> 2
A7: 1.1.1 | B7: 3 | C7: Decompose brief into atomic statements tagged GIVEN / IMPLIED / ABSENT | D7: Discovery | E7: REQ | F7: 1 | G7: =IF($F7="","",Dashboard!$B$3+$F7-1) -> 46294 | H7: =IF($T7="","",Dashboard!$B$3+$T7-1) -> 46294 | I7: 1 | J7: 3 | L7: To do | M7: =IF($L7="Done",1,IF($L7="Doing",0.5,0)) -> 0 | O7: brief all sections | P7: One statement per brief sentence, each tagged | R7: 1.1 | S7: 1 | T7: =$F7+$I7-1 -> 1 | U7: =IF($L7="Deferred",0,$J7) -> 3 | V7: =IF($L7="Deferred",0,$J7*$M7) -> 0 | W7: =IF($L7="Deferred",0,N($K7)) -> 0 | X7: =$F7 -> 1 | Y7: =$T7 -> 1
A8: 1.1.2 | B8: 3 | C8: Convert plan section 6 findings into REQ / ASM / EDG / OQ entries | D8: Discovery | E8: REQ | F8: 2 | G8: =IF($F8="","",Dashboard!$B$3+$F8-1) -> 46295 | H8: =IF($T8="","",Dashboard!$B$3+$T8-1) -> 46295 | I8: 1 | J8: 2 | L8: To do | M8: =IF($L8="Done",1,IF($L8="Doing",0.5,0)) -> 0 | O8: plan.md S6 | P8: All 59 findings carry an id and a type | R8: 1.1 | S8: 1 | T8: =$F8+$I8-1 -> 2 | U8: =IF($L8="Deferred",0,$J8) -> 2 | V8: =IF($L8="Deferred",0,$J8*$M8) -> 0 | W8: =IF($L8="Deferred",0,N($K8)) -> 0 | X8: =$F8 -> 2 | Y8: =$T8 -> 2
A9: 1.1.3 | B9: 3 | C9: Assumptions register with rationale | D9: Discovery | E9: REQ | F9: 2 | G9: =IF($F9="","",Dashboard!$B$3+$F9-1) -> 46295 | H9: =IF($T9="","",Dashboard!$B$3+$T9-1) -> 46295 | I9: 1 | J9: 1 | L9: To do | M9: =IF($L9="Done",1,IF($L9="Doing",0.5,0)) -> 0 | P9: Every ASM states what breaks if it is wrong | R9: 1.1 | S9: 1 | T9: =$F9+$I9-1 -> 2 | U9: =IF($L9="Deferred",0,$J9) -> 1 | V9: =IF($L9="Deferred",0,$J9*$M9) -> 0 | W9: =IF($L9="Deferred",0,N($K9)) -> 0 | X9: =$F9 -> 2 | Y9: =$T9 -> 2
A10: 1.2 | B10: 2 | C10: Stakeholder simulation | D10: Discovery | F10: =IFERROR(_xlfn.MINIFS($X$5:$X$144,$R$5:$R$144,$A10,$B$5:$B$144,3),"") -> 1 | G10: =IF($F10="","",Dashboard!$B$3+$F10-1) -> 46294 | H10: =IF($T10="","",Dashboard!$B$3+$T10-1) -> 46296 | I10: =IFERROR($T10-$F10+1,"") -> 3 | J10: =SUMIFS($U$5:$U$144,$R$5:$R$144,$A10,$B$5:$B$144,3) -> 10 | K10: =SUMIFS($W$5:$W$144,$R$5:$R$144,$A10,$B$5:$B$144,3) -> 0 | M10: =IFERROR(SUMIFS($V$5:$V$144,$R$5:$R$144,$A10,$B$5:$B$144,3)/SUMIFS($U$5:$U$144,$R$5:$R$144,$A10,$B$5:$B$144,3),0) -> 0 | R10: 1 | S10: 1 | T10: =IFERROR(_xlfn.MAXIFS($Y$5:$Y$144,$R$5:$R$144,$A10,$B$5:$B$144,3),"") -> 3
A11: 1.2.1 | B11: 3 | C11: Persona interviews 1-6 commuter, traveller, impaired passenger, driver, station manager, controller | D11: Discovery | E11: REQ | F11: 1 | G11: =IF($F11="","",Dashboard!$B$3+$F11-1) -> 46294 | H11: =IF($T11="","",Dashboard!$B$3+$T11-1) -> 46294 | I11: 1 | J11: 3 | L11: To do | M11: =IF($L11="Done",1,IF($L11="Doing",0.5,0)) -> 0 | P11: Transcript plus extracted requirements per persona | R11: 1.2 | S11: 1 | T11: =$F11+$I11-1 -> 1 | U11: =IF($L11="Deferred",0,$J11) -> 3 | V11: =IF($L11="Deferred",0,$J11*$M11) -> 0 | W11: =IF($L11="Deferred",0,N($K11)) -> 0 | X11: =$F11 -> 1 | Y11: =$T11 -> 1
A12: 1.2.2 | B12: 3 | C12: Persona interviews 7-12 CS agent, catering ops, security, QA, accessibility, DPO | D12: Discovery | E12: REQ | F12: 2 | G12: =IF($F12="","",Dashboard!$B$3+$F12-1) -> 46295 | H12: =IF($T12="","",Dashboard!$B$3+$T12-1) -> 46295 | I12: 1 | J12: 3 | L12: To do | M12: =IF($L12="Done",1,IF($L12="Doing",0.5,0)) -> 0 | P12: Transcript plus extracted requirements per persona | R12: 1.2 | S12: 1 | T12: =$F12+$I12-1 -> 2 | U12: =IF($L12="Deferred",0,$J12) -> 3 | V12: =IF($L12="Deferred",0,$J12*$M12) -> 0 | W12: =IF($L12="Deferred",0,N($K12)) -> 0 | X12: =$F12 -> 2 | Y12: =$T12 -> 2
A13: 1.2.3 | B13: 3 | C13: Adversarial pass - what would make each persona distrust the system | D13: Discovery | E13: REQ | F13: 2 | G13: =IF($F13="","",Dashboard!$B$3+$F13-1) -> 46295 | H13: =IF($T13="","",Dashboard!$B$3+$T13-1) -> 46295 | I13: 1 | J13: 2 | L13: To do | M13: =IF($L13="Done",1,IF($L13="Doing",0.5,0)) -> 0 | P13: Failure requirements captured as EDG entries | R13: 1.2 | S13: 1 | T13: =$F13+$I13-1 -> 2 | U13: =IF($L13="Deferred",0,$J13) -> 2 | V13: =IF($L13="Deferred",0,$J13*$M13) -> 0 | W13: =IF($L13="Deferred",0,N($K13)) -> 0 | X13: =$F13 -> 2 | Y13: =$T13 -> 2
A14: 1.2.4 | B14: 3 | C14: Reconcile conflicts and record the losing option in writing | D14: Discovery | E14: REQ | F14: 3 | G14: =IF($F14="","",Dashboard!$B$3+$F14-1) -> 46296 | H14: =IF($T14="","",Dashboard!$B$3+$T14-1) -> 46296 | I14: 1 | J14: 2 | L14: To do | M14: =IF($L14="Done",1,IF($L14="Doing",0.5,0)) -> 0 | P14: No averaged requirements - conflicts resolved by me, both sides recorded | R14: 1.2 | S14: 1 | T14: =$F14+$I14-1 -> 3 | U14: =IF($L14="Deferred",0,$J14) -> 2 | V14: =IF($L14="Deferred",0,$J14*$M14) -> 0 | W14: =IF($L14="Deferred",0,N($K14)) -> 0 | X14: =$F14 -> 3 | Y14: =$T14 -> 3
A15: 1.3 | B15: 2 | C15: Requirement engineering | D15: Discovery | F15: =IFERROR(_xlfn.MINIFS($X$5:$X$144,$R$5:$R$144,$A15,$B$5:$B$144,3),"") -> 2 | G15: =IF($F15="","",Dashboard!$B$3+$F15-1) -> 46295 | H15: =IF($T15="","",Dashboard!$B$3+$T15-1) -> 46296 | I15: =IFERROR($T15-$F15+1,"") -> 2 | J15: =SUMIFS($U$5:$U$144,$R$5:$R$144,$A15,$B$5:$B$144,3) -> 7.5 | K15: =SUMIFS($W$5:$W$144,$R$5:$R$144,$A15,$B$5:$B$144,3) -> 0 | M15: =IFERROR(SUMIFS($V$5:$V$144,$R$5:$R$144,$A15,$B$5:$B$144,3)/SUMIFS($U$5:$U$144,$R$5:$R$144,$A15,$B$5:$B$144,3),0) -> 0 | R15: 1 | S15: 1 | T15: =IFERROR(_xlfn.MAXIFS($Y$5:$Y$144,$R$5:$R$144,$A15,$B$5:$B$144,3),"") -> 3
A16: 1.3.1 | B16: 3 | C16: Edge case catalogue target 40 plus entries | D16: Discovery | E16: REQ | F16: 2 | G16: =IF($F16="","",Dashboard!$B$3+$F16-1) -> 46295 | H16: =IF($T16="","",Dashboard!$B$3+$T16-1) -> 46295 | I16: 1 | J16: 2 | L16: To do | M16: =IF($L16="Done",1,IF($L16="Doing",0.5,0)) -> 0 | P16: EDG ids assigned | R16: 1.3 | S16: 1 | T16: =$F16+$I16-1 -> 2 | U16: =IF($L16="Deferred",0,$J16) -> 2 | V16: =IF($L16="Deferred",0,$J16*$M16) -> 0 | W16: =IF($L16="Deferred",0,N($K16)) -> 0 | X16: =$F16 -> 2 | Y16: =$T16 -> 2
A17: 1.3.2 | B17: 3 | C17: Prioritise MoSCoW plus risk times value score | D17: Discovery | E17: REQ | F17: 3 | G17: =IF($F17="","",Dashboard!$B$3+$F17-1) -> 46296 | H17: =IF($T17="","",Dashboard!$B$3+$T17-1) -> 46296 | I17: 1 | J17: 1.5 | L17: To do | M17: =IF($L17="Done",1,IF($L17="Doing",0.5,0)) -> 0 | P17: Every Must maps to one of the five E2E flows | R17: 1.3 | S17: 1 | T17: =$F17+$I17-1 -> 3 | U17: =IF($L17="Deferred",0,$J17) -> 1.5 | V17: =IF($L17="Deferred",0,$J17*$M17) -> 0 | W17: =IF($L17="Deferred",0,N($K17)) -> 0 | X17: =$F17 -> 3 | Y17: =$T17 -> 3
A18: 1.3.3 | B18: 3 | C18: User stories and acceptance criteria for all Must items | D18: Discovery | E18: REQ | F18: 3 | G18: =IF($F18="","",Dashboard!$B$3+$F18-1) -> 46296 | H18: =IF($T18="","",Dashboard!$B$3+$T18-1) -> 46296 | I18: 1 | J18: 3 | L18: To do | M18: =IF($L18="Done",1,IF($L18="Doing",0.5,0)) -> 0 | P18: Given/When/Then for each AC | R18: 1.3 | S18: 1 | T18: =$F18+$I18-1 -> 3 | U18: =IF($L18="Deferred",0,$J18) -> 3 | V18: =IF($L18="Deferred",0,$J18*$M18) -> 0 | W18: =IF($L18="Deferred",0,N($K18)) -> 0 | X18: =$F18 -> 3 | Y18: =$T18 -> 3
A19: 1.3.4 | B19: 3 | C19: Traceability matrix skeleton REQ to US to AC to test | D19: Discovery | E19: REQ | F19: 3 | G19: =IF($F19="","",Dashboard!$B$3+$F19-1) -> 46296 | H19: =IF($T19="","",Dashboard!$B$3+$T19-1) -> 46296 | I19: 1 | J19: 1 | L19: To do | M19: =IF($L19="Done",1,IF($L19="Doing",0.5,0)) -> 0 | P19: One row per requirement, test column present but empty | R19: 1.3 | S19: 1 | T19: =$F19+$I19-1 -> 3 | U19: =IF($L19="Deferred",0,$J19) -> 1 | V19: =IF($L19="Deferred",0,$J19*$M19) -> 0 | W19: =IF($L19="Deferred",0,N($K19)) -> 0 | X19: =$F19 -> 3 | Y19: =$T19 -> 3
A20: 1.4 | B20: 2 | C20: Scope control | D20: Discovery | F20: =IFERROR(_xlfn.MINIFS($X$5:$X$144,$R$5:$R$144,$A20,$B$5:$B$144,3),"") -> 3 | G20: =IF($F20="","",Dashboard!$B$3+$F20-1) -> 46296 | H20: =IF($T20="","",Dashboard!$B$3+$T20-1) -> 46296 | I20: =IFERROR($T20-$F20+1,"") -> 1 | J20: =SUMIFS($U$5:$U$144,$R$5:$R$144,$A20,$B$5:$B$144,3) -> 1 | K20: =SUMIFS($W$5:$W$144,$R$5:$R$144,$A20,$B$5:$B$144,3) -> 0 | M20: =IFERROR(SUMIFS($V$5:$V$144,$R$5:$R$144,$A20,$B$5:$B$144,3)/SUMIFS($U$5:$U$144,$R$5:$R$144,$A20,$B$5:$B$144,3),0) -> 0 | R20: 1 | S20: 1 | T20: =IFERROR(_xlfn.MAXIFS($Y$5:$Y$144,$R$5:$R$144,$A20,$B$5:$B$144,3),"") -> 3
A21: 1.4.1 | B21: 3 | C21: Send open questions OQ-01 to OQ-08 to assessors | D21: Discovery | E21: REQ | F21: 3 | G21: =IF($F21="","",Dashboard!$B$3+$F21-1) -> 46296 | H21: =IF($T21="","",Dashboard!$B$3+$T21-1) -> 46296 | I21: 1 | J21: 0.5 | L21: To do | M21: =IF($L21="Done",1,IF($L21="Doing",0.5,0)) -> 0 | O21: plan.md S20 | P21: Sent, with fallback assumption recorded for each | R21: 1.4 | S21: 1 | T21: =$F21+$I21-1 -> 3 | U21: =IF($L21="Deferred",0,$J21) -> 0.5 | V21: =IF($L21="Deferred",0,$J21*$M21) -> 0 | W21: =IF($L21="Deferred",0,N($K21)) -> 0 | X21: =$F21 -> 3 | Y21: =$T21 -> 3
A22: 1.4.2 | B22: 3 | C22: Baseline scope and freeze requirements | D22: Discovery | E22: REQ | F22: 3 | G22: =IF($F22="","",Dashboard!$B$3+$F22-1) -> 46296 | H22: =IF($T22="","",Dashboard!$B$3+$T22-1) -> 46296 | I22: 1 | J22: 0.5 | L22: To do | M22: =IF($L22="Done",1,IF($L22="Doing",0.5,0)) -> 0 | N22: G1 | P22: Scope signed off by me, change log opened | R22: 1.4 | S22: 1 | T22: =$F22+$I22-1 -> 3 | U22: =IF($L22="Deferred",0,$J22) -> 0.5 | V22: =IF($L22="Deferred",0,$J22*$M22) -> 0 | W22: =IF($L22="Deferred",0,N($K22)) -> 0 | X22: =$F22 -> 3 | Y22: =$T22 -> 3
A23: 1.5 | B23: 2 | C23: Project setup | D23: Discovery | F23: =IFERROR(_xlfn.MINIFS($X$5:$X$144,$R$5:$R$144,$A23,$B$5:$B$144,3),"") -> 1 | G23: =IF($F23="","",Dashboard!$B$3+$F23-1) -> 46294 | H23: =IF($T23="","",Dashboard!$B$3+$T23-1) -> 46294 | I23: =IFERROR($T23-$F23+1,"") -> 1 | J23: =SUMIFS($U$5:$U$144,$R$5:$R$144,$A23,$B$5:$B$144,3) -> 4 | K23: =SUMIFS($W$5:$W$144,$R$5:$R$144,$A23,$B$5:$B$144,3) -> 0 | M23: =IFERROR(SUMIFS($V$5:$V$144,$R$5:$R$144,$A23,$B$5:$B$144,3)/SUMIFS($U$5:$U$144,$R$5:$R$144,$A23,$B$5:$B$144,3),0) -> 0.75 | R23: 1 | S23: 1 | T23: =IFERROR(_xlfn.MAXIFS($Y$5:$Y$144,$R$5:$R$144,$A23,$B$5:$B$144,3),"") -> 1
A24: 1.5.1 | B24: 3 | C24: Author master delivery plan | D24: Discovery | E24: DOC | F24: 1 | G24: =IF($F24="","",Dashboard!$B$3+$F24-1) -> 46294 | H24: =IF($T24="","",Dashboard!$B$3+$T24-1) -> 46294 | I24: 1 | J24: 2 | L24: Done | M24: =IF($L24="Done",1,IF($L24="Doing",0.5,0)) -> 1 | O24: plan.md | P24: Stack decided, scope fixed, 59 gaps registered | R24: 1.5 | S24: 1 | T24: =$F24+$I24-1 -> 1 | U24: =IF($L24="Deferred",0,$J24) -> 2 | V24: =IF($L24="Deferred",0,$J24*$M24) -> 2 | W24: =IF($L24="Deferred",0,N($K24)) -> 0 | X24: =$F24 -> 1 | Y24: =$T24 -> 1
A25: 1.5.2 | B25: 3 | C25: Create repo and docs folder skeleton | D25: Discovery | E25: ARCH | F25: 1 | G25: =IF($F25="","",Dashboard!$B$3+$F25-1) -> 46294 | H25: =IF($T25="","",Dashboard!$B$3+$T25-1) -> 46294 | I25: 1 | J25: 1 | L25: To do | M25: =IF($L25="Done",1,IF($L25="Doing",0.5,0)) -> 0 | P25: docs/00 to 06 present, git initialised | R25: 1.5 | S25: 1 | T25: =$F25+$I25-1 -> 1 | U25: =IF($L25="Deferred",0,$J25) -> 1 | V25: =IF($L25="Deferred",0,$J25*$M25) -> 0 | W25: =IF($L25="Deferred",0,N($K25)) -> 0 | X25: =$F25 -> 1 | Y25: =$T25 -> 1
A26: 1.5.3 | B26: 3 | C26: Set up tracking workbook and git commit template | D26: Discovery | E26: DOC | F26: 1 | G26: =IF($F26="","",Dashboard!$B$3+$F26-1) -> 46294 | H26: =IF($T26="","",Dashboard!$B$3+$T26-1) -> 46294 | I26: 1 | J26: 1 | L26: Done | M26: =IF($L26="Done",1,IF($L26="Doing",0.5,0)) -> 1 | P26: Workbook live, commit.template configured | R26: 1.5 | S26: 1 | T26: =$F26+$I26-1 -> 1 | U26: =IF($L26="Deferred",0,$J26) -> 1 | V26: =IF($L26="Deferred",0,$J26*$M26) -> 1 | W26: =IF($L26="Deferred",0,N($K26)) -> 0 | X26: =$F26 -> 1 | Y26: =$T26 -> 1
A27: 2 | B27: 1 | C27: Design and Decide | D27: Design and Decide | F27: =IFERROR(_xlfn.MINIFS($X$5:$X$144,$S$5:$S$144,$A27,$B$5:$B$144,3),"") -> 4 | G27: =IF($F27="","",Dashboard!$B$3+$F27-1) -> 46297 | H27: =IF($T27="","",Dashboard!$B$3+$T27-1) -> 46298 | I27: =IFERROR($T27-$F27+1,"") -> 2 | J27: =SUMIFS($U$5:$U$144,$S$5:$S$144,$A27,$B$5:$B$144,3) -> 16 | K27: =SUMIFS($W$5:$W$144,$S$5:$S$144,$A27,$B$5:$B$144,3) -> 0 | M27: =IFERROR(SUMIFS($V$5:$V$144,$S$5:$S$144,$A27,$B$5:$B$144,3)/SUMIFS($U$5:$U$144,$S$5:$S$144,$A27,$B$5:$B$144,3),0) -> 0 | T27: =IFERROR(_xlfn.MAXIFS($Y$5:$Y$144,$S$5:$S$144,$A27,$B$5:$B$144,3),"") -> 5
A28: 2.1 | B28: 2 | C28: Domain design | D28: Design and Decide | F28: =IFERROR(_xlfn.MINIFS($X$5:$X$144,$R$5:$R$144,$A28,$B$5:$B$144,3),"") -> 4 | G28: =IF($F28="","",Dashboard!$B$3+$F28-1) -> 46297 | H28: =IF($T28="","",Dashboard!$B$3+$T28-1) -> 46297 | I28: =IFERROR($T28-$F28+1,"") -> 1 | J28: =SUMIFS($U$5:$U$144,$R$5:$R$144,$A28,$B$5:$B$144,3) -> 5 | K28: =SUMIFS($W$5:$W$144,$R$5:$R$144,$A28,$B$5:$B$144,3) -> 0 | M28: =IFERROR(SUMIFS($V$5:$V$144,$R$5:$R$144,$A28,$B$5:$B$144,3)/SUMIFS($U$5:$U$144,$R$5:$R$144,$A28,$B$5:$B$144,3),0) -> 0 | R28: 2 | S28: 2 | T28: =IFERROR(_xlfn.MAXIFS($Y$5:$Y$144,$R$5:$R$144,$A28,$B$5:$B$144,3),"") -> 4
A29: 2.1.1 | B29: 3 | C29: Domain model - network, timetable versions, service calendars | D29: Design and Decide | E29: ARCH | F29: 4 | G29: =IF($F29="","",Dashboard!$B$3+$F29-1) -> 46297 | H29: =IF($T29="","",Dashboard!$B$3+$T29-1) -> 46297 | I29: 1 | J29: 3 | L29: To do | M29: =IF($L29="Done",1,IF($L29="Doing",0.5,0)) -> 0 | P29: Service date separated from calendar date | R29: 2.1 | S29: 2 | T29: =$F29+$I29-1 -> 4 | U29: =IF($L29="Deferred",0,$J29) -> 3 | V29: =IF($L29="Deferred",0,$J29*$M29) -> 0 | W29: =IF($L29="Deferred",0,N($K29)) -> 0 | X29: =$F29 -> 4 | Y29: =$T29 -> 4
A30: 2.1.2 | B30: 3 | C30: Journey state machine including Unknown and TerminatedShort | D30: Design and Decide | E30: ARCH | F30: 4 | G30: =IF($F30="","",Dashboard!$B$3+$F30-1) -> 46297 | H30: =IF($T30="","",Dashboard!$B$3+$T30-1) -> 46297 | I30: 1 | J30: 2 | L30: To do | M30: =IF($L30="Done",1,IF($L30="Doing",0.5,0)) -> 0 | P30: Diagram plus the invariant list that becomes unit tests | R30: 2.1 | S30: 2 | T30: =$F30+$I30-1 -> 4 | U30: =IF($L30="Deferred",0,$J30) -> 2 | V30: =IF($L30="Deferred",0,$J30*$M30) -> 0 | W30: =IF($L30="Deferred",0,N($K30)) -> 0 | X30: =$F30 -> 4 | Y30: =$T30 -> 4
A31: 2.2 | B31: 2 | C31: Architecture decisions | D31: Design and Decide | F31: =IFERROR(_xlfn.MINIFS($X$5:$X$144,$R$5:$R$144,$A31,$B$5:$B$144,3),"") -> 4 | G31: =IF($F31="","",Dashboard!$B$3+$F31-1) -> 46297 | H31: =IF($T31="","",Dashboard!$B$3+$T31-1) -> 46297 | I31: =IFERROR($T31-$F31+1,"") -> 1 | J31: =SUMIFS($U$5:$U$144,$R$5:$R$144,$A31,$B$5:$B$144,3) -> 3 | K31: =SUMIFS($W$5:$W$144,$R$5:$R$144,$A31,$B$5:$B$144,3) -> 0 | M31: =IFERROR(SUMIFS($V$5:$V$144,$R$5:$R$144,$A31,$B$5:$B$144,3)/SUMIFS($U$5:$U$144,$R$5:$R$144,$A31,$B$5:$B$144,3),0) -> 0 | R31: 2 | S31: 2 | T31: =IFERROR(_xlfn.MAXIFS($Y$5:$Y$144,$R$5:$R$144,$A31,$B$5:$B$144,3),"") -> 4
A32: 2.2.1 | B32: 3 | C32: Write ADR 0001 to 0008 | D32: Design and Decide | E32: ARCH | F32: 4 | G32: =IF($F32="","",Dashboard!$B$3+$F32-1) -> 46297 | H32: =IF($T32="","",Dashboard!$B$3+$T32-1) -> 46297 | I32: 1 | J32: 2 | L32: To do | M32: =IF($L32="Done",1,IF($L32="Doing",0.5,0)) -> 0 | P32: Each ADR names the rejected option and why | R32: 2.2 | S32: 2 | T32: =$F32+$I32-1 -> 4 | U32: =IF($L32="Deferred",0,$J32) -> 2 | V32: =IF($L32="Deferred",0,$J32*$M32) -> 0 | W32: =IF($L32="Deferred",0,N($K32)) -> 0 | X32: =$F32 -> 4 | Y32: =$T32 -> 4
A33: 2.2.2 | B33: 3 | C33: C4 context and container diagrams | D33: Design and Decide | E33: ARCH | F33: 4 | G33: =IF($F33="","",Dashboard!$B$3+$F33-1) -> 46297 | H33: =IF($T33="","",Dashboard!$B$3+$T33-1) -> 46297 | I33: 1 | J33: 1 | L33: To do | M33: =IF($L33="Done",1,IF($L33="Doing",0.5,0)) -> 0 | P33: Two levels, committed as source | R33: 2.2 | S33: 2 | T33: =$F33+$I33-1 -> 4 | U33: =IF($L33="Deferred",0,$J33) -> 1 | V33: =IF($L33="Deferred",0,$J33*$M33) -> 0 | W33: =IF($L33="Deferred",0,N($K33)) -> 0 | X33: =$F33 -> 4 | Y33: =$T33 -> 4
A34: 2.3 | B34: 2 | C34: Security design | D34: Design and Decide | F34: =IFERROR(_xlfn.MINIFS($X$5:$X$144,$R$5:$R$144,$A34,$B$5:$B$144,3),"") -> 5 | G34: =IF($F34="","",Dashboard!$B$3+$F34-1) -> 46298 | H34: =IF($T34="","",Dashboard!$B$3+$T34-1) -> 46298 | I34: =IFERROR($T34-$F34+1,"") -> 1 | J34: =SUMIFS($U$5:$U$144,$R$5:$R$144,$A34,$B$5:$B$144,3) -> 5 | K34: =SUMIFS($W$5:$W$144,$R$5:$R$144,$A34,$B$5:$B$144,3) -> 0 | M34: =IFERROR(SUMIFS($V$5:$V$144,$R$5:$R$144,$A34,$B$5:$B$144,3)/SUMIFS($U$5:$U$144,$R$5:$R$144,$A34,$B$5:$B$144,3),0) -> 0 | R34: 2 | S34: 2 | T34: =IFERROR(_xlfn.MAXIFS($Y$5:$Y$144,$R$5:$R$144,$A34,$B$5:$B$144,3),"") -> 5
A35: 2.3.1 | B35: 3 | C35: STRIDE threat model per trust boundary | D35: Design and Decide | E35: SEC | F35: 5 | G35: =IF($F35="","",Dashboard!$B$3+$F35-1) -> 46298 | H35: =IF($T35="","",Dashboard!$B$3+$T35-1) -> 46298 | I35: 1 | J35: 2.5 | L35: To do | M35: =IF($L35="Done",1,IF($L35="Doing",0.5,0)) -> 0 | P35: Five boundaries covered, each risk mapped to a control | R35: 2.3 | S35: 2 | T35: =$F35+$I35-1 -> 5 | U35: =IF($L35="Deferred",0,$J35) -> 2.5 | V35: =IF($L35="Deferred",0,$J35*$M35) -> 0 | W35: =IF($L35="Deferred",0,N($K35)) -> 0 | X35: =$F35 -> 5 | Y35: =$T35 -> 5
A36: 2.3.2 | B36: 3 | C36: Permission matrix for ten roles with scoped permissions | D36: Design and Decide | E36: SEC | F36: 5 | G36: =IF($F36="","",Dashboard!$B$3+$F36-1) -> 46298 | H36: =IF($T36="","",Dashboard!$B$3+$T36-1) -> 46298 | I36: 1 | J36: 1.5 | L36: To do | M36: =IF($L36="Done",1,IF($L36="Doing",0.5,0)) -> 0 | P36: Every cell has a planned positive and negative test | R36: 2.3 | S36: 2 | T36: =$F36+$I36-1 -> 5 | U36: =IF($L36="Deferred",0,$J36) -> 1.5 | V36: =IF($L36="Deferred",0,$J36*$M36) -> 0 | W36: =IF($L36="Deferred",0,N($K36)) -> 0 | X36: =$F36 -> 5 | Y36: =$T36 -> 5
A37: 2.3.3 | B37: 3 | C37: Data classification and retention schedule | D37: Design and Decide | E37: SEC | F37: 5 | G37: =IF($F37="","",Dashboard!$B$3+$F37-1) -> 46298 | H37: =IF($T37="","",Dashboard!$B$3+$T37-1) -> 46298 | I37: 1 | J37: 1 | L37: To do | M37: =IF($L37="Done",1,IF($L37="Doing",0.5,0)) -> 0 | P37: Four classes, owner, retention and log-redaction rule each | R37: 2.3 | S37: 2 | T37: =$F37+$I37-1 -> 5 | U37: =IF($L37="Deferred",0,$J37) -> 1 | V37: =IF($L37="Deferred",0,$J37*$M37) -> 0 | W37: =IF($L37="Deferred",0,N($K37)) -> 0 | X37: =$F37 -> 5 | Y37: =$T37 -> 5
A38: 2.4 | B38: 2 | C38: Design system | D38: Design and Decide | F38: =IFERROR(_xlfn.MINIFS($X$5:$X$144,$R$5:$R$144,$A38,$B$5:$B$144,3),"") -> 5 | G38: =IF($F38="","",Dashboard!$B$3+$F38-1) -> 46298 | H38: =IF($T38="","",Dashboard!$B$3+$T38-1) -> 46298 | I38: =IFERROR($T38-$F38+1,"") -> 1 | J38: =SUMIFS($U$5:$U$144,$R$5:$R$144,$A38,$B$5:$B$144,3) -> 3 | K38: =SUMIFS($W$5:$W$144,$R$5:$R$144,$A38,$B$5:$B$144,3) -> 0 | M38: =IFERROR(SUMIFS($V$5:$V$144,$R$5:$R$144,$A38,$B$5:$B$144,3)/SUMIFS($U$5:$U$144,$R$5:$R$144,$A38,$B$5:$B$144,3),0) -> 0 | R38: 2 | S38: 2 | T38: =IFERROR(_xlfn.MAXIFS($Y$5:$Y$144,$R$5:$R$144,$A38,$B$5:$B$144,3),"") -> 5
A39: 2.4.1 | B39: 3 | C39: Design tokens v1 - colour, status semantics, three type scales | D39: Design and Decide | E39: UX | F39: 5 | G39: =IF($F39="","",Dashboard!$B$3+$F39-1) -> 46298 | H39: =IF($T39="","",Dashboard!$B$3+$T39-1) -> 46298 | I39: 1 | J39: 2 | L39: To do | M39: =IF($L39="Done",1,IF($L39="Doing",0.5,0)) -> 0 | P39: Status never colour-only; contrast verified | R39: 2.4 | S39: 2 | T39: =$F39+$I39-1 -> 5 | U39: =IF($L39="Deferred",0,$J39) -> 2 | V39: =IF($L39="Deferred",0,$J39*$M39) -> 0 | W39: =IF($L39="Deferred",0,N($K39)) -> 0 | X39: =$F39 -> 5 | Y39: =$T39 -> 5
A40: 2.4.2 | B40: 3 | C40: Wireframe the six demo-critical screens | D40: Design and Decide | E40: UX | F40: 5 | G40: =IF($F40="","",Dashboard!$B$3+$F40-1) -> 46298 | H40: =IF($T40="","",Dashboard!$B$3+$T40-1) -> 46298 | I40: 1 | J40: 1 | L40: To do | M40: =IF($L40="Done",1,IF($L40="Doing",0.5,0)) -> 0 | P40: Includes stale and offline states | R40: 2.4 | S40: 2 | T40: =$F40+$I40-1 -> 5 | U40: =IF($L40="Deferred",0,$J40) -> 1 | V40: =IF($L40="Deferred",0,$J40*$M40) -> 0 | W40: =IF($L40="Deferred",0,N($K40)) -> 0 | X40: =$F40 -> 5 | Y40: =$T40 -> 5
A41: 3 | B41: 1 | C41: Backend Spine | D41: Backend Spine | F41: =IFERROR(_xlfn.MINIFS($X$5:$X$144,$S$5:$S$144,$A41,$B$5:$B$144,3),"") -> 6 | G41: =IF($F41="","",Dashboard!$B$3+$F41-1) -> 46299 | H41: =IF($T41="","",Dashboard!$B$3+$T41-1) -> 46300 | I41: =IFERROR($T41-$F41+1,"") -> 2 | J41: =SUMIFS($U$5:$U$144,$S$5:$S$144,$A41,$B$5:$B$144,3) -> 17 | K41: =SUMIFS($W$5:$W$144,$S$5:$S$144,$A41,$B$5:$B$144,3) -> 0 | M41: =IFERROR(SUMIFS($V$5:$V$144,$S$5:$S$144,$A41,$B$5:$B$144,3)/SUMIFS($U$5:$U$144,$S$5:$S$144,$A41,$B$5:$B$144,3),0) -> 0 | T41: =IFERROR(_xlfn.MAXIFS($Y$5:$Y$144,$S$5:$S$144,$A41,$B$5:$B$144,3),"") -> 7
A42: 3.1 | B42: 2 | C42: Solution foundation | D42: Backend Spine | F42: =IFERROR(_xlfn.MINIFS($X$5:$X$144,$R$5:$R$144,$A42,$B$5:$B$144,3),"") -> 6 | G42: =IF($F42="","",Dashboard!$B$3+$F42-1) -> 46299 | H42: =IF($T42="","",Dashboard!$B$3+$T42-1) -> 46299 | I42: =IFERROR($T42-$F42+1,"") -> 1 | J42: =SUMIFS($U$5:$U$144,$R$5:$R$144,$A42,$B$5:$B$144,3) -> 5 | K42: =SUMIFS($W$5:$W$144,$R$5:$R$144,$A42,$B$5:$B$144,3) -> 0 | M42: =IFERROR(SUMIFS($V$5:$V$144,$R$5:$R$144,$A42,$B$5:$B$144,3)/SUMIFS($U$5:$U$144,$R$5:$R$144,$A42,$B$5:$B$144,3),0) -> 0 | R42: 3 | S42: 3 | T42: =IFERROR(_xlfn.MAXIFS($Y$5:$Y$144,$R$5:$R$144,$A42,$B$5:$B$144,3),"") -> 6
A43: 3.1.1 | B43: 3 | C43: Scaffold .NET solution Domain, Application, Infrastructure, Api | D43: Backend Spine | E43: BE | F43: 6 | G43: =IF($F43="","",Dashboard!$B$3+$F43-1) -> 46299 | H43: =IF($T43="","",Dashboard!$B$3+$T43-1) -> 46299 | I43: 1 | J43: 1.5 | L43: To do | M43: =IF($L43="Done",1,IF($L43="Doing",0.5,0)) -> 0 | P43: Domain has zero framework references | R43: 3.1 | S43: 3 | T43: =$F43+$I43-1 -> 6 | U43: =IF($L43="Deferred",0,$J43) -> 1.5 | V43: =IF($L43="Deferred",0,$J43*$M43) -> 0 | W43: =IF($L43="Deferred",0,N($K43)) -> 0 | X43: =$F43 -> 6 | Y43: =$T43 -> 6
A44: 3.1.2 | B44: 3 | C44: EF Core model and first migration | D44: Backend Spine | E44: BE | F44: 6 | G44: =IF($F44="","",Dashboard!$B$3+$F44-1) -> 46299 | H44: =IF($T44="","",Dashboard!$B$3+$T44-1) -> 46299 | I44: 1 | J44: 2 | L44: To do | M44: =IF($L44="Done",1,IF($L44="Doing",0.5,0)) -> 0 | P44: Migration applies clean | R44: 3.1 | S44: 3 | T44: =$F44+$I44-1 -> 6 | U44: =IF($L44="Deferred",0,$J44) -> 2 | V44: =IF($L44="Deferred",0,$J44*$M44) -> 0 | W44: =IF($L44="Deferred",0,N($K44)) -> 0 | X44: =$F44 -> 6 | Y44: =$T44 -> 6
A45: 3.1.3 | B45: 3 | C45: Seed network - 12 stations, 6 routes, 40 services | D45: Backend Spine | E45: BE | F45: 6 | G45: =IF($F45="","",Dashboard!$B$3+$F45-1) -> 46299 | H45: =IF($T45="","",Dashboard!$B$3+$T45-1) -> 46299 | I45: 1 | J45: 1.5 | L45: To do | M45: =IF($L45="Done",1,IF($L45="Doing",0.5,0)) -> 0 | P45: Deterministic seed, re-runnable | R45: 3.1 | S45: 3 | T45: =$F45+$I45-1 -> 6 | U45: =IF($L45="Deferred",0,$J45) -> 1.5 | V45: =IF($L45="Deferred",0,$J45*$M45) -> 0 | W45: =IF($L45="Deferred",0,N($K45)) -> 0 | X45: =$F45 -> 6 | Y45: =$T45 -> 6
A46: 3.2 | B46: 2 | C46: Identity foundation | D46: Backend Spine | F46: =IFERROR(_xlfn.MINIFS($X$5:$X$144,$R$5:$R$144,$A46,$B$5:$B$144,3),"") -> 6 | G46: =IF($F46="","",Dashboard!$B$3+$F46-1) -> 46299 | H46: =IF($T46="","",Dashboard!$B$3+$T46-1) -> 46299 | I46: =IFERROR($T46-$F46+1,"") -> 1 | J46: =SUMIFS($U$5:$U$144,$R$5:$R$144,$A46,$B$5:$B$144,3) -> 1.5 | K46: =SUMIFS($W$5:$W$144,$R$5:$R$144,$A46,$B$5:$B$144,3) -> 0 | M46: =IFERROR(SUMIFS($V$5:$V$144,$R$5:$R$144,$A46,$B$5:$B$144,3)/SUMIFS($U$5:$U$144,$R$5:$R$144,$A46,$B$5:$B$144,3),0) -> 0 | R46: 3 | S46: 3 | T46: =IFERROR(_xlfn.MAXIFS($Y$5:$Y$144,$R$5:$R$144,$A46,$B$5:$B$144,3),"") -> 6
A47: 3.2.1 | B47: 3 | C47: JWT per-audience tokens and permission claims | D47: Backend Spine | E47: BE | F47: 6 | G47: =IF($F47="","",Dashboard!$B$3+$F47-1) -> 46299 | H47: =IF($T47="","",Dashboard!$B$3+$T47-1) -> 46299 | I47: 1 | J47: 1.5 | L47: To do | M47: =IF($L47="Done",1,IF($L47="Doing",0.5,0)) -> 0 | P47: Four auth postures demonstrable | R47: 3.2 | S47: 3 | T47: =$F47+$I47-1 -> 6 | U47: =IF($L47="Deferred",0,$J47) -> 1.5 | V47: =IF($L47="Deferred",0,$J47*$M47) -> 0 | W47: =IF($L47="Deferred",0,N($K47)) -> 0 | X47: =$F47 -> 6 | Y47: =$T47 -> 6
A48: 3.3 | B48: 2 | C48: Network and Timetable module | D48: Backend Spine | F48: =IFERROR(_xlfn.MINIFS($X$5:$X$144,$R$5:$R$144,$A48,$B$5:$B$144,3),"") -> 7 | G48: =IF($F48="","",Dashboard!$B$3+$F48-1) -> 46300 | H48: =IF($T48="","",Dashboard!$B$3+$T48-1) -> 46300 | I48: =IFERROR($T48-$F48+1,"") -> 1 | J48: =SUMIFS($U$5:$U$144,$R$5:$R$144,$A48,$B$5:$B$144,3) -> 6 | K48: =SUMIFS($W$5:$W$144,$R$5:$R$144,$A48,$B$5:$B$144,3) -> 0 | M48: =IFERROR(SUMIFS($V$5:$V$144,$R$5:$R$144,$A48,$B$5:$B$144,3)/SUMIFS($U$5:$U$144,$R$5:$R$144,$A48,$B$5:$B$144,3),0) -> 0 | R48: 3 | S48: 3 | T48: =IFERROR(_xlfn.MAXIFS($Y$5:$Y$144,$R$5:$R$144,$A48,$B$5:$B$144,3),"") -> 7
A49: 3.3.1 | B49: 3 | C49: Read endpoints - stations, departures, routes | D49: Backend Spine | E49: BE | F49: 7 | G49: =IF($F49="","",Dashboard!$B$3+$F49-1) -> 46300 | H49: =IF($T49="","",Dashboard!$B$3+$T49-1) -> 46300 | I49: 1 | J49: 2.5 | L49: To do | M49: =IF($L49="Done",1,IF($L49="Doing",0.5,0)) -> 0 | P49: Public, rate limited, cached, p95 under 300ms | R49: 3.3 | S49: 3 | T49: =$F49+$I49-1 -> 7 | U49: =IF($L49="Deferred",0,$J49) -> 2.5 | V49: =IF($L49="Deferred",0,$J49*$M49) -> 0 | W49: =IF($L49="Deferred",0,N($K49)) -> 0 | X49: =$F49 -> 7 | Y49: =$T49 -> 7
A50: 3.3.2 | B50: 3 | C50: Timetable admin writes with draft, publish, supersede | D50: Backend Spine | E50: BE | F50: 7 | G50: =IF($F50="","",Dashboard!$B$3+$F50-1) -> 46300 | H50: =IF($T50="","",Dashboard!$B$3+$T50-1) -> 46300 | I50: 1 | J50: 2.5 | L50: To do | M50: =IF($L50="Done",1,IF($L50="Doing",0.5,0)) -> 0 | P50: Published version immutable | R50: 3.3 | S50: 3 | T50: =$F50+$I50-1 -> 7 | U50: =IF($L50="Deferred",0,$J50) -> 2.5 | V50: =IF($L50="Deferred",0,$J50*$M50) -> 0 | W50: =IF($L50="Deferred",0,N($K50)) -> 0 | X50: =$F50 -> 7 | Y50: =$T50 -> 7
A51: 3.3.3 | B51: 3 | C51: OpenAPI document and generated typed clients | D51: Backend Spine | E51: BE | F51: 7 | G51: =IF($F51="","",Dashboard!$B$3+$F51-1) -> 46300 | H51: =IF($T51="","",Dashboard!$B$3+$T51-1) -> 46300 | I51: 1 | J51: 1 | L51: To do | M51: =IF($L51="Done",1,IF($L51="Doing",0.5,0)) -> 0 | P51: Web and mobile clients generated | R51: 3.3 | S51: 3 | T51: =$F51+$I51-1 -> 7 | U51: =IF($L51="Deferred",0,$J51) -> 1 | V51: =IF($L51="Deferred",0,$J51*$M51) -> 0 | W51: =IF($L51="Deferred",0,N($K51)) -> 0 | X51: =$F51 -> 7 | Y51: =$T51 -> 7
A52: 3.4 | B52: 2 | C52: Engineering platform | D52: Backend Spine | F52: =IFERROR(_xlfn.MINIFS($X$5:$X$144,$R$5:$R$144,$A52,$B$5:$B$144,3),"") -> 6 | G52: =IF($F52="","",Dashboard!$B$3+$F52-1) -> 46299 | H52: =IF($T52="","",Dashboard!$B$3+$T52-1) -> 46300 | I52: =IFERROR($T52-$F52+1,"") -> 2 | J52: =SUMIFS($U$5:$U$144,$R$5:$R$144,$A52,$B$5:$B$144,3) -> 4.5 | K52: =SUMIFS($W$5:$W$144,$R$5:$R$144,$A52,$B$5:$B$144,3) -> 0 | M52: =IFERROR(SUMIFS($V$5:$V$144,$R$5:$R$144,$A52,$B$5:$B$144,3)/SUMIFS($U$5:$U$144,$R$5:$R$144,$A52,$B$5:$B$144,3),0) -> 0 | R52: 3 | S52: 3 | T52: =IFERROR(_xlfn.MAXIFS($Y$5:$Y$144,$R$5:$R$144,$A52,$B$5:$B$144,3),"") -> 7
A53: 3.4.1 | B53: 3 | C53: Docker compose api, db, redis, seq plus Flutter toolchain smoke test | D53: Backend Spine | E53: OPS | F53: 6 | G53: =IF($F53="","",Dashboard!$B$3+$F53-1) -> 46299 | H53: =IF($T53="","",Dashboard!$B$3+$T53-1) -> 46299 | I53: 1 | J53: 1.5 | L53: To do | M53: =IF($L53="Done",1,IF($L53="Doing",0.5,0)) -> 0 | P53: One command up; emulator and FCM proven early - risk R3 | R53: 3.4 | S53: 3 | T53: =$F53+$I53-1 -> 6 | U53: =IF($L53="Deferred",0,$J53) -> 1.5 | V53: =IF($L53="Deferred",0,$J53*$M53) -> 0 | W53: =IF($L53="Deferred",0,N($K53)) -> 0 | X53: =$F53 -> 6 | Y53: =$T53 -> 6
A54: 3.4.2 | B54: 3 | C54: First domain unit tests and IClock abstraction | D54: Backend Spine | E54: QA | F54: 6 | G54: =IF($F54="","",Dashboard!$B$3+$F54-1) -> 46299 | H54: =IF($T54="","",Dashboard!$B$3+$T54-1) -> 46299 | I54: 1 | J54: 1 | L54: To do | M54: =IF($L54="Done",1,IF($L54="Doing",0.5,0)) -> 0 | P54: Time injectable everywhere - prerequisite for all later tests | R54: 3.4 | S54: 3 | T54: =$F54+$I54-1 -> 6 | U54: =IF($L54="Deferred",0,$J54) -> 1 | V54: =IF($L54="Deferred",0,$J54*$M54) -> 0 | W54: =IF($L54="Deferred",0,N($K54)) -> 0 | X54: =$F54 -> 6 | Y54: =$T54 -> 6
A55: 3.4.3 | B55: 3 | C55: GitHub Actions - build, unit, integration, architecture tests | D55: Backend Spine | E55: QA | F55: 7 | G55: =IF($F55="","",Dashboard!$B$3+$F55-1) -> 46300 | H55: =IF($T55="","",Dashboard!$B$3+$T55-1) -> 46300 | I55: 1 | J55: 2 | L55: To do | M55: =IF($L55="Done",1,IF($L55="Doing",0.5,0)) -> 0 | N55: G2 | P55: Green run on a clean checkout | R55: 3.4 | S55: 3 | T55: =$F55+$I55-1 -> 7 | U55: =IF($L55="Deferred",0,$J55) -> 2 | V55: =IF($L55="Deferred",0,$J55*$M55) -> 0 | W55: =IF($L55="Deferred",0,N($K55)) -> 0 | X55: =$F55 -> 7 | Y55: =$T55 -> 7
A56: 4 | B56: 1 | C56: Live Core | D56: Live Core | F56: =IFERROR(_xlfn.MINIFS($X$5:$X$144,$S$5:$S$144,$A56,$B$5:$B$144,3),"") -> 8 | G56: =IF($F56="","",Dashboard!$B$3+$F56-1) -> 46301 | H56: =IF($T56="","",Dashboard!$B$3+$T56-1) -> 46302 | I56: =IFERROR($T56-$F56+1,"") -> 2 | J56: =SUMIFS($U$5:$U$144,$S$5:$S$144,$A56,$B$5:$B$144,3) -> 16 | K56: =SUMIFS($W$5:$W$144,$S$5:$S$144,$A56,$B$5:$B$144,3) -> 0 | M56: =IFERROR(SUMIFS($V$5:$V$144,$S$5:$S$144,$A56,$B$5:$B$144,3)/SUMIFS($U$5:$U$144,$S$5:$S$144,$A56,$B$5:$B$144,3),0) -> 0 | T56: =IFERROR(_xlfn.MAXIFS($Y$5:$Y$144,$S$5:$S$144,$A56,$B$5:$B$144,3),"") -> 9
A57: 4.1 | B57: 2 | C57: Journey and telemetry | D57: Live Core | F57: =IFERROR(_xlfn.MINIFS($X$5:$X$144,$R$5:$R$144,$A57,$B$5:$B$144,3),"") -> 8 | G57: =IF($F57="","",Dashboard!$B$3+$F57-1) -> 46301 | H57: =IF($T57="","",Dashboard!$B$3+$T57-1) -> 46301 | I57: =IFERROR($T57-$F57+1,"") -> 1 | J57: =SUMIFS($U$5:$U$144,$R$5:$R$144,$A57,$B$5:$B$144,3) -> 4 | K57: =SUMIFS($W$5:$W$144,$R$5:$R$144,$A57,$B$5:$B$144,3) -> 0 | M57: =IFERROR(SUMIFS($V$5:$V$144,$R$5:$R$144,$A57,$B$5:$B$144,3)/SUMIFS($U$5:$U$144,$R$5:$R$144,$A57,$B$5:$B$144,3),0) -> 0 | R57: 4 | S57: 4 | T57: =IFERROR(_xlfn.MAXIFS($Y$5:$Y$144,$R$5:$R$144,$A57,$B$5:$B$144,3),"") -> 8
A58: 4.1.1 | B58: 3 | C58: Journey generation from timetable with service-date handling | D58: Live Core | E58: BE | F58: 8 | G58: =IF($F58="","",Dashboard!$B$3+$F58-1) -> 46301 | H58: =IF($T58="","",Dashboard!$B$3+$T58-1) -> 46301 | I58: 1 | J58: 2 | L58: To do | M58: =IF($L58="Done",1,IF($L58="Doing",0.5,0)) -> 0 | P58: 23:50 to 00:35 service resolves to the correct service day | R58: 4.1 | S58: 4 | T58: =$F58+$I58-1 -> 8 | U58: =IF($L58="Deferred",0,$J58) -> 2 | V58: =IF($L58="Deferred",0,$J58*$M58) -> 0 | W58: =IF($L58="Deferred",0,N($K58)) -> 0 | X58: =$F58 -> 8 | Y58: =$T58 -> 8
A59: 4.1.2 | B59: 3 | C59: Telemetry ingestion - sequence, idempotency, plausibility rejection | D59: Live Core | E59: BE | F59: 8 | G59: =IF($F59="","",Dashboard!$B$3+$F59-1) -> 46301 | H59: =IF($T59="","",Dashboard!$B$3+$T59-1) -> 46301 | I59: 1 | J59: 2 | L59: To do | M59: =IF($L59="Done",1,IF($L59="Doing",0.5,0)) -> 0 | P59: Duplicate, out-of-order and impossible pings rejected with a logged reason | R59: 4.1 | S59: 4 | T59: =$F59+$I59-1 -> 8 | U59: =IF($L59="Deferred",0,$J59) -> 2 | V59: =IF($L59="Deferred",0,$J59*$M59) -> 0 | W59: =IF($L59="Deferred",0,N($K59)) -> 0 | X59: =$F59 -> 8 | Y59: =$T59 -> 8
A60: 4.2 | B60: 2 | C60: ETA engine | D60: Live Core | F60: =IFERROR(_xlfn.MINIFS($X$5:$X$144,$R$5:$R$144,$A60,$B$5:$B$144,3),"") -> 8 | G60: =IF($F60="","",Dashboard!$B$3+$F60-1) -> 46301 | H60: =IF($T60="","",Dashboard!$B$3+$T60-1) -> 46301 | I60: =IFERROR($T60-$F60+1,"") -> 1 | J60: =SUMIFS($U$5:$U$144,$R$5:$R$144,$A60,$B$5:$B$144,3) -> 3 | K60: =SUMIFS($W$5:$W$144,$R$5:$R$144,$A60,$B$5:$B$144,3) -> 0 | M60: =IFERROR(SUMIFS($V$5:$V$144,$R$5:$R$144,$A60,$B$5:$B$144,3)/SUMIFS($U$5:$U$144,$R$5:$R$144,$A60,$B$5:$B$144,3),0) -> 0 | R60: 4 | S60: 4 | T60: =IFERROR(_xlfn.MAXIFS($Y$5:$Y$144,$R$5:$R$144,$A60,$B$5:$B$144,3),"") -> 8
A61: 4.2.1 | B61: 3 | C61: ETA propagation - offset plus dwell model with confidence levels | D61: Live Core | E61: BE | F61: 8 | G61: =IF($F61="","",Dashboard!$B$3+$F61-1) -> 46301 | H61: =IF($T61="","",Dashboard!$B$3+$T61-1) -> 46301 | I61: 1 | J61: 2 | L61: To do | M61: =IF($L61="Done",1,IF($L61="Doing",0.5,0)) -> 0 | P61: Every estimate carries source and confidence | R61: 4.2 | S61: 4 | T61: =$F61+$I61-1 -> 8 | U61: =IF($L61="Deferred",0,$J61) -> 2 | V61: =IF($L61="Deferred",0,$J61*$M61) -> 0 | W61: =IF($L61="Deferred",0,N($K61)) -> 0 | X61: =$F61 -> 8 | Y61: =$T61 -> 8
A62: 4.2.2 | B62: 3 | C62: Redis journey progress projection | D62: Live Core | E62: BE | F62: 8 | G62: =IF($F62="","",Dashboard!$B$3+$F62-1) -> 46301 | H62: =IF($T62="","",Dashboard!$B$3+$T62-1) -> 46301 | I62: 1 | J62: 1 | L62: To do | M62: =IF($L62="Done",1,IF($L62="Doing",0.5,0)) -> 0 | P62: Hot path off the Postgres write path | R62: 4.2 | S62: 4 | T62: =$F62+$I62-1 -> 8 | U62: =IF($L62="Deferred",0,$J62) -> 1 | V62: =IF($L62="Deferred",0,$J62*$M62) -> 0 | W62: =IF($L62="Deferred",0,N($K62)) -> 0 | X62: =$F62 -> 8 | Y62: =$T62 -> 8
A63: 4.3 | B63: 2 | C63: Realtime distribution | D63: Live Core | F63: =IFERROR(_xlfn.MINIFS($X$5:$X$144,$R$5:$R$144,$A63,$B$5:$B$144,3),"") -> 9 | G63: =IF($F63="","",Dashboard!$B$3+$F63-1) -> 46302 | H63: =IF($T63="","",Dashboard!$B$3+$T63-1) -> 46302 | I63: =IFERROR($T63-$F63+1,"") -> 1 | J63: =SUMIFS($U$5:$U$144,$R$5:$R$144,$A63,$B$5:$B$144,3) -> 4 | K63: =SUMIFS($W$5:$W$144,$R$5:$R$144,$A63,$B$5:$B$144,3) -> 0 | M63: =IFERROR(SUMIFS($V$5:$V$144,$R$5:$R$144,$A63,$B$5:$B$144,3)/SUMIFS($U$5:$U$144,$R$5:$R$144,$A63,$B$5:$B$144,3),0) -> 0 | R63: 4 | S63: 4 | T63: =IFERROR(_xlfn.MAXIFS($Y$5:$Y$144,$R$5:$R$144,$A63,$B$5:$B$144,3),"") -> 9
A64: 4.3.1 | B64: 3 | C64: SignalR hub - snapshot then delta, jittered reconnect | D64: Live Core | E64: BE | F64: 9 | G64: =IF($F64="","",Dashboard!$B$3+$F64-1) -> 46302 | H64: =IF($T64="","",Dashboard!$B$3+$T64-1) -> 46302 | I64: 1 | J64: 3 | L64: To do | M64: =IF($L64="Done",1,IF($L64="Doing",0.5,0)) -> 0 | P64: 200 reconnects do not storm the API | R64: 4.3 | S64: 4 | T64: =$F64+$I64-1 -> 9 | U64: =IF($L64="Deferred",0,$J64) -> 3 | V64: =IF($L64="Deferred",0,$J64*$M64) -> 0 | W64: =IF($L64="Deferred",0,N($K64)) -> 0 | X64: =$F64 -> 9 | Y64: =$T64 -> 9
A65: 4.3.2 | B65: 3 | C65: Notification outbox with dedup and throttle rules | D65: Live Core | E65: BE | F65: 9 | G65: =IF($F65="","",Dashboard!$B$3+$F65-1) -> 46302 | H65: =IF($T65="","",Dashboard!$B$3+$T65-1) -> 46302 | I65: 1 | J65: 1 | L65: To do | M65: =IF($L65="Done",1,IF($L65="Doing",0.5,0)) -> 0 | P65: Six delays produce one push, not six | R65: 4.3 | S65: 4 | T65: =$F65+$I65-1 -> 9 | U65: =IF($L65="Deferred",0,$J65) -> 1 | V65: =IF($L65="Deferred",0,$J65*$M65) -> 0 | W65: =IF($L65="Deferred",0,N($K65)) -> 0 | X65: =$F65 -> 9 | Y65: =$T65 -> 9
A66: 4.4 | B66: 2 | C66: Disruptions | D66: Live Core | F66: =IFERROR(_xlfn.MINIFS($X$5:$X$144,$R$5:$R$144,$A66,$B$5:$B$144,3),"") -> 9 | G66: =IF($F66="","",Dashboard!$B$3+$F66-1) -> 46302 | H66: =IF($T66="","",Dashboard!$B$3+$T66-1) -> 46302 | I66: =IFERROR($T66-$F66+1,"") -> 1 | J66: =SUMIFS($U$5:$U$144,$R$5:$R$144,$A66,$B$5:$B$144,3) -> 4 | K66: =SUMIFS($W$5:$W$144,$R$5:$R$144,$A66,$B$5:$B$144,3) -> 0 | M66: =IFERROR(SUMIFS($V$5:$V$144,$R$5:$R$144,$A66,$B$5:$B$144,3)/SUMIFS($U$5:$U$144,$R$5:$R$144,$A66,$B$5:$B$144,3),0) -> 0 | R66: 4 | S66: 4 | T66: =IFERROR(_xlfn.MAXIFS($Y$5:$Y$144,$R$5:$R$144,$A66,$B$5:$B$144,3),"") -> 9
A67: 4.4.1 | B67: 3 | C67: Disruptions module - publish, update, retract, scope, reason codes | D67: Live Core | E67: BE | F67: 9 | G67: =IF($F67="","",Dashboard!$B$3+$F67-1) -> 46302 | H67: =IF($T67="","",Dashboard!$B$3+$T67-1) -> 46302 | I67: 1 | J67: 2.5 | L67: To do | M67: =IF($L67="Done",1,IF($L67="Doing",0.5,0)) -> 0 | P67: Retraction is a distinct operation from update | R67: 4.4 | S67: 4 | T67: =$F67+$I67-1 -> 9 | U67: =IF($L67="Deferred",0,$J67) -> 2.5 | V67: =IF($L67="Deferred",0,$J67*$M67) -> 0 | W67: =IF($L67="Deferred",0,N($K67)) -> 0 | X67: =$F67 -> 9 | Y67: =$T67 -> 9
A68: 4.4.2 | B68: 3 | C68: Append-only audit trail for high-consequence actions | D68: Live Core | E68: SEC | F68: 9 | G68: =IF($F68="","",Dashboard!$B$3+$F68-1) -> 46302 | H68: =IF($T68="","",Dashboard!$B$3+$T68-1) -> 46302 | I68: 1 | J68: 1.5 | L68: To do | M68: =IF($L68="Done",1,IF($L68="Doing",0.5,0)) -> 0 | P68: Actor, reason, before and after on cancel and publish | R68: 4.4 | S68: 4 | T68: =$F68+$I68-1 -> 9 | U68: =IF($L68="Deferred",0,$J68) -> 1.5 | V68: =IF($L68="Deferred",0,$J68*$M68) -> 0 | W68: =IF($L68="Deferred",0,N($K68)) -> 0 | X68: =$F68 -> 9 | Y68: =$T68 -> 9
A69: 4.5 | B69: 2 | C69: Test instrumentation | D69: Live Core | F69: =IFERROR(_xlfn.MINIFS($X$5:$X$144,$R$5:$R$144,$A69,$B$5:$B$144,3),"") -> 8 | G69: =IF($F69="","",Dashboard!$B$3+$F69-1) -> 46301 | H69: =IF($T69="","",Dashboard!$B$3+$T69-1) -> 46301 | I69: =IFERROR($T69-$F69+1,"") -> 1 | J69: =SUMIFS($U$5:$U$144,$R$5:$R$144,$A69,$B$5:$B$144,3) -> 1 | K69: =SUMIFS($W$5:$W$144,$R$5:$R$144,$A69,$B$5:$B$144,3) -> 0 | M69: =IFERROR(SUMIFS($V$5:$V$144,$R$5:$R$144,$A69,$B$5:$B$144,3)/SUMIFS($U$5:$U$144,$R$5:$R$144,$A69,$B$5:$B$144,3),0) -> 0 | R69: 4 | S69: 4 | T69: =IFERROR(_xlfn.MAXIFS($Y$5:$Y$144,$R$5:$R$144,$A69,$B$5:$B$144,3),"") -> 8
A70: 4.5.1 | B70: 3 | C70: Journey simulator with six seeded scenarios | D70: Live Core | E70: QA | F70: 8 | G70: =IF($F70="","",Dashboard!$B$3+$F70-1) -> 46301 | H70: =IF($T70="","",Dashboard!$B$3+$T70-1) -> 46301 | I70: 1 | J70: 1 | L70: To do | M70: =IF($L70="Done",1,IF($L70="Doing",0.5,0)) -> 0 | P70: on-time, delay, skip-stop, terminate-short, blackout, cancel | R70: 4.5 | S70: 4 | T70: =$F70+$I70-1 -> 8 | U70: =IF($L70="Deferred",0,$J70) -> 1 | V70: =IF($L70="Deferred",0,$J70*$M70) -> 0 | W70: =IF($L70="Deferred",0,N($K70)) -> 0 | X70: =$F70 -> 8 | Y70: =$T70 -> 8
A71: 5 | B71: 1 | C71: Client Applications | D71: Client Applications | F71: =IFERROR(_xlfn.MINIFS($X$5:$X$144,$S$5:$S$144,$A71,$B$5:$B$144,3),"") -> 10 | G71: =IF($F71="","",Dashboard!$B$3+$F71-1) -> 46303 | H71: =IF($T71="","",Dashboard!$B$3+$T71-1) -> 46306 | I71: =IFERROR($T71-$F71+1,"") -> 4 | J71: =SUMIFS($U$5:$U$144,$S$5:$S$144,$A71,$B$5:$B$144,3) -> 32 | K71: =SUMIFS($W$5:$W$144,$S$5:$S$144,$A71,$B$5:$B$144,3) -> 0 | M71: =IFERROR(SUMIFS($V$5:$V$144,$S$5:$S$144,$A71,$B$5:$B$144,3)/SUMIFS($U$5:$U$144,$S$5:$S$144,$A71,$B$5:$B$144,3),0) -> 0 | T71: =IFERROR(_xlfn.MAXIFS($Y$5:$Y$144,$S$5:$S$144,$A71,$B$5:$B$144,3),"") -> 13
A72: 5.1 | B72: 2 | C72: Ops console core | D72: Client Applications | F72: =IFERROR(_xlfn.MINIFS($X$5:$X$144,$R$5:$R$144,$A72,$B$5:$B$144,3),"") -> 10 | G72: =IF($F72="","",Dashboard!$B$3+$F72-1) -> 46303 | H72: =IF($T72="","",Dashboard!$B$3+$T72-1) -> 46303 | I72: =IFERROR($T72-$F72+1,"") -> 1 | J72: =SUMIFS($U$5:$U$144,$R$5:$R$144,$A72,$B$5:$B$144,3) -> 8 | K72: =SUMIFS($W$5:$W$144,$R$5:$R$144,$A72,$B$5:$B$144,3) -> 0 | M72: =IFERROR(SUMIFS($V$5:$V$144,$R$5:$R$144,$A72,$B$5:$B$144,3)/SUMIFS($U$5:$U$144,$R$5:$R$144,$A72,$B$5:$B$144,3),0) -> 0 | R72: 5 | S72: 5 | T72: =IFERROR(_xlfn.MAXIFS($Y$5:$Y$144,$R$5:$R$144,$A72,$B$5:$B$144,3),"") -> 10
A73: 5.1.1 | B73: 3 | C73: Shell, auth, routing and layout | D73: Client Applications | E73: WEB | F73: 10 | G73: =IF($F73="","",Dashboard!$B$3+$F73-1) -> 46303 | H73: =IF($T73="","",Dashboard!$B$3+$T73-1) -> 46303 | I73: 1 | J73: 2 | L73: To do | M73: =IF($L73="Done",1,IF($L73="Doing",0.5,0)) -> 0 | P73: Permission-aware navigation | R73: 5.1 | S73: 5 | T73: =$F73+$I73-1 -> 10 | U73: =IF($L73="Deferred",0,$J73) -> 2 | V73: =IF($L73="Deferred",0,$J73*$M73) -> 0 | W73: =IF($L73="Deferred",0,N($K73)) -> 0 | X73: =$F73 -> 10 | Y73: =$T73 -> 10
A74: 5.1.2 | B74: 3 | C74: Live Network Board with realtime deltas and filters | D74: Client Applications | E74: WEB | F74: 10 | G74: =IF($F74="","",Dashboard!$B$3+$F74-1) -> 46303 | H74: =IF($T74="","",Dashboard!$B$3+$T74-1) -> 46303 | I74: 1 | J74: 3.5 | L74: To do | M74: =IF($L74="Done",1,IF($L74="Doing",0.5,0)) -> 0 | P74: Updates without refresh; stale state visible | R74: 5.1 | S74: 5 | T74: =$F74+$I74-1 -> 10 | U74: =IF($L74="Deferred",0,$J74) -> 3.5 | V74: =IF($L74="Deferred",0,$J74*$M74) -> 0 | W74: =IF($L74="Deferred",0,N($K74)) -> 0 | X74: =$F74 -> 10 | Y74: =$T74 -> 10
A75: 5.1.3 | B75: 3 | C75: Timetable and Journeys screen with per-journey actions | D75: Client Applications | E75: WEB | F75: 10 | G75: =IF($F75="","",Dashboard!$B$3+$F75-1) -> 46303 | H75: =IF($T75="","",Dashboard!$B$3+$T75-1) -> 46303 | I75: 1 | J75: 2.5 | L75: To do | M75: =IF($L75="Done",1,IF($L75="Doing",0.5,0)) -> 0 | P75: Cancel, terminate short, platform change - all with reason codes | R75: 5.1 | S75: 5 | T75: =$F75+$I75-1 -> 10 | U75: =IF($L75="Deferred",0,$J75) -> 2.5 | V75: =IF($L75="Deferred",0,$J75*$M75) -> 0 | W75: =IF($L75="Deferred",0,N($K75)) -> 0 | X75: =$F75 -> 10 | Y75: =$T75 -> 10
A76: 5.2 | B76: 2 | C76: Ops console operational tools | D76: Client Applications | F76: =IFERROR(_xlfn.MINIFS($X$5:$X$144,$R$5:$R$144,$A76,$B$5:$B$144,3),"") -> 11 | G76: =IF($F76="","",Dashboard!$B$3+$F76-1) -> 46304 | H76: =IF($T76="","",Dashboard!$B$3+$T76-1) -> 46304 | I76: =IFERROR($T76-$F76+1,"") -> 1 | J76: =SUMIFS($U$5:$U$144,$R$5:$R$144,$A76,$B$5:$B$144,3) -> 5 | K76: =SUMIFS($W$5:$W$144,$R$5:$R$144,$A76,$B$5:$B$144,3) -> 0 | M76: =IFERROR(SUMIFS($V$5:$V$144,$R$5:$R$144,$A76,$B$5:$B$144,3)/SUMIFS($U$5:$U$144,$R$5:$R$144,$A76,$B$5:$B$144,3),0) -> 0 | R76: 5 | S76: 5 | T76: =IFERROR(_xlfn.MAXIFS($Y$5:$Y$144,$R$5:$R$144,$A76,$B$5:$B$144,3),"") -> 11
A77: 5.2.1 | B77: 3 | C77: Disruption Console with passenger preview and network-wide confirm gate | D77: Client Applications | E77: WEB | F77: 11 | G77: =IF($F77="","",Dashboard!$B$3+$F77-1) -> 46304 | H77: =IF($T77="","",Dashboard!$B$3+$T77-1) -> 46304 | I77: 1 | J77: 2.5 | L77: To do | M77: =IF($L77="Done",1,IF($L77="Doing",0.5,0)) -> 0 | P77: Operator sees exactly what passengers will see before publishing | R77: 5.2 | S77: 5 | T77: =$F77+$I77-1 -> 11 | U77: =IF($L77="Deferred",0,$J77) -> 2.5 | V77: =IF($L77="Deferred",0,$J77*$M77) -> 0 | W77: =IF($L77="Deferred",0,N($K77)) -> 0 | X77: =$F77 -> 11 | Y77: =$T77 -> 11
A78: 5.2.2 | B78: 3 | C78: Station and Device Health with heartbeat and revoke | D78: Client Applications | E78: WEB | F78: 11 | G78: =IF($F78="","",Dashboard!$B$3+$F78-1) -> 46304 | H78: =IF($T78="","",Dashboard!$B$3+$T78-1) -> 46304 | I78: 1 | J78: 1.5 | L78: To do | M78: =IF($L78="Done",1,IF($L78="Doing",0.5,0)) -> 0 | P78: A dead display is visible within 60 seconds | R78: 5.2 | S78: 5 | T78: =$F78+$I78-1 -> 11 | U78: =IF($L78="Deferred",0,$J78) -> 1.5 | V78: =IF($L78="Deferred",0,$J78*$M78) -> 0 | W78: =IF($L78="Deferred",0,N($K78)) -> 0 | X78: =$F78 -> 11 | Y78: =$T78 -> 11
A79: 5.2.3 | B79: 3 | C79: Punctuality report with export | D79: Client Applications | E79: WEB | F79: 11 | G79: =IF($F79="","",Dashboard!$B$3+$F79-1) -> 46304 | H79: =IF($T79="","",Dashboard!$B$3+$T79-1) -> 46304 | I79: 1 | J79: 1 | L79: To do | M79: =IF($L79="Done",1,IF($L79="Doing",0.5,0)) -> 0 | P79: OTP by service, route and day | R79: 5.2 | S79: 5 | T79: =$F79+$I79-1 -> 11 | U79: =IF($L79="Deferred",0,$J79) -> 1 | V79: =IF($L79="Deferred",0,$J79*$M79) -> 0 | W79: =IF($L79="Deferred",0,N($K79)) -> 0 | X79: =$F79 -> 11 | Y79: =$T79 -> 11
A80: 5.3 | B80: 2 | C80: Station kiosk display | D80: Client Applications | F80: =IFERROR(_xlfn.MINIFS($X$5:$X$144,$R$5:$R$144,$A80,$B$5:$B$144,3),"") -> 11 | G80: =IF($F80="","",Dashboard!$B$3+$F80-1) -> 46304 | H80: =IF($T80="","",Dashboard!$B$3+$T80-1) -> 46304 | I80: =IFERROR($T80-$F80+1,"") -> 1 | J80: =SUMIFS($U$5:$U$144,$R$5:$R$144,$A80,$B$5:$B$144,3) -> 3 | K80: =SUMIFS($W$5:$W$144,$R$5:$R$144,$A80,$B$5:$B$144,3) -> 0 | M80: =IFERROR(SUMIFS($V$5:$V$144,$R$5:$R$144,$A80,$B$5:$B$144,3)/SUMIFS($U$5:$U$144,$R$5:$R$144,$A80,$B$5:$B$144,3),0) -> 0 | R80: 5 | S80: 5 | T80: =IFERROR(_xlfn.MAXIFS($Y$5:$Y$144,$R$5:$R$144,$A80,$B$5:$B$144,3),"") -> 11
A81: 5.3.1 | B81: 3 | C81: Display mode - platform and concourse boards | D81: Client Applications | E81: KIOSK | F81: 11 | G81: =IF($F81="","",Dashboard!$B$3+$F81-1) -> 46304 | H81: =IF($T81="","",Dashboard!$B$3+$T81-1) -> 46304 | I81: 1 | J81: 2 | L81: To do | M81: =IF($L81="Done",1,IF($L81="Doing",0.5,0)) -> 0 | P81: Legible at 5 to 10 metres; delay shown as a delta | R81: 5.3 | S81: 5 | T81: =$F81+$I81-1 -> 11 | U81: =IF($L81="Deferred",0,$J81) -> 2 | V81: =IF($L81="Deferred",0,$J81*$M81) -> 0 | W81: =IF($L81="Deferred",0,N($K81)) -> 0 | X81: =$F81 -> 11 | Y81: =$T81 -> 11
A82: 5.3.2 | B82: 3 | C82: Service worker last-known-good snapshot and staleness banner | D82: Client Applications | E82: KIOSK | F82: 11 | G82: =IF($F82="","",Dashboard!$B$3+$F82-1) -> 46304 | H82: =IF($T82="","",Dashboard!$B$3+$T82-1) -> 46304 | I82: 1 | J82: 1 | L82: To do | M82: =IF($L82="Done",1,IF($L82="Doing",0.5,0)) -> 0 | P82: Offline board never implies freshness | R82: 5.3 | S82: 5 | T82: =$F82+$I82-1 -> 11 | U82: =IF($L82="Deferred",0,$J82) -> 1 | V82: =IF($L82="Deferred",0,$J82*$M82) -> 0 | W82: =IF($L82="Deferred",0,N($K82)) -> 0 | X82: =$F82 -> 11 | Y82: =$T82 -> 11
A83: 5.4 | B83: 2 | C83: Mobile foundation | D83: Client Applications | F83: =IFERROR(_xlfn.MINIFS($X$5:$X$144,$R$5:$R$144,$A83,$B$5:$B$144,3),"") -> 12 | G83: =IF($F83="","",Dashboard!$B$3+$F83-1) -> 46305 | H83: =IF($T83="","",Dashboard!$B$3+$T83-1) -> 46305 | I83: =IFERROR($T83-$F83+1,"") -> 1 | J83: =SUMIFS($U$5:$U$144,$R$5:$R$144,$A83,$B$5:$B$144,3) -> 3 | K83: =SUMIFS($W$5:$W$144,$R$5:$R$144,$A83,$B$5:$B$144,3) -> 0 | M83: =IFERROR(SUMIFS($V$5:$V$144,$R$5:$R$144,$A83,$B$5:$B$144,3)/SUMIFS($U$5:$U$144,$R$5:$R$144,$A83,$B$5:$B$144,3),0) -> 0 | R83: 5 | S83: 5 | T83: =IFERROR(_xlfn.MAXIFS($Y$5:$Y$144,$R$5:$R$144,$A83,$B$5:$B$144,3),"") -> 12
A84: 5.4.1 | B84: 3 | C84: Flutter melos monorepo - core, design_system, api_client packages | D84: Client Applications | E84: MOB | F84: 12 | G84: =IF($F84="","",Dashboard!$B$3+$F84-1) -> 46305 | H84: =IF($T84="","",Dashboard!$B$3+$T84-1) -> 46305 | I84: 1 | J84: 2 | L84: To do | M84: =IF($L84="Done",1,IF($L84="Doing",0.5,0)) -> 0 | P84: Both apps build from shared packages | R84: 5.4 | S84: 5 | T84: =$F84+$I84-1 -> 12 | U84: =IF($L84="Deferred",0,$J84) -> 2 | V84: =IF($L84="Deferred",0,$J84*$M84) -> 0 | W84: =IF($L84="Deferred",0,N($K84)) -> 0 | X84: =$F84 -> 12 | Y84: =$T84 -> 12
A85: 5.4.2 | B85: 3 | C85: Design token codegen - tokens.json to Dart and CSS | D85: Client Applications | E85: UX | F85: 12 | G85: =IF($F85="","",Dashboard!$B$3+$F85-1) -> 46305 | H85: =IF($T85="","",Dashboard!$B$3+$T85-1) -> 46305 | I85: 1 | J85: 1 | L85: To do | M85: =IF($L85="Done",1,IF($L85="Doing",0.5,0)) -> 0 | P85: One source of truth, no drift between React and Flutter | R85: 5.4 | S85: 5 | T85: =$F85+$I85-1 -> 12 | U85: =IF($L85="Deferred",0,$J85) -> 1 | V85: =IF($L85="Deferred",0,$J85*$M85) -> 0 | W85: =IF($L85="Deferred",0,N($K85)) -> 0 | X85: =$F85 -> 12 | Y85: =$T85 -> 12
A86: 5.5 | B86: 2 | C86: Passenger application | D86: Client Applications | F86: =IFERROR(_xlfn.MINIFS($X$5:$X$144,$R$5:$R$144,$A86,$B$5:$B$144,3),"") -> 12 | G86: =IF($F86="","",Dashboard!$B$3+$F86-1) -> 46305 | H86: =IF($T86="","",Dashboard!$B$3+$T86-1) -> 46306 | I86: =IFERROR($T86-$F86+1,"") -> 2 | J86: =SUMIFS($U$5:$U$144,$R$5:$R$144,$A86,$B$5:$B$144,3) -> 8 | K86: =SUMIFS($W$5:$W$144,$R$5:$R$144,$A86,$B$5:$B$144,3) -> 0 | M86: =IFERROR(SUMIFS($V$5:$V$144,$R$5:$R$144,$A86,$B$5:$B$144,3)/SUMIFS($U$5:$U$144,$R$5:$R$144,$A86,$B$5:$B$144,3),0) -> 0 | R86: 5 | S86: 5 | T86: =IFERROR(_xlfn.MAXIFS($Y$5:$Y$144,$R$5:$R$144,$A86,$B$5:$B$144,3),"") -> 13
A87: 5.5.1 | B87: 3 | C87: Plan and station departures screens | D87: Client Applications | E87: MOB | F87: 12 | G87: =IF($F87="","",Dashboard!$B$3+$F87-1) -> 46305 | H87: =IF($T87="","",Dashboard!$B$3+$T87-1) -> 46305 | I87: 1 | J87: 2.5 | L87: To do | M87: =IF($L87="Done",1,IF($L87="Doing",0.5,0)) -> 0 | P87: Three-second glanceability | R87: 5.5 | S87: 5 | T87: =$F87+$I87-1 -> 12 | U87: =IF($L87="Deferred",0,$J87) -> 2.5 | V87: =IF($L87="Deferred",0,$J87*$M87) -> 0 | W87: =IF($L87="Deferred",0,N($K87)) -> 0 | X87: =$F87 -> 12 | Y87: =$T87 -> 12
A88: 5.5.2 | B88: 3 | C88: Journey detail with live progress and confidence chip | D88: Client Applications | E88: MOB | F88: 12 | G88: =IF($F88="","",Dashboard!$B$3+$F88-1) -> 46305 | H88: =IF($T88="","",Dashboard!$B$3+$T88-1) -> 46305 | I88: 1 | J88: 2.5 | L88: To do | M88: =IF($L88="Done",1,IF($L88="Doing",0.5,0)) -> 0 | P88: Scheduled vs live vs confirmed visually distinct | R88: 5.5 | S88: 5 | T88: =$F88+$I88-1 -> 12 | U88: =IF($L88="Deferred",0,$J88) -> 2.5 | V88: =IF($L88="Deferred",0,$J88*$M88) -> 0 | W88: =IF($L88="Deferred",0,N($K88)) -> 0 | X88: =$F88 -> 12 | Y88: =$T88 -> 12
A89: 5.5.3 | B89: 3 | C89: Follow a journey - subscriptions, preferences, quiet hours | D89: Client Applications | E89: MOB | F89: 13 | G89: =IF($F89="","",Dashboard!$B$3+$F89-1) -> 46306 | H89: =IF($T89="","",Dashboard!$B$3+$T89-1) -> 46306 | I89: 1 | J89: 1.5 | L89: To do | M89: =IF($L89="Done",1,IF($L89="Doing",0.5,0)) -> 0 | P89: Opt-in, revocable | R89: 5.5 | S89: 5 | T89: =$F89+$I89-1 -> 13 | U89: =IF($L89="Deferred",0,$J89) -> 1.5 | V89: =IF($L89="Deferred",0,$J89*$M89) -> 0 | W89: =IF($L89="Deferred",0,N($K89)) -> 0 | X89: =$F89 -> 13 | Y89: =$T89 -> 13
A90: 5.5.4 | B90: 3 | C90: Push notifications via FCM with dedup verification | D90: Client Applications | E90: MOB | F90: 13 | G90: =IF($F90="","",Dashboard!$B$3+$F90-1) -> 46306 | H90: =IF($T90="","",Dashboard!$B$3+$T90-1) -> 46306 | I90: 1 | J90: 1.5 | L90: To do | M90: =IF($L90="Done",1,IF($L90="Doing",0.5,0)) -> 0 | P90: Throttling proven by test, not by inspection | R90: 5.5 | S90: 5 | T90: =$F90+$I90-1 -> 13 | U90: =IF($L90="Deferred",0,$J90) -> 1.5 | V90: =IF($L90="Deferred",0,$J90*$M90) -> 0 | W90: =IF($L90="Deferred",0,N($K90)) -> 0 | X90: =$F90 -> 13 | Y90: =$T90 -> 13
A91: 5.6 | B91: 2 | C91: Driver application | D91: Client Applications | F91: =IFERROR(_xlfn.MINIFS($X$5:$X$144,$R$5:$R$144,$A91,$B$5:$B$144,3),"") -> 13 | G91: =IF($F91="","",Dashboard!$B$3+$F91-1) -> 46306 | H91: =IF($T91="","",Dashboard!$B$3+$T91-1) -> 46306 | I91: =IFERROR($T91-$F91+1,"") -> 1 | J91: =SUMIFS($U$5:$U$144,$R$5:$R$144,$A91,$B$5:$B$144,3) -> 5 | K91: =SUMIFS($W$5:$W$144,$R$5:$R$144,$A91,$B$5:$B$144,3) -> 0 | M91: =IFERROR(SUMIFS($V$5:$V$144,$R$5:$R$144,$A91,$B$5:$B$144,3)/SUMIFS($U$5:$U$144,$R$5:$R$144,$A91,$B$5:$B$144,3),0) -> 0 | R91: 5 | S91: 5 | T91: =IFERROR(_xlfn.MAXIFS($Y$5:$Y$144,$R$5:$R$144,$A91,$B$5:$B$144,3),"") -> 13
A92: 5.6.1 | B92: 3 | C92: Duty roster and sign-on | D92: Client Applications | E92: MOB | F92: 13 | G92: =IF($F92="","",Dashboard!$B$3+$F92-1) -> 46306 | H92: =IF($T92="","",Dashboard!$B$3+$T92-1) -> 46306 | I92: 1 | J92: 1.5 | L92: To do | M92: =IF($L92="Done",1,IF($L92="Doing",0.5,0)) -> 0 | P92: Short session, re-auth on sensitive action | R92: 5.6 | S92: 5 | T92: =$F92+$I92-1 -> 13 | U92: =IF($L92="Deferred",0,$J92) -> 1.5 | V92: =IF($L92="Deferred",0,$J92*$M92) -> 0 | W92: =IF($L92="Deferred",0,N($K92)) -> 0 | X92: =$F92 -> 13 | Y92: =$T92 -> 13
A93: 5.6.2 | B93: 3 | C93: Active journey glanceable stop list | D93: Client Applications | E93: MOB | F93: 13 | G93: =IF($F93="","",Dashboard!$B$3+$F93-1) -> 46306 | H93: =IF($T93="","",Dashboard!$B$3+$T93-1) -> 46306 | I93: 1 | J93: 1.5 | L93: To do | M93: =IF($L93="Done",1,IF($L93="Doing",0.5,0)) -> 0 | P93: Readable with gloves, in glare, no typing while moving | R93: 5.6 | S93: 5 | T93: =$F93+$I93-1 -> 13 | U93: =IF($L93="Deferred",0,$J93) -> 1.5 | V93: =IF($L93="Deferred",0,$J93*$M93) -> 0 | W93: =IF($L93="Deferred",0,N($K93)) -> 0 | X93: =$F93 -> 13 | Y93: =$T93 -> 13
A94: 5.6.3 | B94: 3 | C94: Stop confirm with Drift offline queue and replay | D94: Client Applications | E94: MOB | F94: 13 | G94: =IF($F94="","",Dashboard!$B$3+$F94-1) -> 46306 | H94: =IF($T94="","",Dashboard!$B$3+$T94-1) -> 46306 | I94: 1 | J94: 2 | L94: To do | M94: =IF($L94="Done",1,IF($L94="Doing",0.5,0)) -> 0 | P94: Queue survives app kill; device and server time both recorded | R94: 5.6 | S94: 5 | T94: =$F94+$I94-1 -> 13 | U94: =IF($L94="Deferred",0,$J94) -> 2 | V94: =IF($L94="Deferred",0,$J94*$M94) -> 0 | W94: =IF($L94="Deferred",0,N($K94)) -> 0 | X94: =$F94 -> 13 | Y94: =$T94 -> 13
A95: 6 | B95: 1 | C95: External Integration | D95: External Integration | F95: =IFERROR(_xlfn.MINIFS($X$5:$X$144,$S$5:$S$144,$A95,$B$5:$B$144,3),"") -> 14 | G95: =IF($F95="","",Dashboard!$B$3+$F95-1) -> 46307 | H95: =IF($T95="","",Dashboard!$B$3+$T95-1) -> 46307 | I95: =IFERROR($T95-$F95+1,"") -> 1 | J95: =SUMIFS($U$5:$U$144,$S$5:$S$144,$A95,$B$5:$B$144,3) -> 9.5 | K95: =SUMIFS($W$5:$W$144,$S$5:$S$144,$A95,$B$5:$B$144,3) -> 0 | M95: =IFERROR(SUMIFS($V$5:$V$144,$S$5:$S$144,$A95,$B$5:$B$144,3)/SUMIFS($U$5:$U$144,$S$5:$S$144,$A95,$B$5:$B$144,3),0) -> 0 | T95: =IFERROR(_xlfn.MAXIFS($Y$5:$Y$144,$S$5:$S$144,$A95,$B$5:$B$144,3),"") -> 14
A96: 6.1 | B96: 2 | C96: RailBite external platform | D96: External Integration | F96: =IFERROR(_xlfn.MINIFS($X$5:$X$144,$R$5:$R$144,$A96,$B$5:$B$144,3),"") -> 14 | G96: =IF($F96="","",Dashboard!$B$3+$F96-1) -> 46307 | H96: =IF($T96="","",Dashboard!$B$3+$T96-1) -> 46307 | I96: =IFERROR($T96-$F96+1,"") -> 1 | J96: =SUMIFS($U$5:$U$144,$R$5:$R$144,$A96,$B$5:$B$144,3) -> 2.5 | K96: =SUMIFS($W$5:$W$144,$R$5:$R$144,$A96,$B$5:$B$144,3) -> 0 | M96: =IFERROR(SUMIFS($V$5:$V$144,$R$5:$R$144,$A96,$B$5:$B$144,3)/SUMIFS($U$5:$U$144,$R$5:$R$144,$A96,$B$5:$B$144,3),0) -> 0 | R96: 6 | S96: 6 | T96: =IFERROR(_xlfn.MAXIFS($Y$5:$Y$144,$R$5:$R$144,$A96,$B$5:$B$144,3),"") -> 14
A97: 6.1.1 | B97: 3 | C97: Node app - menu, stock, station eligibility, order lifecycle | D97: External Integration | E97: INT | F97: 14 | G97: =IF($F97="","",Dashboard!$B$3+$F97-1) -> 46307 | H97: =IF($T97="","",Dashboard!$B$3+$T97-1) -> 46307 | I97: 1 | J97: 2.5 | L97: To do | M97: =IF($L97="Done",1,IF($L97="Doing",0.5,0)) -> 0 | P97: Own database; owns menu, price and payment | R97: 6.1 | S97: 6 | T97: =$F97+$I97-1 -> 14 | U97: =IF($L97="Deferred",0,$J97) -> 2.5 | V97: =IF($L97="Deferred",0,$J97*$M97) -> 0 | W97: =IF($L97="Deferred",0,N($K97)) -> 0 | X97: =$F97 -> 14 | Y97: =$T97 -> 14
A98: 6.2 | B98: 2 | C98: Integration contract | D98: External Integration | F98: =IFERROR(_xlfn.MINIFS($X$5:$X$144,$R$5:$R$144,$A98,$B$5:$B$144,3),"") -> 14 | G98: =IF($F98="","",Dashboard!$B$3+$F98-1) -> 46307 | H98: =IF($T98="","",Dashboard!$B$3+$T98-1) -> 46307 | I98: =IFERROR($T98-$F98+1,"") -> 1 | J98: =SUMIFS($U$5:$U$144,$R$5:$R$144,$A98,$B$5:$B$144,3) -> 5 | K98: =SUMIFS($W$5:$W$144,$R$5:$R$144,$A98,$B$5:$B$144,3) -> 0 | M98: =IFERROR(SUMIFS($V$5:$V$144,$R$5:$R$144,$A98,$B$5:$B$144,3)/SUMIFS($U$5:$U$144,$R$5:$R$144,$A98,$B$5:$B$144,3),0) -> 0 | R98: 6 | S98: 6 | T98: =IFERROR(_xlfn.MAXIFS($Y$5:$Y$144,$R$5:$R$144,$A98,$B$5:$B$144,3),"") -> 14
A99: 6.2.1 | B99: 3 | C99: Outbound reference and ETA feed with API key auth | D99: External Integration | E99: INT | F99: 14 | G99: =IF($F99="","",Dashboard!$B$3+$F99-1) -> 46307 | H99: =IF($T99="","",Dashboard!$B$3+$T99-1) -> 46307 | I99: 1 | J99: 1.5 | L99: To do | M99: =IF($L99="Done",1,IF($L99="Doing",0.5,0)) -> 0 | P99: Minimum payload - no passenger identity | R99: 6.2 | S99: 6 | T99: =$F99+$I99-1 -> 14 | U99: =IF($L99="Deferred",0,$J99) -> 1.5 | V99: =IF($L99="Deferred",0,$J99*$M99) -> 0 | W99: =IF($L99="Deferred",0,N($K99)) -> 0 | X99: =$F99 -> 14 | Y99: =$T99 -> 14
A100: 6.2.2 | B100: 3 | C100: Inbound HMAC signed webhooks with replay window and idempotency | D100: External Integration | E100: INT | F100: 14 | G100: =IF($F100="","",Dashboard!$B$3+$F100-1) -> 46307 | H100: =IF($T100="","",Dashboard!$B$3+$T100-1) -> 46307 | I100: 1 | J100: 2 | L100: To do | M100: =IF($L100="Done",1,IF($L100="Doing",0.5,0)) -> 0 | P100: Duplicate delivery is a no-op | R100: 6.2 | S100: 6 | T100: =$F100+$I100-1 -> 14 | U100: =IF($L100="Deferred",0,$J100) -> 2 | V100: =IF($L100="Deferred",0,$J100*$M100) -> 0 | W100: =IF($L100="Deferred",0,N($K100)) -> 0 | X100: =$F100 -> 14 | Y100: =$T100 -> 14
A101: 6.2.3 | B101: 3 | C101: Outbox retry, backoff, circuit breaker and dead letter queue | D101: External Integration | E101: INT | F101: 14 | G101: =IF($F101="","",Dashboard!$B$3+$F101-1) -> 46307 | H101: =IF($T101="","",Dashboard!$B$3+$T101-1) -> 46307 | I101: 1 | J101: 1.5 | L101: To do | M101: =IF($L101="Done",1,IF($L101="Doing",0.5,0)) -> 0 | P101: Provider outage does not lose an event | R101: 6.2 | S101: 6 | T101: =$F101+$I101-1 -> 14 | U101: =IF($L101="Deferred",0,$J101) -> 1.5 | V101: =IF($L101="Deferred",0,$J101*$M101) -> 0 | W101: =IF($L101="Deferred",0,N($K101)) -> 0 | X101: =$F101 -> 14 | Y101: =$T101 -> 14
...

Sheet Gantt
A1: SmartRail — Gantt
A2: Fully generated from the WBS sheet. Nothing to edit here. Bars: blue = planned, amber = in progress, green = done, red = blocked.
F3: =Dashboard!$B$3+1-1 -> 46294 | G3: =Dashboard!$B$3+2-1 -> 46295 | H3: =Dashboard!$B$3+3-1 -> 46296 | I3: =Dashboard!$B$3+4-1 -> 46297 | J3: =Dashboard!$B$3+5-1 -> 46298 | K3: =Dashboard!$B$3+6-1 -> 46299 | L3: =Dashboard!$B$3+7-1 -> 46300 | M3: =Dashboard!$B$3+8-1 -> 46301 | N3: =Dashboard!$B$3+9-1 -> 46302 | O3: =Dashboard!$B$3+10-1 -> 46303 | P3: =Dashboard!$B$3+11-1 -> 46304 | Q3: =Dashboard!$B$3+12-1 -> 46305 | R3: =Dashboard!$B$3+13-1 -> 46306 | S3: =Dashboard!$B$3+14-1 -> 46307 | T3: =Dashboard!$B$3+15-1 -> 46308 | U3: =Dashboard!$B$3+16-1 -> 46309 | V3: =Dashboard!$B$3+17-1 -> 46310 | W3: =Dashboard!$B$3+18-1 -> 46311 | X3: =Dashboard!$B$3+19-1 -> 46312 | Y3: =Dashboard!$B$3+20-1 -> 46313 | Z3: =Dashboard!$B$3+21-1 -> 46314
A4: WBS | B4: Work item | C4: WS | D4: Est h | E4: % Done | F4: D1 | G4: D2 | H4: D3 | I4: D4 | J4: D5 | K4: D6 | L4: D7 | M4: D8 | N4: D9 | O4: D10 | P4: D11 | Q4: D12 | R4: D13 | S4: D14 | T4: D15 | U4: D16 | V4: D17 | W4: D18 | X4: D19 | Y4: D20 | Z4: D21
A5: =WBS!$A5 -> 1 | B5: =WBS!$C5 -> Discovery | C5: =IF(WBS!$E5="","",WBS!$E5) | D5: =WBS!$J5 -> 28.5 | E5: =WBS!$M5 -> 0.10526316 | F5: =IF(OR(WBS!$F5="",WBS!$T5=""),"",IF(AND(1>=WBS!$F5,1<=WBS!$T5),IF(WBS!$L5="Done",3,IF(WBS!$L5="Doing",2,IF(WBS!$L5="Blocked",4,IF(WBS!$L5="Deferred",5,1)))),"")) -> 1 | G5: =IF(OR(WBS!$F5="",WBS!$T5=""),"",IF(AND(2>=WBS!$F5,2<=WBS!$T5),IF(WBS!$L5="Done",3,IF(WBS!$L5="Doing",2,IF(WBS!$L5="Blocked",4,IF(WBS!$L5="Deferred",5,1)))),"")) -> 1 | H5: =IF(OR(WBS!$F5="",WBS!$T5=""),"",IF(AND(3>=WBS!$F5,3<=WBS!$T5),IF(WBS!$L5="Done",3,IF(WBS!$L5="Doing",2,IF(WBS!$L5="Blocked",4,IF(WBS!$L5="Deferred",5,1)))),"")) -> 1 | I5: =IF(OR(WBS!$F5="",WBS!$T5=""),"",IF(AND(4>=WBS!$F5,4<=WBS!$T5),IF(WBS!$L5="Done",3,IF(WBS!$L5="Doing",2,IF(WBS!$L5="Blocked",4,IF(WBS!$L5="Deferred",5,1)))),"")) | J5: =IF(OR(WBS!$F5="",WBS!$T5=""),"",IF(AND(5>=WBS!$F5,5<=WBS!$T5),IF(WBS!$L5="Done",3,IF(WBS!$L5="Doing",2,IF(WBS!$L5="Blocked",4,IF(WBS!$L5="Deferred",5,1)))),"")) | K5: =IF(OR(WBS!$F5="",WBS!$T5=""),"",IF(AND(6>=WBS!$F5,6<=WBS!$T5),IF(WBS!$L5="Done",3,IF(WBS!$L5="Doing",2,IF(WBS!$L5="Blocked",4,IF(WBS!$L5="Deferred",5,1)))),"")) | L5: =IF(OR(WBS!$F5="",WBS!$T5=""),"",IF(AND(7>=WBS!$F5,7<=WBS!$T5),IF(WBS!$L5="Done",3,IF(WBS!$L5="Doing",2,IF(WBS!$L5="Blocked",4,IF(WBS!$L5="Deferred",5,1)))),"")) | M5: =IF(OR(WBS!$F5="",WBS!$T5=""),"",IF(AND(8>=WBS!$F5,8<=WBS!$T5),IF(WBS!$L5="Done",3,IF(WBS!$L5="Doing",2,IF(WBS!$L5="Blocked",4,IF(WBS!$L5="Deferred",5,1)))),"")) | N5: =IF(OR(WBS!$F5="",WBS!$T5=""),"",IF(AND(9>=WBS!$F5,9<=WBS!$T5),IF(WBS!$L5="Done",3,IF(WBS!$L5="Doing",2,IF(WBS!$L5="Blocked",4,IF(WBS!$L5="Deferred",5,1)))),"")) | O5: =IF(OR(WBS!$F5="",WBS!$T5=""),"",IF(AND(10>=WBS!$F5,10<=WBS!$T5),IF(WBS!$L5="Done",3,IF(WBS!$L5="Doing",2,IF(WBS!$L5="Blocked",4,IF(WBS!$L5="Deferred",5,1)))),"")) | P5: =IF(OR(WBS!$F5="",WBS!$T5=""),"",IF(AND(11>=WBS!$F5,11<=WBS!$T5),IF(WBS!$L5="Done",3,IF(WBS!$L5="Doing",2,IF(WBS!$L5="Blocked",4,IF(WBS!$L5="Deferred",5,1)))),"")) | Q5: =IF(OR(WBS!$F5="",WBS!$T5=""),"",IF(AND(12>=WBS!$F5,12<=WBS!$T5),IF(WBS!$L5="Done",3,IF(WBS!$L5="Doing",2,IF(WBS!$L5="Blocked",4,IF(WBS!$L5="Deferred",5,1)))),"")) | R5: =IF(OR(WBS!$F5="",WBS!$T5=""),"",IF(AND(13>=WBS!$F5,13<=WBS!$T5),IF(WBS!$L5="Done",3,IF(WBS!$L5="Doing",2,IF(WBS!$L5="Blocked",4,IF(WBS!$L5="Deferred",5,1)))),"")) | S5: =IF(OR(WBS!$F5="",WBS!$T5=""),"",IF(AND(14>=WBS!$F5,14<=WBS!$T5),IF(WBS!$L5="Done",3,IF(WBS!$L5="Doing",2,IF(WBS!$L5="Blocked",4,IF(WBS!$L5="Deferred",5,1)))),"")) | T5: =IF(OR(WBS!$F5="",WBS!$T5=""),"",IF(AND(15>=WBS!$F5,15<=WBS!$T5),IF(WBS!$L5="Done",3,IF(WBS!$L5="Doing",2,IF(WBS!$L5="Blocked",4,IF(WBS!$L5="Deferred",5,1)))),"")) | U5: =IF(OR(WBS!$F5="",WBS!$T5=""),"",IF(AND(16>=WBS!$F5,16<=WBS!$T5),IF(WBS!$L5="Done",3,IF(WBS!$L5="Doing",2,IF(WBS!$L5="Blocked",4,IF(WBS!$L5="Deferred",5,1)))),"")) | V5: =IF(OR(WBS!$F5="",WBS!$T5=""),"",IF(AND(17>=WBS!$F5,17<=WBS!$T5),IF(WBS!$L5="Done",3,IF(WBS!$L5="Doing",2,IF(WBS!$L5="Blocked",4,IF(WBS!$L5="Deferred",5,1)))),"")) | W5: =IF(OR(WBS!$F5="",WBS!$T5=""),"",IF(AND(18>=WBS!$F5,18<=WBS!$T5),IF(WBS!$L5="Done",3,IF(WBS!$L5="Doing",2,IF(WBS!$L5="Blocked",4,IF(WBS!$L5="Deferred",5,1)))),"")) | X5: =IF(OR(WBS!$F5="",WBS!$T5=""),"",IF(AND(19>=WBS!$F5,19<=WBS!$T5),IF(WBS!$L5="Done",3,IF(WBS!$L5="Doing",2,IF(WBS!$L5="Blocked",4,IF(WBS!$L5="Deferred",5,1)))),"")) | Y5: =IF(OR(WBS!$F5="",WBS!$T5=""),"",IF(AND(20>=WBS!$F5,20<=WBS!$T5),IF(WBS!$L5="Done",3,IF(WBS!$L5="Doing",2,IF(WBS!$L5="Blocked",4,IF(WBS!$L5="Deferred",5,1)))),"")) | Z5: =IF(OR(WBS!$F5="",WBS!$T5=""),"",IF(AND(21>=WBS!$F5,21<=WBS!$T5),IF(WBS!$L5="Done",3,IF(WBS!$L5="Doing",2,IF(WBS!$L5="Blocked",4,IF(WBS!$L5="Deferred",5,1)))),""))
A6: =WBS!$A6 -> 1.1 | B6: =WBS!$C6 -> Brief analysis and gap discovery | C6: =IF(WBS!$E6="","",WBS!$E6) | D6: =WBS!$J6 -> 6 | E6: =WBS!$M6 -> 0 | F6: =IF(OR(WBS!$F6="",WBS!$T6=""),"",IF(AND(1>=WBS!$F6,1<=WBS!$T6),IF(WBS!$L6="Done",3,IF(WBS!$L6="Doing",2,IF(WBS!$L6="Blocked",4,IF(WBS!$L6="Deferred",5,1)))),"")) -> 1 | G6: =IF(OR(WBS!$F6="",WBS!$T6=""),"",IF(AND(2>=WBS!$F6,2<=WBS!$T6),IF(WBS!$L6="Done",3,IF(WBS!$L6="Doing",2,IF(WBS!$L6="Blocked",4,IF(WBS!$L6="Deferred",5,1)))),"")) -> 1 | H6: =IF(OR(WBS!$F6="",WBS!$T6=""),"",IF(AND(3>=WBS!$F6,3<=WBS!$T6),IF(WBS!$L6="Done",3,IF(WBS!$L6="Doing",2,IF(WBS!$L6="Blocked",4,IF(WBS!$L6="Deferred",5,1)))),"")) | I6: =IF(OR(WBS!$F6="",WBS!$T6=""),"",IF(AND(4>=WBS!$F6,4<=WBS!$T6),IF(WBS!$L6="Done",3,IF(WBS!$L6="Doing",2,IF(WBS!$L6="Blocked",4,IF(WBS!$L6="Deferred",5,1)))),"")) | J6: =IF(OR(WBS!$F6="",WBS!$T6=""),"",IF(AND(5>=WBS!$F6,5<=WBS!$T6),IF(WBS!$L6="Done",3,IF(WBS!$L6="Doing",2,IF(WBS!$L6="Blocked",4,IF(WBS!$L6="Deferred",5,1)))),"")) | K6: =IF(OR(WBS!$F6="",WBS!$T6=""),"",IF(AND(6>=WBS!$F6,6<=WBS!$T6),IF(WBS!$L6="Done",3,IF(WBS!$L6="Doing",2,IF(WBS!$L6="Blocked",4,IF(WBS!$L6="Deferred",5,1)))),"")) | L6: =IF(OR(WBS!$F6="",WBS!$T6=""),"",IF(AND(7>=WBS!$F6,7<=WBS!$T6),IF(WBS!$L6="Done",3,IF(WBS!$L6="Doing",2,IF(WBS!$L6="Blocked",4,IF(WBS!$L6="Deferred",5,1)))),"")) | M6: =IF(OR(WBS!$F6="",WBS!$T6=""),"",IF(AND(8>=WBS!$F6,8<=WBS!$T6),IF(WBS!$L6="Done",3,IF(WBS!$L6="Doing",2,IF(WBS!$L6="Blocked",4,IF(WBS!$L6="Deferred",5,1)))),"")) | N6: =IF(OR(WBS!$F6="",WBS!$T6=""),"",IF(AND(9>=WBS!$F6,9<=WBS!$T6),IF(WBS!$L6="Done",3,IF(WBS!$L6="Doing",2,IF(WBS!$L6="Blocked",4,IF(WBS!$L6="Deferred",5,1)))),"")) | O6: =IF(OR(WBS!$F6="",WBS!$T6=""),"",IF(AND(10>=WBS!$F6,10<=WBS!$T6),IF(WBS!$L6="Done",3,IF(WBS!$L6="Doing",2,IF(WBS!$L6="Blocked",4,IF(WBS!$L6="Deferred",5,1)))),"")) | P6: =IF(OR(WBS!$F6="",WBS!$T6=""),"",IF(AND(11>=WBS!$F6,11<=WBS!$T6),IF(WBS!$L6="Done",3,IF(WBS!$L6="Doing",2,IF(WBS!$L6="Blocked",4,IF(WBS!$L6="Deferred",5,1)))),"")) | Q6: =IF(OR(WBS!$F6="",WBS!$T6=""),"",IF(AND(12>=WBS!$F6,12<=WBS!$T6),IF(WBS!$L6="Done",3,IF(WBS!$L6="Doing",2,IF(WBS!$L6="Blocked",4,IF(WBS!$L6="Deferred",5,1)))),"")) | R6: =IF(OR(WBS!$F6="",WBS!$T6=""),"",IF(AND(13>=WBS!$F6,13<=WBS!$T6),IF(WBS!$L6="Done",3,IF(WBS!$L6="Doing",2,IF(WBS!$L6="Blocked",4,IF(WBS!$L6="Deferred",5,1)))),"")) | S6: =IF(OR(WBS!$F6="",WBS!$T6=""),"",IF(AND(14>=WBS!$F6,14<=WBS!$T6),IF(WBS!$L6="Done",3,IF(WBS!$L6="Doing",2,IF(WBS!$L6="Blocked",4,IF(WBS!$L6="Deferred",5,1)))),"")) | T6: =IF(OR(WBS!$F6="",WBS!$T6=""),"",IF(AND(15>=WBS!$F6,15<=WBS!$T6),IF(WBS!$L6="Done",3,IF(WBS!$L6="Doing",2,IF(WBS!$L6="Blocked",4,IF(WBS!$L6="Deferred",5,1)))),"")) | U6: =IF(OR(WBS!$F6="",WBS!$T6=""),"",IF(AND(16>=WBS!$F6,16<=WBS!$T6),IF(WBS!$L6="Done",3,IF(WBS!$L6="Doing",2,IF(WBS!$L6="Blocked",4,IF(WBS!$L6="Deferred",5,1)))),"")) | V6: =IF(OR(WBS!$F6="",WBS!$T6=""),"",IF(AND(17>=WBS!$F6,17<=WBS!$T6),IF(WBS!$L6="Done",3,IF(WBS!$L6="Doing",2,IF(WBS!$L6="Blocked",4,IF(WBS!$L6="Deferred",5,1)))),"")) | W6: =IF(OR(WBS!$F6="",WBS!$T6=""),"",IF(AND(18>=WBS!$F6,18<=WBS!$T6),IF(WBS!$L6="Done",3,IF(WBS!$L6="Doing",2,IF(WBS!$L6="Blocked",4,IF(WBS!$L6="Deferred",5,1)))),"")) | X6: =IF(OR(WBS!$F6="",WBS!$T6=""),"",IF(AND(19>=WBS!$F6,19<=WBS!$T6),IF(WBS!$L6="Done",3,IF(WBS!$L6="Doing",2,IF(WBS!$L6="Blocked",4,IF(WBS!$L6="Deferred",5,1)))),"")) | Y6: =IF(OR(WBS!$F6="",WBS!$T6=""),"",IF(AND(20>=WBS!$F6,20<=WBS!$T6),IF(WBS!$L6="Done",3,IF(WBS!$L6="Doing",2,IF(WBS!$L6="Blocked",4,IF(WBS!$L6="Deferred",5,1)))),"")) | Z6: =IF(OR(WBS!$F6="",WBS!$T6=""),"",IF(AND(21>=WBS!$F6,21<=WBS!$T6),IF(WBS!$L6="Done",3,IF(WBS!$L6="Doing",2,IF(WBS!$L6="Blocked",4,IF(WBS!$L6="Deferred",5,1)))),""))
A7: =WBS!$A7 -> 1.1.1 | B7: =WBS!$C7 -> Decompose brief into atomic statements tagged GIVEN / IMPLIED / ABSENT | C7: =IF(WBS!$E7="","",WBS!$E7) -> REQ | D7: =WBS!$J7 -> 3 | E7: =WBS!$M7 -> 0 | F7: =IF(OR(WBS!$F7="",WBS!$T7=""),"",IF(AND(1>=WBS!$F7,1<=WBS!$T7),IF(WBS!$L7="Done",3,IF(WBS!$L7="Doing",2,IF(WBS!$L7="Blocked",4,IF(WBS!$L7="Deferred",5,1)))),"")) -> 1 | G7: =IF(OR(WBS!$F7="",WBS!$T7=""),"",IF(AND(2>=WBS!$F7,2<=WBS!$T7),IF(WBS!$L7="Done",3,IF(WBS!$L7="Doing",2,IF(WBS!$L7="Blocked",4,IF(WBS!$L7="Deferred",5,1)))),"")) | H7: =IF(OR(WBS!$F7="",WBS!$T7=""),"",IF(AND(3>=WBS!$F7,3<=WBS!$T7),IF(WBS!$L7="Done",3,IF(WBS!$L7="Doing",2,IF(WBS!$L7="Blocked",4,IF(WBS!$L7="Deferred",5,1)))),"")) | I7: =IF(OR(WBS!$F7="",WBS!$T7=""),"",IF(AND(4>=WBS!$F7,4<=WBS!$T7),IF(WBS!$L7="Done",3,IF(WBS!$L7="Doing",2,IF(WBS!$L7="Blocked",4,IF(WBS!$L7="Deferred",5,1)))),"")) | J7: =IF(OR(WBS!$F7="",WBS!$T7=""),"",IF(AND(5>=WBS!$F7,5<=WBS!$T7),IF(WBS!$L7="Done",3,IF(WBS!$L7="Doing",2,IF(WBS!$L7="Blocked",4,IF(WBS!$L7="Deferred",5,1)))),"")) | K7: =IF(OR(WBS!$F7="",WBS!$T7=""),"",IF(AND(6>=WBS!$F7,6<=WBS!$T7),IF(WBS!$L7="Done",3,IF(WBS!$L7="Doing",2,IF(WBS!$L7="Blocked",4,IF(WBS!$L7="Deferred",5,1)))),"")) | L7: =IF(OR(WBS!$F7="",WBS!$T7=""),"",IF(AND(7>=WBS!$F7,7<=WBS!$T7),IF(WBS!$L7="Done",3,IF(WBS!$L7="Doing",2,IF(WBS!$L7="Blocked",4,IF(WBS!$L7="Deferred",5,1)))),"")) | M7: =IF(OR(WBS!$F7="",WBS!$T7=""),"",IF(AND(8>=WBS!$F7,8<=WBS!$T7),IF(WBS!$L7="Done",3,IF(WBS!$L7="Doing",2,IF(WBS!$L7="Blocked",4,IF(WBS!$L7="Deferred",5,1)))),"")) | N7: =IF(OR(WBS!$F7="",WBS!$T7=""),"",IF(AND(9>=WBS!$F7,9<=WBS!$T7),IF(WBS!$L7="Done",3,IF(WBS!$L7="Doing",2,IF(WBS!$L7="Blocked",4,IF(WBS!$L7="Deferred",5,1)))),"")) | O7: =IF(OR(WBS!$F7="",WBS!$T7=""),"",IF(AND(10>=WBS!$F7,10<=WBS!$T7),IF(WBS!$L7="Done",3,IF(WBS!$L7="Doing",2,IF(WBS!$L7="Blocked",4,IF(WBS!$L7="Deferred",5,1)))),"")) | P7: =IF(OR(WBS!$F7="",WBS!$T7=""),"",IF(AND(11>=WBS!$F7,11<=WBS!$T7),IF(WBS!$L7="Done",3,IF(WBS!$L7="Doing",2,IF(WBS!$L7="Blocked",4,IF(WBS!$L7="Deferred",5,1)))),"")) | Q7: =IF(OR(WBS!$F7="",WBS!$T7=""),"",IF(AND(12>=WBS!$F7,12<=WBS!$T7),IF(WBS!$L7="Done",3,IF(WBS!$L7="Doing",2,IF(WBS!$L7="Blocked",4,IF(WBS!$L7="Deferred",5,1)))),"")) | R7: =IF(OR(WBS!$F7="",WBS!$T7=""),"",IF(AND(13>=WBS!$F7,13<=WBS!$T7),IF(WBS!$L7="Done",3,IF(WBS!$L7="Doing",2,IF(WBS!$L7="Blocked",4,IF(WBS!$L7="Deferred",5,1)))),"")) | S7: =IF(OR(WBS!$F7="",WBS!$T7=""),"",IF(AND(14>=WBS!$F7,14<=WBS!$T7),IF(WBS!$L7="Done",3,IF(WBS!$L7="Doing",2,IF(WBS!$L7="Blocked",4,IF(WBS!$L7="Deferred",5,1)))),"")) | T7: =IF(OR(WBS!$F7="",WBS!$T7=""),"",IF(AND(15>=WBS!$F7,15<=WBS!$T7),IF(WBS!$L7="Done",3,IF(WBS!$L7="Doing",2,IF(WBS!$L7="Blocked",4,IF(WBS!$L7="Deferred",5,1)))),"")) | U7: =IF(OR(WBS!$F7="",WBS!$T7=""),"",IF(AND(16>=WBS!$F7,16<=WBS!$T7),IF(WBS!$L7="Done",3,IF(WBS!$L7="Doing",2,IF(WBS!$L7="Blocked",4,IF(WBS!$L7="Deferred",5,1)))),"")) | V7: =IF(OR(WBS!$F7="",WBS!$T7=""),"",IF(AND(17>=WBS!$F7,17<=WBS!$T7),IF(WBS!$L7="Done",3,IF(WBS!$L7="Doing",2,IF(WBS!$L7="Blocked",4,IF(WBS!$L7="Deferred",5,1)))),"")) | W7: =IF(OR(WBS!$F7="",WBS!$T7=""),"",IF(AND(18>=WBS!$F7,18<=WBS!$T7),IF(WBS!$L7="Done",3,IF(WBS!$L7="Doing",2,IF(WBS!$L7="Blocked",4,IF(WBS!$L7="Deferred",5,1)))),"")) | X7: =IF(OR(WBS!$F7="",WBS!$T7=""),"",IF(AND(19>=WBS!$F7,19<=WBS!$T7),IF(WBS!$L7="Done",3,IF(WBS!$L7="Doing",2,IF(WBS!$L7="Blocked",4,IF(WBS!$L7="Deferred",5,1)))),"")) | Y7: =IF(OR(WBS!$F7="",WBS!$T7=""),"",IF(AND(20>=WBS!$F7,20<=WBS!$T7),IF(WBS!$L7="Done",3,IF(WBS!$L7="Doing",2,IF(WBS!$L7="Blocked",4,IF(WBS!$L7="Deferred",5,1)))),"")) | Z7: =IF(OR(WBS!$F7="",WBS!$T7=""),"",IF(AND(21>=WBS!$F7,21<=WBS!$T7),IF(WBS!$L7="Done",3,IF(WBS!$L7="Doing",2,IF(WBS!$L7="Blocked",4,IF(WBS!$L7="Deferred",5,1)))),""))
A8: =WBS!$A8 -> 1.1.2 | B8: =WBS!$C8 -> Convert plan section 6 findings into REQ / ASM / EDG / OQ entries | C8: =IF(WBS!$E8="","",WBS!$E8) -> REQ | D8: =WBS!$J8 -> 2 | E8: =WBS!$M8 -> 0 | F8: =IF(OR(WBS!$F8="",WBS!$T8=""),"",IF(AND(1>=WBS!$F8,1<=WBS!$T8),IF(WBS!$L8="Done",3,IF(WBS!$L8="Doing",2,IF(WBS!$L8="Blocked",4,IF(WBS!$L8="Deferred",5,1)))),"")) | G8: =IF(OR(WBS!$F8="",WBS!$T8=""),"",IF(AND(2>=WBS!$F8,2<=WBS!$T8),IF(WBS!$L8="Done",3,IF(WBS!$L8="Doing",2,IF(WBS!$L8="Blocked",4,IF(WBS!$L8="Deferred",5,1)))),"")) -> 1 | H8: =IF(OR(WBS!$F8="",WBS!$T8=""),"",IF(AND(3>=WBS!$F8,3<=WBS!$T8),IF(WBS!$L8="Done",3,IF(WBS!$L8="Doing",2,IF(WBS!$L8="Blocked",4,IF(WBS!$L8="Deferred",5,1)))),"")) | I8: =IF(OR(WBS!$F8="",WBS!$T8=""),"",IF(AND(4>=WBS!$F8,4<=WBS!$T8),IF(WBS!$L8="Done",3,IF(WBS!$L8="Doing",2,IF(WBS!$L8="Blocked",4,IF(WBS!$L8="Deferred",5,1)))),"")) | J8: =IF(OR(WBS!$F8="",WBS!$T8=""),"",IF(AND(5>=WBS!$F8,5<=WBS!$T8),IF(WBS!$L8="Done",3,IF(WBS!$L8="Doing",2,IF(WBS!$L8="Blocked",4,IF(WBS!$L8="Deferred",5,1)))),"")) | K8: =IF(OR(WBS!$F8="",WBS!$T8=""),"",IF(AND(6>=WBS!$F8,6<=WBS!$T8),IF(WBS!$L8="Done",3,IF(WBS!$L8="Doing",2,IF(WBS!$L8="Blocked",4,IF(WBS!$L8="Deferred",5,1)))),"")) | L8: =IF(OR(WBS!$F8="",WBS!$T8=""),"",IF(AND(7>=WBS!$F8,7<=WBS!$T8),IF(WBS!$L8="Done",3,IF(WBS!$L8="Doing",2,IF(WBS!$L8="Blocked",4,IF(WBS!$L8="Deferred",5,1)))),"")) | M8: =IF(OR(WBS!$F8="",WBS!$T8=""),"",IF(AND(8>=WBS!$F8,8<=WBS!$T8),IF(WBS!$L8="Done",3,IF(WBS!$L8="Doing",2,IF(WBS!$L8="Blocked",4,IF(WBS!$L8="Deferred",5,1)))),"")) | N8: =IF(OR(WBS!$F8="",WBS!$T8=""),"",IF(AND(9>=WBS!$F8,9<=WBS!$T8),IF(WBS!$L8="Done",3,IF(WBS!$L8="Doing",2,IF(WBS!$L8="Blocked",4,IF(WBS!$L8="Deferred",5,1)))),"")) | O8: =IF(OR(WBS!$F8="",WBS!$T8=""),"",IF(AND(10>=WBS!$F8,10<=WBS!$T8),IF(WBS!$L8="Done",3,IF(WBS!$L8="Doing",2,IF(WBS!$L8="Blocked",4,IF(WBS!$L8="Deferred",5,1)))),"")) | P8: =IF(OR(WBS!$F8="",WBS!$T8=""),"",IF(AND(11>=WBS!$F8,11<=WBS!$T8),IF(WBS!$L8="Done",3,IF(WBS!$L8="Doing",2,IF(WBS!$L8="Blocked",4,IF(WBS!$L8="Deferred",5,1)))),"")) | Q8: =IF(OR(WBS!$F8="",WBS!$T8=""),"",IF(AND(12>=WBS!$F8,12<=WBS!$T8),IF(WBS!$L8="Done",3,IF(WBS!$L8="Doing",2,IF(WBS!$L8="Blocked",4,IF(WBS!$L8="Deferred",5,1)))),"")) | R8: =IF(OR(WBS!$F8="",WBS!$T8=""),"",IF(AND(13>=WBS!$F8,13<=WBS!$T8),IF(WBS!$L8="Done",3,IF(WBS!$L8="Doing",2,IF(WBS!$L8="Blocked",4,IF(WBS!$L8="Deferred",5,1)))),"")) | S8: =IF(OR(WBS!$F8="",WBS!$T8=""),"",IF(AND(14>=WBS!$F8,14<=WBS!$T8),IF(WBS!$L8="Done",3,IF(WBS!$L8="Doing",2,IF(WBS!$L8="Blocked",4,IF(WBS!$L8="Deferred",5,1)))),"")) | T8: =IF(OR(WBS!$F8="",WBS!$T8=""),"",IF(AND(15>=WBS!$F8,15<=WBS!$T8),IF(WBS!$L8="Done",3,IF(WBS!$L8="Doing",2,IF(WBS!$L8="Blocked",4,IF(WBS!$L8="Deferred",5,1)))),"")) | U8: =IF(OR(WBS!$F8="",WBS!$T8=""),"",IF(AND(16>=WBS!$F8,16<=WBS!$T8),IF(WBS!$L8="Done",3,IF(WBS!$L8="Doing",2,IF(WBS!$L8="Blocked",4,IF(WBS!$L8="Deferred",5,1)))),"")) | V8: =IF(OR(WBS!$F8="",WBS!$T8=""),"",IF(AND(17>=WBS!$F8,17<=WBS!$T8),IF(WBS!$L8="Done",3,IF(WBS!$L8="Doing",2,IF(WBS!$L8="Blocked",4,IF(WBS!$L8="Deferred",5,1)))),"")) | W8: =IF(OR(WBS!$F8="",WBS!$T8=""),"",IF(AND(18>=WBS!$F8,18<=WBS!$T8),IF(WBS!$L8="Done",3,IF(WBS!$L8="Doing",2,IF(WBS!$L8="Blocked",4,IF(WBS!$L8="Deferred",5,1)))),"")) | X8: =IF(OR(WBS!$F8="",WBS!$T8=""),"",IF(AND(19>=WBS!$F8,19<=WBS!$T8),IF(WBS!$L8="Done",3,IF(WBS!$L8="Doing",2,IF(WBS!$L8="Blocked",4,IF(WBS!$L8="Deferred",5,1)))),"")) | Y8: =IF(OR(WBS!$F8="",WBS!$T8=""),"",IF(AND(20>=WBS!$F8,20<=WBS!$T8),IF(WBS!$L8="Done",3,IF(WBS!$L8="Doing",2,IF(WBS!$L8="Blocked",4,IF(WBS!$L8="Deferred",5,1)))),"")) | Z8: =IF(OR(WBS!$F8="",WBS!$T8=""),"",IF(AND(21>=WBS!$F8,21<=WBS!$T8),IF(WBS!$L8="Done",3,IF(WBS!$L8="Doing",2,IF(WBS!$L8="Blocked",4,IF(WBS!$L8="Deferred",5,1)))),""))
A9: =WBS!$A9 -> 1.1.3 | B9: =WBS!$C9 -> Assumptions register with rationale | C9: =IF(WBS!$E9="","",WBS!$E9) -> REQ | D9: =WBS!$J9 -> 1 | E9: =WBS!$M9 -> 0 | F9: =IF(OR(WBS!$F9="",WBS!$T9=""),"",IF(AND(1>=WBS!$F9,1<=WBS!$T9),IF(WBS!$L9="Done",3,IF(WBS!$L9="Doing",2,IF(WBS!$L9="Blocked",4,IF(WBS!$L9="Deferred",5,1)))),"")) | G9: =IF(OR(WBS!$F9="",WBS!$T9=""),"",IF(AND(2>=WBS!$F9,2<=WBS!$T9),IF(WBS!$L9="Done",3,IF(WBS!$L9="Doing",2,IF(WBS!$L9="Blocked",4,IF(WBS!$L9="Deferred",5,1)))),"")) -> 1 | H9: =IF(OR(WBS!$F9="",WBS!$T9=""),"",IF(AND(3>=WBS!$F9,3<=WBS!$T9),IF(WBS!$L9="Done",3,IF(WBS!$L9="Doing",2,IF(WBS!$L9="Blocked",4,IF(WBS!$L9="Deferred",5,1)))),"")) | I9: =IF(OR(WBS!$F9="",WBS!$T9=""),"",IF(AND(4>=WBS!$F9,4<=WBS!$T9),IF(WBS!$L9="Done",3,IF(WBS!$L9="Doing",2,IF(WBS!$L9="Blocked",4,IF(WBS!$L9="Deferred",5,1)))),"")) | J9: =IF(OR(WBS!$F9="",WBS!$T9=""),"",IF(AND(5>=WBS!$F9,5<=WBS!$T9),IF(WBS!$L9="Done",3,IF(WBS!$L9="Doing",2,IF(WBS!$L9="Blocked",4,IF(WBS!$L9="Deferred",5,1)))),"")) | K9: =IF(OR(WBS!$F9="",WBS!$T9=""),"",IF(AND(6>=WBS!$F9,6<=WBS!$T9),IF(WBS!$L9="Done",3,IF(WBS!$L9="Doing",2,IF(WBS!$L9="Blocked",4,IF(WBS!$L9="Deferred",5,1)))),"")) | L9: =IF(OR(WBS!$F9="",WBS!$T9=""),"",IF(AND(7>=WBS!$F9,7<=WBS!$T9),IF(WBS!$L9="Done",3,IF(WBS!$L9="Doing",2,IF(WBS!$L9="Blocked",4,IF(WBS!$L9="Deferred",5,1)))),"")) | M9: =IF(OR(WBS!$F9="",WBS!$T9=""),"",IF(AND(8>=WBS!$F9,8<=WBS!$T9),IF(WBS!$L9="Done",3,IF(WBS!$L9="Doing",2,IF(WBS!$L9="Blocked",4,IF(WBS!$L9="Deferred",5,1)))),"")) | N9: =IF(OR(WBS!$F9="",WBS!$T9=""),"",IF(AND(9>=WBS!$F9,9<=WBS!$T9),IF(WBS!$L9="Done",3,IF(WBS!$L9="Doing",2,IF(WBS!$L9="Blocked",4,IF(WBS!$L9="Deferred",5,1)))),"")) | O9: =IF(OR(WBS!$F9="",WBS!$T9=""),"",IF(AND(10>=WBS!$F9,10<=WBS!$T9),IF(WBS!$L9="Done",3,IF(WBS!$L9="Doing",2,IF(WBS!$L9="Blocked",4,IF(WBS!$L9="Deferred",5,1)))),"")) | P9: =IF(OR(WBS!$F9="",WBS!$T9=""),"",IF(AND(11>=WBS!$F9,11<=WBS!$T9),IF(WBS!$L9="Done",3,IF(WBS!$L9="Doing",2,IF(WBS!$L9="Blocked",4,IF(WBS!$L9="Deferred",5,1)))),"")) | Q9: =IF(OR(WBS!$F9="",WBS!$T9=""),"",IF(AND(12>=WBS!$F9,12<=WBS!$T9),IF(WBS!$L9="Done",3,IF(WBS!$L9="Doing",2,IF(WBS!$L9="Blocked",4,IF(WBS!$L9="Deferred",5,1)))),"")) | R9: =IF(OR(WBS!$F9="",WBS!$T9=""),"",IF(AND(13>=WBS!$F9,13<=WBS!$T9),IF(WBS!$L9="Done",3,IF(WBS!$L9="Doing",2,IF(WBS!$L9="Blocked",4,IF(WBS!$L9="Deferred",5,1)))),"")) | S9: =IF(OR(WBS!$F9="",WBS!$T9=""),"",IF(AND(14>=WBS!$F9,14<=WBS!$T9),IF(WBS!$L9="Done",3,IF(WBS!$L9="Doing",2,IF(WBS!$L9="Blocked",4,IF(WBS!$L9="Deferred",5,1)))),"")) | T9: =IF(OR(WBS!$F9="",WBS!$T9=""),"",IF(AND(15>=WBS!$F9,15<=WBS!$T9),IF(WBS!$L9="Done",3,IF(WBS!$L9="Doing",2,IF(WBS!$L9="Blocked",4,IF(WBS!$L9="Deferred",5,1)))),"")) | U9: =IF(OR(WBS!$F9="",WBS!$T9=""),"",IF(AND(16>=WBS!$F9,16<=WBS!$T9),IF(WBS!$L9="Done",3,IF(WBS!$L9="Doing",2,IF(WBS!$L9="Blocked",4,IF(WBS!$L9="Deferred",5,1)))),"")) | V9: =IF(OR(WBS!$F9="",WBS!$T9=""),"",IF(AND(17>=WBS!$F9,17<=WBS!$T9),IF(WBS!$L9="Done",3,IF(WBS!$L9="Doing",2,IF(WBS!$L9="Blocked",4,IF(WBS!$L9="Deferred",5,1)))),"")) | W9: =IF(OR(WBS!$F9="",WBS!$T9=""),"",IF(AND(18>=WBS!$F9,18<=WBS!$T9),IF(WBS!$L9="Done",3,IF(WBS!$L9="Doing",2,IF(WBS!$L9="Blocked",4,IF(WBS!$L9="Deferred",5,1)))),"")) | X9: =IF(OR(WBS!$F9="",WBS!$T9=""),"",IF(AND(19>=WBS!$F9,19<=WBS!$T9),IF(WBS!$L9="Done",3,IF(WBS!$L9="Doing",2,IF(WBS!$L9="Blocked",4,IF(WBS!$L9="Deferred",5,1)))),"")) | Y9: =IF(OR(WBS!$F9="",WBS!$T9=""),"",IF(AND(20>=WBS!$F9,20<=WBS!$T9),IF(WBS!$L9="Done",3,IF(WBS!$L9="Doing",2,IF(WBS!$L9="Blocked",4,IF(WBS!$L9="Deferred",5,1)))),"")) | Z9: =IF(OR(WBS!$F9="",WBS!$T9=""),"",IF(AND(21>=WBS!$F9,21<=WBS!$T9),IF(WBS!$L9="Done",3,IF(WBS!$L9="Doing",2,IF(WBS!$L9="Blocked",4,IF(WBS!$L9="Deferred",5,1)))),""))
A10: =WBS!$A10 -> 1.2 | B10: =WBS!$C10 -> Stakeholder simulation | C10: =IF(WBS!$E10="","",WBS!$E10) | D10: =WBS!$J10 -> 10 | E10: =WBS!$M10 -> 0 | F10: =IF(OR(WBS!$F10="",WBS!$T10=""),"",IF(AND(1>=WBS!$F10,1<=WBS!$T10),IF(WBS!$L10="Done",3,IF(WBS!$L10="Doing",2,IF(WBS!$L10="Blocked",4,IF(WBS!$L10="Deferred",5,1)))),"")) -> 1 | G10: =IF(OR(WBS!$F10="",WBS!$T10=""),"",IF(AND(2>=WBS!$F10,2<=WBS!$T10),IF(WBS!$L10="Done",3,IF(WBS!$L10="Doing",2,IF(WBS!$L10="Blocked",4,IF(WBS!$L10="Deferred",5,1)))),"")) -> 1 | H10: =IF(OR(WBS!$F10="",WBS!$T10=""),"",IF(AND(3>=WBS!$F10,3<=WBS!$T10),IF(WBS!$L10="Done",3,IF(WBS!$L10="Doing",2,IF(WBS!$L10="Blocked",4,IF(WBS!$L10="Deferred",5,1)))),"")) -> 1 | I10: =IF(OR(WBS!$F10="",WBS!$T10=""),"",IF(AND(4>=WBS!$F10,4<=WBS!$T10),IF(WBS!$L10="Done",3,IF(WBS!$L10="Doing",2,IF(WBS!$L10="Blocked",4,IF(WBS!$L10="Deferred",5,1)))),"")) | J10: =IF(OR(WBS!$F10="",WBS!$T10=""),"",IF(AND(5>=WBS!$F10,5<=WBS!$T10),IF(WBS!$L10="Done",3,IF(WBS!$L10="Doing",2,IF(WBS!$L10="Blocked",4,IF(WBS!$L10="Deferred",5,1)))),"")) | K10: =IF(OR(WBS!$F10="",WBS!$T10=""),"",IF(AND(6>=WBS!$F10,6<=WBS!$T10),IF(WBS!$L10="Done",3,IF(WBS!$L10="Doing",2,IF(WBS!$L10="Blocked",4,IF(WBS!$L10="Deferred",5,1)))),"")) | L10: =IF(OR(WBS!$F10="",WBS!$T10=""),"",IF(AND(7>=WBS!$F10,7<=WBS!$T10),IF(WBS!$L10="Done",3,IF(WBS!$L10="Doing",2,IF(WBS!$L10="Blocked",4,IF(WBS!$L10="Deferred",5,1)))),"")) | M10: =IF(OR(WBS!$F10="",WBS!$T10=""),"",IF(AND(8>=WBS!$F10,8<=WBS!$T10),IF(WBS!$L10="Done",3,IF(WBS!$L10="Doing",2,IF(WBS!$L10="Blocked",4,IF(WBS!$L10="Deferred",5,1)))),"")) | N10: =IF(OR(WBS!$F10="",WBS!$T10=""),"",IF(AND(9>=WBS!$F10,9<=WBS!$T10),IF(WBS!$L10="Done",3,IF(WBS!$L10="Doing",2,IF(WBS!$L10="Blocked",4,IF(WBS!$L10="Deferred",5,1)))),"")) | O10: =IF(OR(WBS!$F10="",WBS!$T10=""),"",IF(AND(10>=WBS!$F10,10<=WBS!$T10),IF(WBS!$L10="Done",3,IF(WBS!$L10="Doing",2,IF(WBS!$L10="Blocked",4,IF(WBS!$L10="Deferred",5,1)))),"")) | P10: =IF(OR(WBS!$F10="",WBS!$T10=""),"",IF(AND(11>=WBS!$F10,11<=WBS!$T10),IF(WBS!$L10="Done",3,IF(WBS!$L10="Doing",2,IF(WBS!$L10="Blocked",4,IF(WBS!$L10="Deferred",5,1)))),"")) | Q10: =IF(OR(WBS!$F10="",WBS!$T10=""),"",IF(AND(12>=WBS!$F10,12<=WBS!$T10),IF(WBS!$L10="Done",3,IF(WBS!$L10="Doing",2,IF(WBS!$L10="Blocked",4,IF(WBS!$L10="Deferred",5,1)))),"")) | R10: =IF(OR(WBS!$F10="",WBS!$T10=""),"",IF(AND(13>=WBS!$F10,13<=WBS!$T10),IF(WBS!$L10="Done",3,IF(WBS!$L10="Doing",2,IF(WBS!$L10="Blocked",4,IF(WBS!$L10="Deferred",5,1)))),"")) | S10: =IF(OR(WBS!$F10="",WBS!$T10=""),"",IF(AND(14>=WBS!$F10,14<=WBS!$T10),IF(WBS!$L10="Done",3,IF(WBS!$L10="Doing",2,IF(WBS!$L10="Blocked",4,IF(WBS!$L10="Deferred",5,1)))),"")) | T10: =IF(OR(WBS!$F10="",WBS!$T10=""),"",IF(AND(15>=WBS!$F10,15<=WBS!$T10),IF(WBS!$L10="Done",3,IF(WBS!$L10="Doing",2,IF(WBS!$L10="Blocked",4,IF(WBS!$L10="Deferred",5,1)))),"")) | U10: =IF(OR(WBS!$F10="",WBS!$T10=""),"",IF(AND(16>=WBS!$F10,16<=WBS!$T10),IF(WBS!$L10="Done",3,IF(WBS!$L10="Doing",2,IF(WBS!$L10="Blocked",4,IF(WBS!$L10="Deferred",5,1)))),"")) | V10: =IF(OR(WBS!$F10="",WBS!$T10=""),"",IF(AND(17>=WBS!$F10,17<=WBS!$T10),IF(WBS!$L10="Done",3,IF(WBS!$L10="Doing",2,IF(WBS!$L10="Blocked",4,IF(WBS!$L10="Deferred",5,1)))),"")) | W10: =IF(OR(WBS!$F10="",WBS!$T10=""),"",IF(AND(18>=WBS!$F10,18<=WBS!$T10),IF(WBS!$L10="Done",3,IF(WBS!$L10="Doing",2,IF(WBS!$L10="Blocked",4,IF(WBS!$L10="Deferred",5,1)))),"")) | X10: =IF(OR(WBS!$F10="",WBS!$T10=""),"",IF(AND(19>=WBS!$F10,19<=WBS!$T10),IF(WBS!$L10="Done",3,IF(WBS!$L10="Doing",2,IF(WBS!$L10="Blocked",4,IF(WBS!$L10="Deferred",5,1)))),"")) | Y10: =IF(OR(WBS!$F10="",WBS!$T10=""),"",IF(AND(20>=WBS!$F10,20<=WBS!$T10),IF(WBS!$L10="Done",3,IF(WBS!$L10="Doing",2,IF(WBS!$L10="Blocked",4,IF(WBS!$L10="Deferred",5,1)))),"")) | Z10: =IF(OR(WBS!$F10="",WBS!$T10=""),"",IF(AND(21>=WBS!$F10,21<=WBS!$T10),IF(WBS!$L10="Done",3,IF(WBS!$L10="Doing",2,IF(WBS!$L10="Blocked",4,IF(WBS!$L10="Deferred",5,1)))),""))
A11: =WBS!$A11 -> 1.2.1 | B11: =WBS!$C11 -> Persona interviews 1-6 commuter, traveller, impaired passenger, driver, station manager, controller | C11: =IF(WBS!$E11="","",WBS!$E11) -> REQ | D11: =WBS!$J11 -> 3 | E11: =WBS!$M11 -> 0 | F11: =IF(OR(WBS!$F11="",WBS!$T11=""),"",IF(AND(1>=WBS!$F11,1<=WBS!$T11),IF(WBS!$L11="Done",3,IF(WBS!$L11="Doing",2,IF(WBS!$L11="Blocked",4,IF(WBS!$L11="Deferred",5,1)))),"")) -> 1 | G11: =IF(OR(WBS!$F11="",WBS!$T11=""),"",IF(AND(2>=WBS!$F11,2<=WBS!$T11),IF(WBS!$L11="Done",3,IF(WBS!$L11="Doing",2,IF(WBS!$L11="Blocked",4,IF(WBS!$L11="Deferred",5,1)))),"")) | H11: =IF(OR(WBS!$F11="",WBS!$T11=""),"",IF(AND(3>=WBS!$F11,3<=WBS!$T11),IF(WBS!$L11="Done",3,IF(WBS!$L11="Doing",2,IF(WBS!$L11="Blocked",4,IF(WBS!$L11="Deferred",5,1)))),"")) | I11: =IF(OR(WBS!$F11="",WBS!$T11=""),"",IF(AND(4>=WBS!$F11,4<=WBS!$T11),IF(WBS!$L11="Done",3,IF(WBS!$L11="Doing",2,IF(WBS!$L11="Blocked",4,IF(WBS!$L11="Deferred",5,1)))),"")) | J11: =IF(OR(WBS!$F11="",WBS!$T11=""),"",IF(AND(5>=WBS!$F11,5<=WBS!$T11),IF(WBS!$L11="Done",3,IF(WBS!$L11="Doing",2,IF(WBS!$L11="Blocked",4,IF(WBS!$L11="Deferred",5,1)))),"")) | K11: =IF(OR(WBS!$F11="",WBS!$T11=""),"",IF(AND(6>=WBS!$F11,6<=WBS!$T11),IF(WBS!$L11="Done",3,IF(WBS!$L11="Doing",2,IF(WBS!$L11="Blocked",4,IF(WBS!$L11="Deferred",5,1)))),"")) | L11: =IF(OR(WBS!$F11="",WBS!$T11=""),"",IF(AND(7>=WBS!$F11,7<=WBS!$T11),IF(WBS!$L11="Done",3,IF(WBS!$L11="Doing",2,IF(WBS!$L11="Blocked",4,IF(WBS!$L11="Deferred",5,1)))),"")) | M11: =IF(OR(WBS!$F11="",WBS!$T11=""),"",IF(AND(8>=WBS!$F11,8<=WBS!$T11),IF(WBS!$L11="Done",3,IF(WBS!$L11="Doing",2,IF(WBS!$L11="Blocked",4,IF(WBS!$L11="Deferred",5,1)))),"")) | N11: =IF(OR(WBS!$F11="",WBS!$T11=""),"",IF(AND(9>=WBS!$F11,9<=WBS!$T11),IF(WBS!$L11="Done",3,IF(WBS!$L11="Doing",2,IF(WBS!$L11="Blocked",4,IF(WBS!$L11="Deferred",5,1)))),"")) | O11: =IF(OR(WBS!$F11="",WBS!$T11=""),"",IF(AND(10>=WBS!$F11,10<=WBS!$T11),IF(WBS!$L11="Done",3,IF(WBS!$L11="Doing",2,IF(WBS!$L11="Blocked",4,IF(WBS!$L11="Deferred",5,1)))),"")) | P11: =IF(OR(WBS!$F11="",WBS!$T11=""),"",IF(AND(11>=WBS!$F11,11<=WBS!$T11),IF(WBS!$L11="Done",3,IF(WBS!$L11="Doing",2,IF(WBS!$L11="Blocked",4,IF(WBS!$L11="Deferred",5,1)))),"")) | Q11: =IF(OR(WBS!$F11="",WBS!$T11=""),"",IF(AND(12>=WBS!$F11,12<=WBS!$T11),IF(WBS!$L11="Done",3,IF(WBS!$L11="Doing",2,IF(WBS!$L11="Blocked",4,IF(WBS!$L11="Deferred",5,1)))),"")) | R11: =IF(OR(WBS!$F11="",WBS!$T11=""),"",IF(AND(13>=WBS!$F11,13<=WBS!$T11),IF(WBS!$L11="Done",3,IF(WBS!$L11="Doing",2,IF(WBS!$L11="Blocked",4,IF(WBS!$L11="Deferred",5,1)))),"")) | S11: =IF(OR(WBS!$F11="",WBS!$T11=""),"",IF(AND(14>=WBS!$F11,14<=WBS!$T11),IF(WBS!$L11="Done",3,IF(WBS!$L11="Doing",2,IF(WBS!$L11="Blocked",4,IF(WBS!$L11="Deferred",5,1)))),"")) | T11: =IF(OR(WBS!$F11="",WBS!$T11=""),"",IF(AND(15>=WBS!$F11,15<=WBS!$T11),IF(WBS!$L11="Done",3,IF(WBS!$L11="Doing",2,IF(WBS!$L11="Blocked",4,IF(WBS!$L11="Deferred",5,1)))),"")) | U11: =IF(OR(WBS!$F11="",WBS!$T11=""),"",IF(AND(16>=WBS!$F11,16<=WBS!$T11),IF(WBS!$L11="Done",3,IF(WBS!$L11="Doing",2,IF(WBS!$L11="Blocked",4,IF(WBS!$L11="Deferred",5,1)))),"")) | V11: =IF(OR(WBS!$F11="",WBS!$T11=""),"",IF(AND(17>=WBS!$F11,17<=WBS!$T11),IF(WBS!$L11="Done",3,IF(WBS!$L11="Doing",2,IF(WBS!$L11="Blocked",4,IF(WBS!$L11="Deferred",5,1)))),"")) | W11: =IF(OR(WBS!$F11="",WBS!$T11=""),"",IF(AND(18>=WBS!$F11,18<=WBS!$T11),IF(WBS!$L11="Done",3,IF(WBS!$L11="Doing",2,IF(WBS!$L11="Blocked",4,IF(WBS!$L11="Deferred",5,1)))),"")) | X11: =IF(OR(WBS!$F11="",WBS!$T11=""),"",IF(AND(19>=WBS!$F11,19<=WBS!$T11),IF(WBS!$L11="Done",3,IF(WBS!$L11="Doing",2,IF(WBS!$L11="Blocked",4,IF(WBS!$L11="Deferred",5,1)))),"")) | Y11: =IF(OR(WBS!$F11="",WBS!$T11=""),"",IF(AND(20>=WBS!$F11,20<=WBS!$T11),IF(WBS!$L11="Done",3,IF(WBS!$L11="Doing",2,IF(WBS!$L11="Blocked",4,IF(WBS!$L11="Deferred",5,1)))),"")) | Z11: =IF(OR(WBS!$F11="",WBS!$T11=""),"",IF(AND(21>=WBS!$F11,21<=WBS!$T11),IF(WBS!$L11="Done",3,IF(WBS!$L11="Doing",2,IF(WBS!$L11="Blocked",4,IF(WBS!$L11="Deferred",5,1)))),""))
A12: =WBS!$A12 -> 1.2.2 | B12: =WBS!$C12 -> Persona interviews 7-12 CS agent, catering ops, security, QA, accessibility, DPO | C12: =IF(WBS!$E12="","",WBS!$E12) -> REQ | D12: =WBS!$J12 -> 3 | E12: =WBS!$M12 -> 0 | F12: =IF(OR(WBS!$F12="",WBS!$T12=""),"",IF(AND(1>=WBS!$F12,1<=WBS!$T12),IF(WBS!$L12="Done",3,IF(WBS!$L12="Doing",2,IF(WBS!$L12="Blocked",4,IF(WBS!$L12="Deferred",5,1)))),"")) | G12: =IF(OR(WBS!$F12="",WBS!$T12=""),"",IF(AND(2>=WBS!$F12,2<=WBS!$T12),IF(WBS!$L12="Done",3,IF(WBS!$L12="Doing",2,IF(WBS!$L12="Blocked",4,IF(WBS!$L12="Deferred",5,1)))),"")) -> 1 | H12: =IF(OR(WBS!$F12="",WBS!$T12=""),"",IF(AND(3>=WBS!$F12,3<=WBS!$T12),IF(WBS!$L12="Done",3,IF(WBS!$L12="Doing",2,IF(WBS!$L12="Blocked",4,IF(WBS!$L12="Deferred",5,1)))),"")) | I12: =IF(OR(WBS!$F12="",WBS!$T12=""),"",IF(AND(4>=WBS!$F12,4<=WBS!$T12),IF(WBS!$L12="Done",3,IF(WBS!$L12="Doing",2,IF(WBS!$L12="Blocked",4,IF(WBS!$L12="Deferred",5,1)))),"")) | J12: =IF(OR(WBS!$F12="",WBS!$T12=""),"",IF(AND(5>=WBS!$F12,5<=WBS!$T12),IF(WBS!$L12="Done",3,IF(WBS!$L12="Doing",2,IF(WBS!$L12="Blocked",4,IF(WBS!$L12="Deferred",5,1)))),"")) | K12: =IF(OR(WBS!$F12="",WBS!$T12=""),"",IF(AND(6>=WBS!$F12,6<=WBS!$T12),IF(WBS!$L12="Done",3,IF(WBS!$L12="Doing",2,IF(WBS!$L12="Blocked",4,IF(WBS!$L12="Deferred",5,1)))),"")) | L12: =IF(OR(WBS!$F12="",WBS!$T12=""),"",IF(AND(7>=WBS!$F12,7<=WBS!$T12),IF(WBS!$L12="Done",3,IF(WBS!$L12="Doing",2,IF(WBS!$L12="Blocked",4,IF(WBS!$L12="Deferred",5,1)))),"")) | M12: =IF(OR(WBS!$F12="",WBS!$T12=""),"",IF(AND(8>=WBS!$F12,8<=WBS!$T12),IF(WBS!$L12="Done",3,IF(WBS!$L12="Doing",2,IF(WBS!$L12="Blocked",4,IF(WBS!$L12="Deferred",5,1)))),"")) | N12: =IF(OR(WBS!$F12="",WBS!$T12=""),"",IF(AND(9>=WBS!$F12,9<=WBS!$T12),IF(WBS!$L12="Done",3,IF(WBS!$L12="Doing",2,IF(WBS!$L12="Blocked",4,IF(WBS!$L12="Deferred",5,1)))),"")) | O12: =IF(OR(WBS!$F12="",WBS!$T12=""),"",IF(AND(10>=WBS!$F12,10<=WBS!$T12),IF(WBS!$L12="Done",3,IF(WBS!$L12="Doing",2,IF(WBS!$L12="Blocked",4,IF(WBS!$L12="Deferred",5,1)))),"")) | P12: =IF(OR(WBS!$F12="",WBS!$T12=""),"",IF(AND(11>=WBS!$F12,11<=WBS!$T12),IF(WBS!$L12="Done",3,IF(WBS!$L12="Doing",2,IF(WBS!$L12="Blocked",4,IF(WBS!$L12="Deferred",5,1)))),"")) | Q12: =IF(OR(WBS!$F12="",WBS!$T12=""),"",IF(AND(12>=WBS!$F12,12<=WBS!$T12),IF(WBS!$L12="Done",3,IF(WBS!$L12="Doing",2,IF(WBS!$L12="Blocked",4,IF(WBS!$L12="Deferred",5,1)))),"")) | R12: =IF(OR(WBS!$F12="",WBS!$T12=""),"",IF(AND(13>=WBS!$F12,13<=WBS!$T12),IF(WBS!$L12="Done",3,IF(WBS!$L12="Doing",2,IF(WBS!$L12="Blocked",4,IF(WBS!$L12="Deferred",5,1)))),"")) | S12: =IF(OR(WBS!$F12="",WBS!$T12=""),"",IF(AND(14>=WBS!$F12,14<=WBS!$T12),IF(WBS!$L12="Done",3,IF(WBS!$L12="Doing",2,IF(WBS!$L12="Blocked",4,IF(WBS!$L12="Deferred",5,1)))),"")) | T12: =IF(OR(WBS!$F12="",WBS!$T12=""),"",IF(AND(15>=WBS!$F12,15<=WBS!$T12),IF(WBS!$L12="Done",3,IF(WBS!$L12="Doing",2,IF(WBS!$L12="Blocked",4,IF(WBS!$L12="Deferred",5,1)))),"")) | U12: =IF(OR(WBS!$F12="",WBS!$T12=""),"",IF(AND(16>=WBS!$F12,16<=WBS!$T12),IF(WBS!$L12="Done",3,IF(WBS!$L12="Doing",2,IF(WBS!$L12="Blocked",4,IF(WBS!$L12="Deferred",5,1)))),"")) | V12: =IF(OR(WBS!$F12="",WBS!$T12=""),"",IF(AND(17>=WBS!$F12,17<=WBS!$T12),IF(WBS!$L12="Done",3,IF(WBS!$L12="Doing",2,IF(WBS!$L12="Blocked",4,IF(WBS!$L12="Deferred",5,1)))),"")) | W12: =IF(OR(WBS!$F12="",WBS!$T12=""),"",IF(AND(18>=WBS!$F12,18<=WBS!$T12),IF(WBS!$L12="Done",3,IF(WBS!$L12="Doing",2,IF(WBS!$L12="Blocked",4,IF(WBS!$L12="Deferred",5,1)))),"")) | X12: =IF(OR(WBS!$F12="",WBS!$T12=""),"",IF(AND(19>=WBS!$F12,19<=WBS!$T12),IF(WBS!$L12="Done",3,IF(WBS!$L12="Doing",2,IF(WBS!$L12="Blocked",4,IF(WBS!$L12="Deferred",5,1)))),"")) | Y12: =IF(OR(WBS!$F12="",WBS!$T12=""),"",IF(AND(20>=WBS!$F12,20<=WBS!$T12),IF(WBS!$L12="Done",3,IF(WBS!$L12="Doing",2,IF(WBS!$L12="Blocked",4,IF(WBS!$L12="Deferred",5,1)))),"")) | Z12: =IF(OR(WBS!$F12="",WBS!$T12=""),"",IF(AND(21>=WBS!$F12,21<=WBS!$T12),IF(WBS!$L12="Done",3,IF(WBS!$L12="Doing",2,IF(WBS!$L12="Blocked",4,IF(WBS!$L12="Deferred",5,1)))),""))
A13: =WBS!$A13 -> 1.2.3 | B13: =WBS!$C13 -> Adversarial pass - what would make each persona distrust the system | C13: =IF(WBS!$E13="","",WBS!$E13) -> REQ | D13: =WBS!$J13 -> 2 | E13: =WBS!$M13 -> 0 | F13: =IF(OR(WBS!$F13="",WBS!$T13=""),"",IF(AND(1>=WBS!$F13,1<=WBS!$T13),IF(WBS!$L13="Done",3,IF(WBS!$L13="Doing",2,IF(WBS!$L13="Blocked",4,IF(WBS!$L13="Deferred",5,1)))),"")) | G13: =IF(OR(WBS!$F13="",WBS!$T13=""),"",IF(AND(2>=WBS!$F13,2<=WBS!$T13),IF(WBS!$L13="Done",3,IF(WBS!$L13="Doing",2,IF(WBS!$L13="Blocked",4,IF(WBS!$L13="Deferred",5,1)))),"")) -> 1 | H13: =IF(OR(WBS!$F13="",WBS!$T13=""),"",IF(AND(3>=WBS!$F13,3<=WBS!$T13),IF(WBS!$L13="Done",3,IF(WBS!$L13="Doing",2,IF(WBS!$L13="Blocked",4,IF(WBS!$L13="Deferred",5,1)))),"")) | I13: =IF(OR(WBS!$F13="",WBS!$T13=""),"",IF(AND(4>=WBS!$F13,4<=WBS!$T13),IF(WBS!$L13="Done",3,IF(WBS!$L13="Doing",2,IF(WBS!$L13="Blocked",4,IF(WBS!$L13="Deferred",5,1)))),"")) | J13: =IF(OR(WBS!$F13="",WBS!$T13=""),"",IF(AND(5>=WBS!$F13,5<=WBS!$T13),IF(WBS!$L13="Done",3,IF(WBS!$L13="Doing",2,IF(WBS!$L13="Blocked",4,IF(WBS!$L13="Deferred",5,1)))),"")) | K13: =IF(OR(WBS!$F13="",WBS!$T13=""),"",IF(AND(6>=WBS!$F13,6<=WBS!$T13),IF(WBS!$L13="Done",3,IF(WBS!$L13="Doing",2,IF(WBS!$L13="Blocked",4,IF(WBS!$L13="Deferred",5,1)))),"")) | L13: =IF(OR(WBS!$F13="",WBS!$T13=""),"",IF(AND(7>=WBS!$F13,7<=WBS!$T13),IF(WBS!$L13="Done",3,IF(WBS!$L13="Doing",2,IF(WBS!$L13="Blocked",4,IF(WBS!$L13="Deferred",5,1)))),"")) | M13: =IF(OR(WBS!$F13="",WBS!$T13=""),"",IF(AND(8>=WBS!$F13,8<=WBS!$T13),IF(WBS!$L13="Done",3,IF(WBS!$L13="Doing",2,IF(WBS!$L13="Blocked",4,IF(WBS!$L13="Deferred",5,1)))),"")) | N13: =IF(OR(WBS!$F13="",WBS!$T13=""),"",IF(AND(9>=WBS!$F13,9<=WBS!$T13),IF(WBS!$L13="Done",3,IF(WBS!$L13="Doing",2,IF(WBS!$L13="Blocked",4,IF(WBS!$L13="Deferred",5,1)))),"")) | O13: =IF(OR(WBS!$F13="",WBS!$T13=""),"",IF(AND(10>=WBS!$F13,10<=WBS!$T13),IF(WBS!$L13="Done",3,IF(WBS!$L13="Doing",2,IF(WBS!$L13="Blocked",4,IF(WBS!$L13="Deferred",5,1)))),"")) | P13: =IF(OR(WBS!$F13="",WBS!$T13=""),"",IF(AND(11>=WBS!$F13,11<=WBS!$T13),IF(WBS!$L13="Done",3,IF(WBS!$L13="Doing",2,IF(WBS!$L13="Blocked",4,IF(WBS!$L13="Deferred",5,1)))),"")) | Q13: =IF(OR(WBS!$F13="",WBS!$T13=""),"",IF(AND(12>=WBS!$F13,12<=WBS!$T13),IF(WBS!$L13="Done",3,IF(WBS!$L13="Doing",2,IF(WBS!$L13="Blocked",4,IF(WBS!$L13="Deferred",5,1)))),"")) | R13: =IF(OR(WBS!$F13="",WBS!$T13=""),"",IF(AND(13>=WBS!$F13,13<=WBS!$T13),IF(WBS!$L13="Done",3,IF(WBS!$L13="Doing",2,IF(WBS!$L13="Blocked",4,IF(WBS!$L13="Deferred",5,1)))),"")) | S13: =IF(OR(WBS!$F13="",WBS!$T13=""),"",IF(AND(14>=WBS!$F13,14<=WBS!$T13),IF(WBS!$L13="Done",3,IF(WBS!$L13="Doing",2,IF(WBS!$L13="Blocked",4,IF(WBS!$L13="Deferred",5,1)))),"")) | T13: =IF(OR(WBS!$F13="",WBS!$T13=""),"",IF(AND(15>=WBS!$F13,15<=WBS!$T13),IF(WBS!$L13="Done",3,IF(WBS!$L13="Doing",2,IF(WBS!$L13="Blocked",4,IF(WBS!$L13="Deferred",5,1)))),"")) | U13: =IF(OR(WBS!$F13="",WBS!$T13=""),"",IF(AND(16>=WBS!$F13,16<=WBS!$T13),IF(WBS!$L13="Done",3,IF(WBS!$L13="Doing",2,IF(WBS!$L13="Blocked",4,IF(WBS!$L13="Deferred",5,1)))),"")) | V13: =IF(OR(WBS!$F13="",WBS!$T13=""),"",IF(AND(17>=WBS!$F13,17<=WBS!$T13),IF(WBS!$L13="Done",3,IF(WBS!$L13="Doing",2,IF(WBS!$L13="Blocked",4,IF(WBS!$L13="Deferred",5,1)))),"")) | W13: =IF(OR(WBS!$F13="",WBS!$T13=""),"",IF(AND(18>=WBS!$F13,18<=WBS!$T13),IF(WBS!$L13="Done",3,IF(WBS!$L13="Doing",2,IF(WBS!$L13="Blocked",4,IF(WBS!$L13="Deferred",5,1)))),"")) | X13: =IF(OR(WBS!$F13="",WBS!$T13=""),"",IF(AND(19>=WBS!$F13,19<=WBS!$T13),IF(WBS!$L13="Done",3,IF(WBS!$L13="Doing",2,IF(WBS!$L13="Blocked",4,IF(WBS!$L13="Deferred",5,1)))),"")) | Y13: =IF(OR(WBS!$F13="",WBS!$T13=""),"",IF(AND(20>=WBS!$F13,20<=WBS!$T13),IF(WBS!$L13="Done",3,IF(WBS!$L13="Doing",2,IF(WBS!$L13="Blocked",4,IF(WBS!$L13="Deferred",5,1)))),"")) | Z13: =IF(OR(WBS!$F13="",WBS!$T13=""),"",IF(AND(21>=WBS!$F13,21<=WBS!$T13),IF(WBS!$L13="Done",3,IF(WBS!$L13="Doing",2,IF(WBS!$L13="Blocked",4,IF(WBS!$L13="Deferred",5,1)))),""))
A14: =WBS!$A14 -> 1.2.4 | B14: =WBS!$C14 -> Reconcile conflicts and record the losing option in writing | C14: =IF(WBS!$E14="","",WBS!$E14) -> REQ | D14: =WBS!$J14 -> 2 | E14: =WBS!$M14 -> 0 | F14: =IF(OR(WBS!$F14="",WBS!$T14=""),"",IF(AND(1>=WBS!$F14,1<=WBS!$T14),IF(WBS!$L14="Done",3,IF(WBS!$L14="Doing",2,IF(WBS!$L14="Blocked",4,IF(WBS!$L14="Deferred",5,1)))),"")) | G14: =IF(OR(WBS!$F14="",WBS!$T14=""),"",IF(AND(2>=WBS!$F14,2<=WBS!$T14),IF(WBS!$L14="Done",3,IF(WBS!$L14="Doing",2,IF(WBS!$L14="Blocked",4,IF(WBS!$L14="Deferred",5,1)))),"")) | H14: =IF(OR(WBS!$F14="",WBS!$T14=""),"",IF(AND(3>=WBS!$F14,3<=WBS!$T14),IF(WBS!$L14="Done",3,IF(WBS!$L14="Doing",2,IF(WBS!$L14="Blocked",4,IF(WBS!$L14="Deferred",5,1)))),"")) -> 1 | I14: =IF(OR(WBS!$F14="",WBS!$T14=""),"",IF(AND(4>=WBS!$F14,4<=WBS!$T14),IF(WBS!$L14="Done",3,IF(WBS!$L14="Doing",2,IF(WBS!$L14="Blocked",4,IF(WBS!$L14="Deferred",5,1)))),"")) | J14: =IF(OR(WBS!$F14="",WBS!$T14=""),"",IF(AND(5>=WBS!$F14,5<=WBS!$T14),IF(WBS!$L14="Done",3,IF(WBS!$L14="Doing",2,IF(WBS!$L14="Blocked",4,IF(WBS!$L14="Deferred",5,1)))),"")) | K14: =IF(OR(WBS!$F14="",WBS!$T14=""),"",IF(AND(6>=WBS!$F14,6<=WBS!$T14),IF(WBS!$L14="Done",3,IF(WBS!$L14="Doing",2,IF(WBS!$L14="Blocked",4,IF(WBS!$L14="Deferred",5,1)))),"")) | L14: =IF(OR(WBS!$F14="",WBS!$T14=""),"",IF(AND(7>=WBS!$F14,7<=WBS!$T14),IF(WBS!$L14="Done",3,IF(WBS!$L14="Doing",2,IF(WBS!$L14="Blocked",4,IF(WBS!$L14="Deferred",5,1)))),"")) | M14: =IF(OR(WBS!$F14="",WBS!$T14=""),"",IF(AND(8>=WBS!$F14,8<=WBS!$T14),IF(WBS!$L14="Done",3,IF(WBS!$L14="Doing",2,IF(WBS!$L14="Blocked",4,IF(WBS!$L14="Deferred",5,1)))),"")) | N14: =IF(OR(WBS!$F14="",WBS!$T14=""),"",IF(AND(9>=WBS!$F14,9<=WBS!$T14),IF(WBS!$L14="Done",3,IF(WBS!$L14="Doing",2,IF(WBS!$L14="Blocked",4,IF(WBS!$L14="Deferred",5,1)))),"")) | O14: =IF(OR(WBS!$F14="",WBS!$T14=""),"",IF(AND(10>=WBS!$F14,10<=WBS!$T14),IF(WBS!$L14="Done",3,IF(WBS!$L14="Doing",2,IF(WBS!$L14="Blocked",4,IF(WBS!$L14="Deferred",5,1)))),"")) | P14: =IF(OR(WBS!$F14="",WBS!$T14=""),"",IF(AND(11>=WBS!$F14,11<=WBS!$T14),IF(WBS!$L14="Done",3,IF(WBS!$L14="Doing",2,IF(WBS!$L14="Blocked",4,IF(WBS!$L14="Deferred",5,1)))),"")) | Q14: =IF(OR(WBS!$F14="",WBS!$T14=""),"",IF(AND(12>=WBS!$F14,12<=WBS!$T14),IF(WBS!$L14="Done",3,IF(WBS!$L14="Doing",2,IF(WBS!$L14="Blocked",4,IF(WBS!$L14="Deferred",5,1)))),"")) | R14: =IF(OR(WBS!$F14="",WBS!$T14=""),"",IF(AND(13>=WBS!$F14,13<=WBS!$T14),IF(WBS!$L14="Done",3,IF(WBS!$L14="Doing",2,IF(WBS!$L14="Blocked",4,IF(WBS!$L14="Deferred",5,1)))),"")) | S14: =IF(OR(WBS!$F14="",WBS!$T14=""),"",IF(AND(14>=WBS!$F14,14<=WBS!$T14),IF(WBS!$L14="Done",3,IF(WBS!$L14="Doing",2,IF(WBS!$L14="Blocked",4,IF(WBS!$L14="Deferred",5,1)))),"")) | T14: =IF(OR(WBS!$F14="",WBS!$T14=""),"",IF(AND(15>=WBS!$F14,15<=WBS!$T14),IF(WBS!$L14="Done",3,IF(WBS!$L14="Doing",2,IF(WBS!$L14="Blocked",4,IF(WBS!$L14="Deferred",5,1)))),"")) | U14: =IF(OR(WBS!$F14="",WBS!$T14=""),"",IF(AND(16>=WBS!$F14,16<=WBS!$T14),IF(WBS!$L14="Done",3,IF(WBS!$L14="Doing",2,IF(WBS!$L14="Blocked",4,IF(WBS!$L14="Deferred",5,1)))),"")) | V14: =IF(OR(WBS!$F14="",WBS!$T14=""),"",IF(AND(17>=WBS!$F14,17<=WBS!$T14),IF(WBS!$L14="Done",3,IF(WBS!$L14="Doing",2,IF(WBS!$L14="Blocked",4,IF(WBS!$L14="Deferred",5,1)))),"")) | W14: =IF(OR(WBS!$F14="",WBS!$T14=""),"",IF(AND(18>=WBS!$F14,18<=WBS!$T14),IF(WBS!$L14="Done",3,IF(WBS!$L14="Doing",2,IF(WBS!$L14="Blocked",4,IF(WBS!$L14="Deferred",5,1)))),"")) | X14: =IF(OR(WBS!$F14="",WBS!$T14=""),"",IF(AND(19>=WBS!$F14,19<=WBS!$T14),IF(WBS!$L14="Done",3,IF(WBS!$L14="Doing",2,IF(WBS!$L14="Blocked",4,IF(WBS!$L14="Deferred",5,1)))),"")) | Y14: =IF(OR(WBS!$F14="",WBS!$T14=""),"",IF(AND(20>=WBS!$F14,20<=WBS!$T14),IF(WBS!$L14="Done",3,IF(WBS!$L14="Doing",2,IF(WBS!$L14="Blocked",4,IF(WBS!$L14="Deferred",5,1)))),"")) | Z14: =IF(OR(WBS!$F14="",WBS!$T14=""),"",IF(AND(21>=WBS!$F14,21<=WBS!$T14),IF(WBS!$L14="Done",3,IF(WBS!$L14="Doing",2,IF(WBS!$L14="Blocked",4,IF(WBS!$L14="Deferred",5,1)))),""))
A15: =WBS!$A15 -> 1.3 | B15: =WBS!$C15 -> Requirement engineering | C15: =IF(WBS!$E15="","",WBS!$E15) | D15: =WBS!$J15 -> 7.5 | E15: =WBS!$M15 -> 0 | F15: =IF(OR(WBS!$F15="",WBS!$T15=""),"",IF(AND(1>=WBS!$F15,1<=WBS!$T15),IF(WBS!$L15="Done",3,IF(WBS!$L15="Doing",2,IF(WBS!$L15="Blocked",4,IF(WBS!$L15="Deferred",5,1)))),"")) | G15: =IF(OR(WBS!$F15="",WBS!$T15=""),"",IF(AND(2>=WBS!$F15,2<=WBS!$T15),IF(WBS!$L15="Done",3,IF(WBS!$L15="Doing",2,IF(WBS!$L15="Blocked",4,IF(WBS!$L15="Deferred",5,1)))),"")) -> 1 | H15: =IF(OR(WBS!$F15="",WBS!$T15=""),"",IF(AND(3>=WBS!$F15,3<=WBS!$T15),IF(WBS!$L15="Done",3,IF(WBS!$L15="Doing",2,IF(WBS!$L15="Blocked",4,IF(WBS!$L15="Deferred",5,1)))),"")) -> 1 | I15: =IF(OR(WBS!$F15="",WBS!$T15=""),"",IF(AND(4>=WBS!$F15,4<=WBS!$T15),IF(WBS!$L15="Done",3,IF(WBS!$L15="Doing",2,IF(WBS!$L15="Blocked",4,IF(WBS!$L15="Deferred",5,1)))),"")) | J15: =IF(OR(WBS!$F15="",WBS!$T15=""),"",IF(AND(5>=WBS!$F15,5<=WBS!$T15),IF(WBS!$L15="Done",3,IF(WBS!$L15="Doing",2,IF(WBS!$L15="Blocked",4,IF(WBS!$L15="Deferred",5,1)))),"")) | K15: =IF(OR(WBS!$F15="",WBS!$T15=""),"",IF(AND(6>=WBS!$F15,6<=WBS!$T15),IF(WBS!$L15="Done",3,IF(WBS!$L15="Doing",2,IF(WBS!$L15="Blocked",4,IF(WBS!$L15="Deferred",5,1)))),"")) | L15: =IF(OR(WBS!$F15="",WBS!$T15=""),"",IF(AND(7>=WBS!$F15,7<=WBS!$T15),IF(WBS!$L15="Done",3,IF(WBS!$L15="Doing",2,IF(WBS!$L15="Blocked",4,IF(WBS!$L15="Deferred",5,1)))),"")) | M15: =IF(OR(WBS!$F15="",WBS!$T15=""),"",IF(AND(8>=WBS!$F15,8<=WBS!$T15),IF(WBS!$L15="Done",3,IF(WBS!$L15="Doing",2,IF(WBS!$L15="Blocked",4,IF(WBS!$L15="Deferred",5,1)))),"")) | N15: =IF(OR(WBS!$F15="",WBS!$T15=""),"",IF(AND(9>=WBS!$F15,9<=WBS!$T15),IF(WBS!$L15="Done",3,IF(WBS!$L15="Doing",2,IF(WBS!$L15="Blocked",4,IF(WBS!$L15="Deferred",5,1)))),"")) | O15: =IF(OR(WBS!$F15="",WBS!$T15=""),"",IF(AND(10>=WBS!$F15,10<=WBS!$T15),IF(WBS!$L15="Done",3,IF(WBS!$L15="Doing",2,IF(WBS!$L15="Blocked",4,IF(WBS!$L15="Deferred",5,1)))),"")) | P15: =IF(OR(WBS!$F15="",WBS!$T15=""),"",IF(AND(11>=WBS!$F15,11<=WBS!$T15),IF(WBS!$L15="Done",3,IF(WBS!$L15="Doing",2,IF(WBS!$L15="Blocked",4,IF(WBS!$L15="Deferred",5,1)))),"")) | Q15: =IF(OR(WBS!$F15="",WBS!$T15=""),"",IF(AND(12>=WBS!$F15,12<=WBS!$T15),IF(WBS!$L15="Done",3,IF(WBS!$L15="Doing",2,IF(WBS!$L15="Blocked",4,IF(WBS!$L15="Deferred",5,1)))),"")) | R15: =IF(OR(WBS!$F15="",WBS!$T15=""),"",IF(AND(13>=WBS!$F15,13<=WBS!$T15),IF(WBS!$L15="Done",3,IF(WBS!$L15="Doing",2,IF(WBS!$L15="Blocked",4,IF(WBS!$L15="Deferred",5,1)))),"")) | S15: =IF(OR(WBS!$F15="",WBS!$T15=""),"",IF(AND(14>=WBS!$F15,14<=WBS!$T15),IF(WBS!$L15="Done",3,IF(WBS!$L15="Doing",2,IF(WBS!$L15="Blocked",4,IF(WBS!$L15="Deferred",5,1)))),"")) | T15: =IF(OR(WBS!$F15="",WBS!$T15=""),"",IF(AND(15>=WBS!$F15,15<=WBS!$T15),IF(WBS!$L15="Done",3,IF(WBS!$L15="Doing",2,IF(WBS!$L15="Blocked",4,IF(WBS!$L15="Deferred",5,1)))),"")) | U15: =IF(OR(WBS!$F15="",WBS!$T15=""),"",IF(AND(16>=WBS!$F15,16<=WBS!$T15),IF(WBS!$L15="Done",3,IF(WBS!$L15="Doing",2,IF(WBS!$L15="Blocked",4,IF(WBS!$L15="Deferred",5,1)))),"")) | V15: =IF(OR(WBS!$F15="",WBS!$T15=""),"",IF(AND(17>=WBS!$F15,17<=WBS!$T15),IF(WBS!$L15="Done",3,IF(WBS!$L15="Doing",2,IF(WBS!$L15="Blocked",4,IF(WBS!$L15="Deferred",5,1)))),"")) | W15: =IF(OR(WBS!$F15="",WBS!$T15=""),"",IF(AND(18>=WBS!$F15,18<=WBS!$T15),IF(WBS!$L15="Done",3,IF(WBS!$L15="Doing",2,IF(WBS!$L15="Blocked",4,IF(WBS!$L15="Deferred",5,1)))),"")) | X15: =IF(OR(WBS!$F15="",WBS!$T15=""),"",IF(AND(19>=WBS!$F15,19<=WBS!$T15),IF(WBS!$L15="Done",3,IF(WBS!$L15="Doing",2,IF(WBS!$L15="Blocked",4,IF(WBS!$L15="Deferred",5,1)))),"")) | Y15: =IF(OR(WBS!$F15="",WBS!$T15=""),"",IF(AND(20>=WBS!$F15,20<=WBS!$T15),IF(WBS!$L15="Done",3,IF(WBS!$L15="Doing",2,IF(WBS!$L15="Blocked",4,IF(WBS!$L15="Deferred",5,1)))),"")) | Z15: =IF(OR(WBS!$F15="",WBS!$T15=""),"",IF(AND(21>=WBS!$F15,21<=WBS!$T15),IF(WBS!$L15="Done",3,IF(WBS!$L15="Doing",2,IF(WBS!$L15="Blocked",4,IF(WBS!$L15="Deferred",5,1)))),""))
A16: =WBS!$A16 -> 1.3.1 | B16: =WBS!$C16 -> Edge case catalogue target 40 plus entries | C16: =IF(WBS!$E16="","",WBS!$E16) -> REQ | D16: =WBS!$J16 -> 2 | E16: =WBS!$M16 -> 0 | F16: =IF(OR(WBS!$F16="",WBS!$T16=""),"",IF(AND(1>=WBS!$F16,1<=WBS!$T16),IF(WBS!$L16="Done",3,IF(WBS!$L16="Doing",2,IF(WBS!$L16="Blocked",4,IF(WBS!$L16="Deferred",5,1)))),"")) | G16: =IF(OR(WBS!$F16="",WBS!$T16=""),"",IF(AND(2>=WBS!$F16,2<=WBS!$T16),IF(WBS!$L16="Done",3,IF(WBS!$L16="Doing",2,IF(WBS!$L16="Blocked",4,IF(WBS!$L16="Deferred",5,1)))),"")) -> 1 | H16: =IF(OR(WBS!$F16="",WBS!$T16=""),"",IF(AND(3>=WBS!$F16,3<=WBS!$T16),IF(WBS!$L16="Done",3,IF(WBS!$L16="Doing",2,IF(WBS!$L16="Blocked",4,IF(WBS!$L16="Deferred",5,1)))),"")) | I16: =IF(OR(WBS!$F16="",WBS!$T16=""),"",IF(AND(4>=WBS!$F16,4<=WBS!$T16),IF(WBS!$L16="Done",3,IF(WBS!$L16="Doing",2,IF(WBS!$L16="Blocked",4,IF(WBS!$L16="Deferred",5,1)))),"")) | J16: =IF(OR(WBS!$F16="",WBS!$T16=""),"",IF(AND(5>=WBS!$F16,5<=WBS!$T16),IF(WBS!$L16="Done",3,IF(WBS!$L16="Doing",2,IF(WBS!$L16="Blocked",4,IF(WBS!$L16="Deferred",5,1)))),"")) | K16: =IF(OR(WBS!$F16="",WBS!$T16=""),"",IF(AND(6>=WBS!$F16,6<=WBS!$T16),IF(WBS!$L16="Done",3,IF(WBS!$L16="Doing",2,IF(WBS!$L16="Blocked",4,IF(WBS!$L16="Deferred",5,1)))),"")) | L16: =IF(OR(WBS!$F16="",WBS!$T16=""),"",IF(AND(7>=WBS!$F16,7<=WBS!$T16),IF(WBS!$L16="Done",3,IF(WBS!$L16="Doing",2,IF(WBS!$L16="Blocked",4,IF(WBS!$L16="Deferred",5,1)))),"")) | M16: =IF(OR(WBS!$F16="",WBS!$T16=""),"",IF(AND(8>=WBS!$F16,8<=WBS!$T16),IF(WBS!$L16="Done",3,IF(WBS!$L16="Doing",2,IF(WBS!$L16="Blocked",4,IF(WBS!$L16="Deferred",5,1)))),"")) | N16: =IF(OR(WBS!$F16="",WBS!$T16=""),"",IF(AND(9>=WBS!$F16,9<=WBS!$T16),IF(WBS!$L16="Done",3,IF(WBS!$L16="Doing",2,IF(WBS!$L16="Blocked",4,IF(WBS!$L16="Deferred",5,1)))),"")) | O16: =IF(OR(WBS!$F16="",WBS!$T16=""),"",IF(AND(10>=WBS!$F16,10<=WBS!$T16),IF(WBS!$L16="Done",3,IF(WBS!$L16="Doing",2,IF(WBS!$L16="Blocked",4,IF(WBS!$L16="Deferred",5,1)))),"")) | P16: =IF(OR(WBS!$F16="",WBS!$T16=""),"",IF(AND(11>=WBS!$F16,11<=WBS!$T16),IF(WBS!$L16="Done",3,IF(WBS!$L16="Doing",2,IF(WBS!$L16="Blocked",4,IF(WBS!$L16="Deferred",5,1)))),"")) | Q16: =IF(OR(WBS!$F16="",WBS!$T16=""),"",IF(AND(12>=WBS!$F16,12<=WBS!$T16),IF(WBS!$L16="Done",3,IF(WBS!$L16="Doing",2,IF(WBS!$L16="Blocked",4,IF(WBS!$L16="Deferred",5,1)))),"")) | R16: =IF(OR(WBS!$F16="",WBS!$T16=""),"",IF(AND(13>=WBS!$F16,13<=WBS!$T16),IF(WBS!$L16="Done",3,IF(WBS!$L16="Doing",2,IF(WBS!$L16="Blocked",4,IF(WBS!$L16="Deferred",5,1)))),"")) | S16: =IF(OR(WBS!$F16="",WBS!$T16=""),"",IF(AND(14>=WBS!$F16,14<=WBS!$T16),IF(WBS!$L16="Done",3,IF(WBS!$L16="Doing",2,IF(WBS!$L16="Blocked",4,IF(WBS!$L16="Deferred",5,1)))),"")) | T16: =IF(OR(WBS!$F16="",WBS!$T16=""),"",IF(AND(15>=WBS!$F16,15<=WBS!$T16),IF(WBS!$L16="Done",3,IF(WBS!$L16="Doing",2,IF(WBS!$L16="Blocked",4,IF(WBS!$L16="Deferred",5,1)))),"")) | U16: =IF(OR(WBS!$F16="",WBS!$T16=""),"",IF(AND(16>=WBS!$F16,16<=WBS!$T16),IF(WBS!$L16="Done",3,IF(WBS!$L16="Doing",2,IF(WBS!$L16="Blocked",4,IF(WBS!$L16="Deferred",5,1)))),"")) | V16: =IF(OR(WBS!$F16="",WBS!$T16=""),"",IF(AND(17>=WBS!$F16,17<=WBS!$T16),IF(WBS!$L16="Done",3,IF(WBS!$L16="Doing",2,IF(WBS!$L16="Blocked",4,IF(WBS!$L16="Deferred",5,1)))),"")) | W16: =IF(OR(WBS!$F16="",WBS!$T16=""),"",IF(AND(18>=WBS!$F16,18<=WBS!$T16),IF(WBS!$L16="Done",3,IF(WBS!$L16="Doing",2,IF(WBS!$L16="Blocked",4,IF(WBS!$L16="Deferred",5,1)))),"")) | X16: =IF(OR(WBS!$F16="",WBS!$T16=""),"",IF(AND(19>=WBS!$F16,19<=WBS!$T16),IF(WBS!$L16="Done",3,IF(WBS!$L16="Doing",2,IF(WBS!$L16="Blocked",4,IF(WBS!$L16="Deferred",5,1)))),"")) | Y16: =IF(OR(WBS!$F16="",WBS!$T16=""),"",IF(AND(20>=WBS!$F16,20<=WBS!$T16),IF(WBS!$L16="Done",3,IF(WBS!$L16="Doing",2,IF(WBS!$L16="Blocked",4,IF(WBS!$L16="Deferred",5,1)))),"")) | Z16: =IF(OR(WBS!$F16="",WBS!$T16=""),"",IF(AND(21>=WBS!$F16,21<=WBS!$T16),IF(WBS!$L16="Done",3,IF(WBS!$L16="Doing",2,IF(WBS!$L16="Blocked",4,IF(WBS!$L16="Deferred",5,1)))),""))
... A144: =WBS!$A144 -> 8.4.3 | B144: =WBS!$C144 -> Final review and submission | C144: =IF(WBS!$E144="","",WBS!$E144) -> DOC | D144: =WBS!$J144 -> 1 | E144: =WBS!$M144 -> 0 | F144: =IF(OR(WBS!$F144="",WBS!$T144=""),"",IF(AND(1>=WBS!$F144,1<=WBS!$T144),IF(WBS!$L144="Done",3,IF(WBS!$L144="Doing",2,IF(WBS!$L144="Blocked",4,IF(WBS!$L144="Deferred",5,1)))),"")) | G144: =IF(OR(WBS!$F144="",WBS!$T144=""),"",IF(AND(2>=WBS!$F144,2<=WBS!$T144),IF(WBS!$L144="Done",3,IF(WBS!$L144="Doing",2,IF(WBS!$L144="Blocked",4,IF(WBS!$L144="Deferred",5,1)))),"")) | H144: =IF(OR(WBS!$F144="",WBS!$T144=""),"",IF(AND(3>=WBS!$F144,3<=WBS!$T144),IF(WBS!$L144="Done",3,IF(WBS!$L144="Doing",2,IF(WBS!$L144="Blocked",4,IF(WBS!$L144="Deferred",5,1)))),"")) | I144: =IF(OR(WBS!$F144="",WBS!$T144=""),"",IF(AND(4>=WBS!$F144,4<=WBS!$T144),IF(WBS!$L144="Done",3,IF(WBS!$L144="Doing",2,IF(WBS!$L144="Blocked",4,IF(WBS!$L144="Deferred",5,1)))),"")) | J144: =IF(OR(WBS!$F144="",WBS!$T144=""),"",IF(AND(5>=WBS!$F144,5<=WBS!$T144),IF(WBS!$L144="Done",3,IF(WBS!$L144="Doing",2,IF(WBS!$L144="Blocked",4,IF(WBS!$L144="Deferred",5,1)))),"")) | K144: =IF(OR(WBS!$F144="",WBS!$T144=""),"",IF(AND(6>=WBS!$F144,6<=WBS!$T144),IF(WBS!$L144="Done",3,IF(WBS!$L144="Doing",2,IF(WBS!$L144="Blocked",4,IF(WBS!$L144="Deferred",5,1)))),"")) | L144: =IF(OR(WBS!$F144="",WBS!$T144=""),"",IF(AND(7>=WBS!$F144,7<=WBS!$T144),IF(WBS!$L144="Done",3,IF(WBS!$L144="Doing",2,IF(WBS!$L144="Blocked",4,IF(WBS!$L144="Deferred",5,1)))),"")) | M144: =IF(OR(WBS!$F144="",WBS!$T144=""),"",IF(AND(8>=WBS!$F144,8<=WBS!$T144),IF(WBS!$L144="Done",3,IF(WBS!$L144="Doing",2,IF(WBS!$L144="Blocked",4,IF(WBS!$L144="Deferred",5,1)))),"")) | N144: =IF(OR(WBS!$F144="",WBS!$T144=""),"",IF(AND(9>=WBS!$F144,9<=WBS!$T144),IF(WBS!$L144="Done",3,IF(WBS!$L144="Doing",2,IF(WBS!$L144="Blocked",4,IF(WBS!$L144="Deferred",5,1)))),"")) | O144: =IF(OR(WBS!$F144="",WBS!$T144=""),"",IF(AND(10>=WBS!$F144,10<=WBS!$T144),IF(WBS!$L144="Done",3,IF(WBS!$L144="Doing",2,IF(WBS!$L144="Blocked",4,IF(WBS!$L144="Deferred",5,1)))),"")) | P144: =IF(OR(WBS!$F144="",WBS!$T144=""),"",IF(AND(11>=WBS!$F144,11<=WBS!$T144),IF(WBS!$L144="Done",3,IF(WBS!$L144="Doing",2,IF(WBS!$L144="Blocked",4,IF(WBS!$L144="Deferred",5,1)))),"")) | Q144: =IF(OR(WBS!$F144="",WBS!$T144=""),"",IF(AND(12>=WBS!$F144,12<=WBS!$T144),IF(WBS!$L144="Done",3,IF(WBS!$L144="Doing",2,IF(WBS!$L144="Blocked",4,IF(WBS!$L144="Deferred",5,1)))),"")) | R144: =IF(OR(WBS!$F144="",WBS!$T144=""),"",IF(AND(13>=WBS!$F144,13<=WBS!$T144),IF(WBS!$L144="Done",3,IF(WBS!$L144="Doing",2,IF(WBS!$L144="Blocked",4,IF(WBS!$L144="Deferred",5,1)))),"")) | S144: =IF(OR(WBS!$F144="",WBS!$T144=""),"",IF(AND(14>=WBS!$F144,14<=WBS!$T144),IF(WBS!$L144="Done",3,IF(WBS!$L144="Doing",2,IF(WBS!$L144="Blocked",4,IF(WBS!$L144="Deferred",5,1)))),"")) | T144: =IF(OR(WBS!$F144="",WBS!$T144=""),"",IF(AND(15>=WBS!$F144,15<=WBS!$T144),IF(WBS!$L144="Done",3,IF(WBS!$L144="Doing",2,IF(WBS!$L144="Blocked",4,IF(WBS!$L144="Deferred",5,1)))),"")) | U144: =IF(OR(WBS!$F144="",WBS!$T144=""),"",IF(AND(16>=WBS!$F144,16<=WBS!$T144),IF(WBS!$L144="Done",3,IF(WBS!$L144="Doing",2,IF(WBS!$L144="Blocked",4,IF(WBS!$L144="Deferred",5,1)))),"")) | V144: =IF(OR(WBS!$F144="",WBS!$T144=""),"",IF(AND(17>=WBS!$F144,17<=WBS!$T144),IF(WBS!$L144="Done",3,IF(WBS!$L144="Doing",2,IF(WBS!$L144="Blocked",4,IF(WBS!$L144="Deferred",5,1)))),"")) | W144: =IF(OR(WBS!$F144="",WBS!$T144=""),"",IF(AND(18>=WBS!$F144,18<=WBS!$T144),IF(WBS!$L144="Done",3,IF(WBS!$L144="Doing",2,IF(WBS!$L144="Blocked",4,IF(WBS!$L144="Deferred",5,1)))),"")) | X144: =IF(OR(WBS!$F144="",WBS!$T144=""),"",IF(AND(19>=WBS!$F144,19<=WBS!$T144),IF(WBS!$L144="Done",3,IF(WBS!$L144="Doing",2,IF(WBS!$L144="Blocked",4,IF(WBS!$L144="Deferred",5,1)))),"")) | Y144: =IF(OR(WBS!$F144="",WBS!$T144=""),"",IF(AND(20>=WBS!$F144,20<=WBS!$T144),IF(WBS!$L144="Done",3,IF(WBS!$L144="Doing",2,IF(WBS!$L144="Blocked",4,IF(WBS!$L144="Deferred",5,1)))),"")) | Z144: =IF(OR(WBS!$F144="",WBS!$T144=""),"",IF(AND(21>=WBS!$F144,21<=WBS!$T144),IF(WBS!$L144="Done",3,IF(WBS!$L144="Doing",2,IF(WBS!$L144="Blocked",4,IF(WBS!$L144="Deferred",5,1)))),"")) -> 1

Sheet AI Policy
A1: AI Usage Policy
A2: Answers brief §21 bullets 1 and 2 (which tools, what responsibilities) and carries the justification for every tool choice. Written once, revised only with a dated note.
A4: Governing principle
A5: Authoring and review are deliberately split across different models. The model that produced an artifact does not review it, because a single model's blind spot is invisible to itself — it will defend its own reasoning. Cross-model review is the cheapest available substitute for a second engineer, and the disagreements it produces are the most useful output: every one is logged, and resolved by me in writing rather than by averaging the two answers.
A7: 1. Tool registry
A8: Tool | B8: Access / model | C8: Assigned responsibilities | D8: Why this tool for this work (justification) | E8: Explicitly NOT used for | F8: How its output is validated
A9: ChatGPT | B9: GPT, web + chat | C9: Requirement engineering: brief decomposition, stakeholder persona simulation, discovery-finding enumeration, document structuring. | D9: Chosen for the RE phase because it sustains a long structured document process across many turns and holds a framework consistently. The RE output is prose and structure, not code, so agentic file access adds nothing here. | E9: Code generation, architecture decisions, security review — keeps a clean attribution boundary between RE and build phases. | F9: Every generated requirement must trace to a brief line or be labelled my assumption. Persona conflicts are reconciled by me, never averaged.
A10: Gemini | B10: Gemini, chat | C10: Independent cross-check: reviews artifacts authored by the other two tools, competitive and market analysis of existing railway apps, standards and accessibility lookup, second opinion on the domain model. | D10: Used as the reviewer precisely because it did NOT author the artifact. Large context makes it suitable for 'read this whole requirements doc and tell me what is missing'. Independence is the point, so it is kept out of authoring. | E10: Primary authoring of requirements, code or documents — that would destroy its value as an independent reviewer. | F10: Findings are triaged by me; false positives are logged too, because a reviewer's noise rate is itself evidence about how much to trust it.
A11: Claude Code | B11: Claude, agentic CLI in the repo | C11: Implementation, test generation, refactoring, code review, threat modelling, and the project tracking automation. | D11: Operates on files in the repository, so changes are applied and verified in place rather than copy-pasted from a chat window — which removes a whole class of transcription error. Strong at multi-file reasoning across the .NET, React and Flutter codebases. | E11: Merging anything unreviewed; final requirement sign-off. | F11: Must compile, tests must pass, AND I write an explain-back note before merge (brief §28 — I can be asked to explain any line).
A12: Claude (chat) | B12: Claude, chat | C12: Architecture option analysis, ADR drafting, scope and plan critique. | D12: Used where the task is judgment rather than file editing — weighing options and arguing against my own plan. Separate from Claude Code so the tracking stays honest about which mode produced what. | E12: Writing code into the repository. | F12: I make the decision; the ADR records the rejected option and why.
A13: GitHub Copilot | B13: not used | C13: — | D13: Deliberately not used. Inline autocomplete produces code I would not have consciously chosen, which is the exact risk brief §28 warns about, and its contributions are almost impossible to log honestly line by line. | E13: Everything. | F13: n/a
A16: 2. Responsibility assignment — who does what, and who checks it
A17: AI role | B17: Primary tool | C17: Cross-check tool | D17: Validation gate | E17: Evidence recorded on
A18: requirements-analyst | B18: ChatGPT | C18: Gemini | D18: Traces to a brief line or is labelled an assumption by me | E18: AI Usage Log
A19: stakeholder-persona | B19: ChatGPT | C19: Gemini | D19: Conflicts recorded, not averaged; losing option written down | E19: AI Usage Log
A20: domain-modeller | B20: Claude (chat) | C20: Gemini | D20: Invariant unit tests written first — a model that cannot be tested is rejected | E20: Decisions
A21: architect | B21: Claude (chat) | C21: Gemini | D21: I decide; ADR names the rejected option and why | E21: Decisions
A22: ux-designer | B22: ChatGPT | C22: Gemini | D22: Checked against context-of-use constraints; glanceability judged by me | E22: AI Usage Log
A23: implementer | B23: Claude Code | C23: Gemini | D23: Compiles, tests pass, explain-back note written | E23: Modified Impl
A24: reviewer | B24: Gemini | C24: Claude Code | D24: Findings triaged by me; false positives logged | E24: AI Usage Log
A25: test-engineer | B25: Claude Code | C25: — | D25: Every generated test must fail before it passes — no tautological tests | E25: AI Usage Log
A26: security-reviewer | B26: Claude Code | C26: Gemini | D26: Findings fixed or formally accepted in writing with a named reason | E26: AI Failures
A27: technical-writer | B27: ChatGPT | C27: Claude Code | D27: Facts re-checked against the code, not against the previous draft | E27: Prompt Library
A29: 3. Operating rules
A30: 1 | B30: Nothing merges that I cannot explain line by line. If explaining takes longer than rewriting it simpler, rewrite it simpler. (§28)
A31: 2 | B31: The model that authored an artifact does not review it.
A32: 3 | B32: AI output is input, not conclusion. Where two tools disagree, I decide in writing and record the losing argument.
A33: 4 | B33: Every contribution is logged the same day. A record reconstructed at the end is not evidence, and memory flattens every disagreement into 'it worked fine'.
A34: 5 | B34: Challenge rate is monitored, not maximised — but a rate near zero means the output is not being examined.
A35: 6 | B35: No AI-generated dependency or pattern I have not used before enters the build without me reading its documentation first.
A36: 7 | B36: Prompts that worked are saved to the Prompt Library; prompts that failed are more interesting and go to AI Failures.

Sheet AI Usage Log
A1: AI Usage Log
A2: One row per AI contribution. Log it the same day — this record cannot be rebuilt from memory at the end. The two grey rows are examples: delete them once you start. Columns K and M are the ones assessors read.
A4: # | B4: Date | C4: Day | D4: WBS / task | E4: WS | F4: AI tool | G4: AI role | H4: What I delegated | I4: What it produced | J4: Verdict | K4: Was it wrong | L4: Error type | M4: What I changed or why I rejected it | N4: How I validated it | O4: Saved h | P4: Lost h | Q4: Net h | R4: Evidence (commit / file)
A5: 1 | B5: 2026-10-04 | C5: 6 | D5: 3.1.2 | E5: BE | F5: Claude Code | G5: implementer | H5: Generate the EF Core configuration for Journey and JourneyStop | I5: Config with an Include chain eager-loading every stop on the departures query | J5: Accepted with edits | K5: Yes | L5: Wrong domain logic | M5: Rejected the Include chain - it produced an N+1 across JourneyStop on the public departures endpoint. Replaced with a projection to a read DTO. Kept its naming conventions. | N5: Integration test | O5: 1.5 | P5: 0.5 | Q5: =IFERROR($O5-$P5,0) -> 1 | R5: a1b2c3d
A6: 2 | B6: 2026-10-04 | C6: 6 | D6: 4.1.1 | E6: BE | F6: Claude Code | G6: domain-modeller | H6: Propose the service-date handling for journeys crossing midnight | I6: Used DateTime.Today for the service date | J6: Rejected | K6: Yes | L6: Missed edge case | M6: Its model breaks every 23:50 departure - the arrival falls on the next calendar day and the journey would be filed under the wrong service day. Implemented a GTFS-style service date with offsets allowed past 24:00, which I had already flagged as gap 11 in the plan. | N6: Unit test | O6: 0 | P6: 1 | Q6: =IFERROR($O6-$P6,0) -> -1 | R6: e4f5g6h
A7: =IF($B7="","",ROW()-4) | C7: =IF($B7="","",$B7-Dashboard!$B$3+1) | Q7: =IF($B7="","",IFERROR($O7-$P7,0))
A8: =IF($B8="","",ROW()-4) | C8: =IF($B8="","",$B8-Dashboard!$B$3+1) | Q8: =IF($B8="","",IFERROR($O8-$P8,0))
A9: =IF($B9="","",ROW()-4) | C9: =IF($B9="","",$B9-Dashboard!$B$3+1) | Q9: =IF($B9="","",IFERROR($O9-$P9,0))
A10: =IF($B10="","",ROW()-4) | C10: =IF($B10="","",$B10-Dashboard!$B$3+1) | Q10: =IF($B10="","",IFERROR($O10-$P10,0))
A11: =IF($B11="","",ROW()-4) | C11: =IF($B11="","",$B11-Dashboard!$B$3+1) | Q11: =IF($B11="","",IFERROR($O11-$P11,0))
A12: =IF($B12="","",ROW()-4) | C12: =IF($B12="","",$B12-Dashboard!$B$3+1) | Q12: =IF($B12="","",IFERROR($O12-$P12,0))
A13: =IF($B13="","",ROW()-4) | C13: =IF($B13="","",$B13-Dashboard!$B$3+1) | Q13: =IF($B13="","",IFERROR($O13-$P13,0))
A14: =IF($B14="","",ROW()-4) | C14: =IF($B14="","",$B14-Dashboard!$B$3+1) | Q14: =IF($B14="","",IFERROR($O14-$P14,0))
A15: =IF($B15="","",ROW()-4) | C15: =IF($B15="","",$B15-Dashboard!$B$3+1) | Q15: =IF($B15="","",IFERROR($O15-$P15,0))
A16: =IF($B16="","",ROW()-4) | C16: =IF($B16="","",$B16-Dashboard!$B$3+1) | Q16: =IF($B16="","",IFERROR($O16-$P16,0))
A17: =IF($B17="","",ROW()-4) | C17: =IF($B17="","",$B17-Dashboard!$B$3+1) | Q17: =IF($B17="","",IFERROR($O17-$P17,0))
A18: =IF($B18="","",ROW()-4) | C18: =IF($B18="","",$B18-Dashboard!$B$3+1) | Q18: =IF($B18="","",IFERROR($O18-$P18,0))
... A204: =IF($B204="","",ROW()-4) | C204: =IF($B204="","",$B204-Dashboard!$B$3+1) | Q204: =IF($B204="","",IFERROR($O204-$P204,0))

Sheet Prompt Library
A1: Prompt and workflow library
A2: Brief §21 bullet 3 — important prompts and workflows. Record the ones that changed the outcome, not every message. Grey rows are examples; delete them.
A4: # | B4: Date | C4: Tool | D4: WBS | E4: Purpose | F4: Prompt or workflow (summary) | G4: Why structured this way | H4: Outcome | I4: Reused | J4: Evidence
A5: 1 | B5: 2026-09-30 | C5: ChatGPT | D5: 1.2.1 | E5: Stakeholder simulation | F5: Interview protocol per persona, fixed 5 questions: their day / what breaks today / what they need to see / what they must never see / what they would do if the system lied to them | G5: The last question is the one that produces failure requirements. Open-ended 'what do you want' prompts return feature lists; asking about distrust returns edge cases. | H5: 11 edge cases not in the brief | I5: Yes | J5: docs/00-requirements
A6: 2 | B6: 2026-10-02 | C6: Gemini | D6: 2.1.1 | E6: Independent model review | F6: Paste the full domain model and ask: which railway situations would this model fail to represent? Do not suggest improvements, only failures. | G6: Forbidding suggestions stops it drifting into agreeable rewriting. Asking only for failures makes the answer checkable against the brief. | H6: Found missing crew handover | I6: Yes | J6: ADR-0002
A7: =IF($B7="","",ROW()-4)
A8: =IF($B8="","",ROW()-4)
A9: =IF($B9="","",ROW()-4)
A10: =IF($B10="","",ROW()-4)
A11: =IF($B11="","",ROW()-4)
A12: =IF($B12="","",ROW()-4)
A13: =IF($B13="","",ROW()-4)
A14: =IF($B14="","",ROW()-4)
A15: =IF($B15="","",ROW()-4)
A16: =IF($B16="","",ROW()-4)
A17: =IF($B17="","",ROW()-4)
A18: =IF($B18="","",ROW()-4)
... A84: =IF($B84="","",ROW()-4)

Sheet AI Failures
A1: Where AI was wrong or insufficient — and where my judgment improved it
A2: Brief §21 bullets 5 and 6. Target 8 substantive entries. These are the highest-value entries in the whole submission: they prove the output was examined, not accepted. The two rows below are real, from 2026-10-01 — verify the wording and keep them.
A4: # | B4: Date | C4: Tool | D4: WBS | E4: What it claimed or produced | F4: Why it was wrong or insufficient | G4: How I detected it | H4: What I did instead | I4: Impact had it shipped | J4: Evidence | K4: §21 bullet
A5: 1 | B5: 2026-10-01 | C5: ChatGPT | D5: 1.0 | E5: Proposed a 14-step requirement-engineering process with a separate 'Current-State Analysis' phase, and two large frames for the stakeholder-impact step. | F5: Insufficient rather than incorrect. The brief describes a fictional organisation with no documented current process and no client to interview, so a current-state phase can only output 'unknown'. And the process was sized for a multi-month engagement, not a 21-day window that also has to produce six running applications. | G5: Compared the step count against the remaining calendar and the six-app build scope. | H5: Collapsed current-state into a short subsection of Discovery with a written note explaining why the method was adapted, consolidated the impact step into a single matrix, and timeboxed the whole RE phase to a D5 freeze. | I5: Beautiful requirements with three half-built applications — the failure mode brief §25 warns about directly. | J5: docs/00-requirements | K5: 5
A6: 2 | B6: 2026-10-01 | C6: ChatGPT | D6: 1.3 | E6: An assumption register where 'SmartRail will have an authoritative source for operational railway information' was listed as an assumption with status 'To validate'. | F6: That is an architecture decision I am making, not an assumption about an unknown. The register was mixing three different things: facts stated in the brief, decisions I had made, and genuine unknowns. 'To validate' was also unclosable — there is no client to validate with, so every row would still read 'To validate' on submission day. | G6: Tried to write the 'what breaks if this is wrong' column and found the answer was 'nothing, because I chose it'. | H6: Split the register into facts / decisions / assumptions, moved decisions to ADRs, replaced the status values with closable ones, and added a risk-if-wrong column. | I6: A register that looks unfinished and blurs the line between evidence and choice — exactly what §22 asks candidates to distinguish. | J6: Decisions sheet | K6: 6
A7: =IF($B7="","",ROW()-4)
A8: =IF($B8="","",ROW()-4)
A9: =IF($B9="","",ROW()-4)
A10: =IF($B10="","",ROW()-4)
A11: =IF($B11="","",ROW()-4)
A12: =IF($B12="","",ROW()-4)
A13: =IF($B13="","",ROW()-4)
A14: =IF($B14="","",ROW()-4)
A15: =IF($B15="","",ROW()-4)
A16: =IF($B16="","",ROW()-4)
A17: =IF($B17="","",ROW()-4)
A18: =IF($B18="","",ROW()-4)
... A44: =IF($B44="","",ROW()-4)

Sheet Modified Impl
A1: AI-generated implementations I significantly modified
A2: Brief §21 bullet 7. Only substantive rewrites belong here — not formatting or renames. Each row must be defensible in a live code walkthrough (§28). Grey row is an example.
A4: # | B4: Date | C4: Tool | D4: WBS | E4: Component / file | F4: What the AI generated | G4: What I changed | H4: Why | I4: Evidence (commit) | J4: Can I explain it cold
A5: 1 | B5: 2026-10-04 | C5: Claude Code | D5: 3.1.2 | E5: backend/src/SmartRail.Infrastructure/Persistence/JourneyConfiguration.cs | F5: EF Core configuration with an Include chain eager-loading every JourneyStop on the public departures query. | G5: Replaced the Include chain with a projection to a read DTO and a single ordered query; kept its naming conventions and the index definitions, which were correct. | H5: The generated version issued one query per journey on the busiest public endpoint — an N+1 that only appears under a realistic station board with 20 departures, so it would have passed a naive test and failed the 300ms p95 target. | I5: a1b2c3d | J5: Yes
A6: =IF($B6="","",ROW()-4)
A7: =IF($B7="","",ROW()-4)
A8: =IF($B8="","",ROW()-4)
A9: =IF($B9="","",ROW()-4)
A10: =IF($B10="","",ROW()-4)
A11: =IF($B11="","",ROW()-4)
A12: =IF($B12="","",ROW()-4)
A13: =IF($B13="","",ROW()-4)
A14: =IF($B14="","",ROW()-4)
A15: =IF($B15="","",ROW()-4)
A16: =IF($B16="","",ROW()-4)
A17: =IF($B17="","",ROW()-4)
... A44: =IF($B44="","",ROW()-4)

Sheet AI Summary
A1: AI Usage — analysis
A2: All formulas. This is the sheet to screenshot for the AI Usage section of the submission (brief section 23).
A4: Headline
A5: Total logged AI contributions | B5: =COUNTA('AI Usage Log'!$B$5:$B$204) -> 2
A6: Accepted as-is | B6: =COUNTIF('AI Usage Log'!$J$5:$J$204,"Accepted") -> 0
A7: Accepted with edits | B7: =COUNTIF('AI Usage Log'!$J$5:$J$204,"Accepted with edits") -> 1
A8: Rejected | B8: =COUNTIF('AI Usage Log'!$J$5:$J$204,"Rejected") -> 1
A9: Challenge rate (edited or rejected) | B9: =IFERROR(($B7+$B8)/$B5,0) -> 1
A10: Times AI was wrong | B10: =COUNTIF('AI Usage Log'!$K$5:$K$204,"Yes") -> 2
A11: Target for 'AI was wrong' write-ups | B11: 8
A12: Write-up target met | B12: =IF($B10>=$B11,"YES","NOT YET - need "&($B11-$B10)&" more") -> NOT YET - need 6 more
A13: Hours saved | B13: =SUM('AI Usage Log'!$O$5:$O$204) -> 1.5
A14: Hours lost to AI error | B14: =SUM('AI Usage Log'!$P$5:$P$204) -> 1.5
A15: Net hours | B15: =$B13-$B14 -> 0
A17: By AI role | E17: By error type
A18: AI role | B18: Uses | C18: Rejected or edited | E18: Error type | F18: Count
A19: requirements-analyst | B19: =COUNTIF('AI Usage Log'!$G$5:$G$204,$A19) -> 0 | C19: =COUNTIFS('AI Usage Log'!$G$5:$G$204,$A19,'AI Usage Log'!$J$5:$J$204,"Rejected")+COUNTIFS('AI Usage Log'!$G$5:$G$204,$A19,'AI Usage Log'!$J$5:$J$204,"Accepted with edits") -> 0 | E19: None | F19: =COUNTIF('AI Usage Log'!$L$5:$L$204,$E19) -> 0
A20: stakeholder-persona | B20: =COUNTIF('AI Usage Log'!$G$5:$G$204,$A20) -> 0 | C20: =COUNTIFS('AI Usage Log'!$G$5:$G$204,$A20,'AI Usage Log'!$J$5:$J$204,"Rejected")+COUNTIFS('AI Usage Log'!$G$5:$G$204,$A20,'AI Usage Log'!$J$5:$J$204,"Accepted with edits") -> 0 | E20: Hallucinated API | F20: =COUNTIF('AI Usage Log'!$L$5:$L$204,$E20) -> 0
A21: domain-modeller | B21: =COUNTIF('AI Usage Log'!$G$5:$G$204,$A21) -> 1 | C21: =COUNTIFS('AI Usage Log'!$G$5:$G$204,$A21,'AI Usage Log'!$J$5:$J$204,"Rejected")+COUNTIFS('AI Usage Log'!$G$5:$G$204,$A21,'AI Usage Log'!$J$5:$J$204,"Accepted with edits") -> 1 | E21: Wrong domain logic | F21: =COUNTIF('AI Usage Log'!$L$5:$L$204,$E21) -> 1
A22: architect | B22: =COUNTIF('AI Usage Log'!$G$5:$G$204,$A22) -> 0 | C22: =COUNTIFS('AI Usage Log'!$G$5:$G$204,$A22,'AI Usage Log'!$J$5:$J$204,"Rejected")+COUNTIFS('AI Usage Log'!$G$5:$G$204,$A22,'AI Usage Log'!$J$5:$J$204,"Accepted with edits") -> 0 | E22: Over-engineered | F22: =COUNTIF('AI Usage Log'!$L$5:$L$204,$E22) -> 0
A23: ux-designer | B23: =COUNTIF('AI Usage Log'!$G$5:$G$204,$A23) -> 0 | C23: =COUNTIFS('AI Usage Log'!$G$5:$G$204,$A23,'AI Usage Log'!$J$5:$J$204,"Rejected")+COUNTIFS('AI Usage Log'!$G$5:$G$204,$A23,'AI Usage Log'!$J$5:$J$204,"Accepted with edits") -> 0 | E23: Security blind spot | F23: =COUNTIF('AI Usage Log'!$L$5:$L$204,$E23) -> 0
A24: implementer | B24: =COUNTIF('AI Usage Log'!$G$5:$G$204,$A24) -> 1 | C24: =COUNTIFS('AI Usage Log'!$G$5:$G$204,$A24,'AI Usage Log'!$J$5:$J$204,"Rejected")+COUNTIFS('AI Usage Log'!$G$5:$G$204,$A24,'AI Usage Log'!$J$5:$J$204,"Accepted with edits") -> 1 | E24: Outdated information | F24: =COUNTIF('AI Usage Log'!$L$5:$L$204,$E24) -> 0
A25: reviewer | B25: =COUNTIF('AI Usage Log'!$G$5:$G$204,$A25) -> 0 | C25: =COUNTIFS('AI Usage Log'!$G$5:$G$204,$A25,'AI Usage Log'!$J$5:$J$204,"Rejected")+COUNTIFS('AI Usage Log'!$G$5:$G$204,$A25,'AI Usage Log'!$J$5:$J$204,"Accepted with edits") -> 0 | E25: Tautological test | F25: =COUNTIF('AI Usage Log'!$L$5:$L$204,$E25) -> 0
A26: test-engineer | B26: =COUNTIF('AI Usage Log'!$G$5:$G$204,$A26) -> 0 | C26: =COUNTIFS('AI Usage Log'!$G$5:$G$204,$A26,'AI Usage Log'!$J$5:$J$204,"Rejected")+COUNTIFS('AI Usage Log'!$G$5:$G$204,$A26,'AI Usage Log'!$J$5:$J$204,"Accepted with edits") -> 0 | E26: Missed edge case | F26: =COUNTIF('AI Usage Log'!$L$5:$L$204,$E26) -> 1
A27: security-reviewer | B27: =COUNTIF('AI Usage Log'!$G$5:$G$204,$A27) -> 0 | C27: =COUNTIFS('AI Usage Log'!$G$5:$G$204,$A27,'AI Usage Log'!$J$5:$J$204,"Rejected")+COUNTIFS('AI Usage Log'!$G$5:$G$204,$A27,'AI Usage Log'!$J$5:$J$204,"Accepted with edits") -> 0 | E27: Ignored constraint | F27: =COUNTIF('AI Usage Log'!$L$5:$L$204,$E27) -> 0
A28: technical-writer | B28: =COUNTIF('AI Usage Log'!$G$5:$G$204,$A28) -> 0 | C28: =COUNTIFS('AI Usage Log'!$G$5:$G$204,$A28,'AI Usage Log'!$J$5:$J$204,"Rejected")+COUNTIFS('AI Usage Log'!$G$5:$G$204,$A28,'AI Usage Log'!$J$5:$J$204,"Accepted with edits") -> 0
A32: By tool
A33: AI tool | B33: Uses | C33: Rejected or edited | D33: Challenge rate | E33: Was wrong | F33: Net h
A34: ChatGPT | B34: =COUNTIF('AI Usage Log'!$F$5:$F$204,$A34) -> 0 | C34: =COUNTIFS('AI Usage Log'!$F$5:$F$204,$A34,'AI Usage Log'!$J$5:$J$204,"Rejected")+COUNTIFS('AI Usage Log'!$F$5:$F$204,$A34,'AI Usage Log'!$J$5:$J$204,"Accepted with edits") -> 0 | D34: =IFERROR($C34/$B34,0) -> 0 | E34: =COUNTIFS('AI Usage Log'!$F$5:$F$204,$A34,'AI Usage Log'!$K$5:$K$204,"Yes") -> 0 | F34: =SUMIFS('AI Usage Log'!$Q$5:$Q$204,'AI Usage Log'!$F$5:$F$204,$A34) -> 0
A35: Gemini | B35: =COUNTIF('AI Usage Log'!$F$5:$F$204,$A35) -> 0 | C35: =COUNTIFS('AI Usage Log'!$F$5:$F$204,$A35,'AI Usage Log'!$J$5:$J$204,"Rejected")+COUNTIFS('AI Usage Log'!$F$5:$F$204,$A35,'AI Usage Log'!$J$5:$J$204,"Accepted with edits") -> 0 | D35: =IFERROR($C35/$B35,0) -> 0 | E35: =COUNTIFS('AI Usage Log'!$F$5:$F$204,$A35,'AI Usage Log'!$K$5:$K$204,"Yes") -> 0 | F35: =SUMIFS('AI Usage Log'!$Q$5:$Q$204,'AI Usage Log'!$F$5:$F$204,$A35) -> 0
A36: Claude Code | B36: =COUNTIF('AI Usage Log'!$F$5:$F$204,$A36) -> 2 | C36: =COUNTIFS('AI Usage Log'!$F$5:$F$204,$A36,'AI Usage Log'!$J$5:$J$204,"Rejected")+COUNTIFS('AI Usage Log'!$F$5:$F$204,$A36,'AI Usage Log'!$J$5:$J$204,"Accepted with edits") -> 2 | D36: =IFERROR($C36/$B36,0) -> 1 | E36: =COUNTIFS('AI Usage Log'!$F$5:$F$204,$A36,'AI Usage Log'!$K$5:$K$204,"Yes") -> 2 | F36: =SUMIFS('AI Usage Log'!$Q$5:$Q$204,'AI Usage Log'!$F$5:$F$204,$A36) -> 0
A37: Claude (chat) | B37: =COUNTIF('AI Usage Log'!$F$5:$F$204,$A37) -> 0 | C37: =COUNTIFS('AI Usage Log'!$F$5:$F$204,$A37,'AI Usage Log'!$J$5:$J$204,"Rejected")+COUNTIFS('AI Usage Log'!$F$5:$F$204,$A37,'AI Usage Log'!$J$5:$J$204,"Accepted with edits") -> 0 | D37: =IFERROR($C37/$B37,0) -> 0 | E37: =COUNTIFS('AI Usage Log'!$F$5:$F$204,$A37,'AI Usage Log'!$K$5:$K$204,"Yes") -> 0 | F37: =SUMIFS('AI Usage Log'!$Q$5:$Q$204,'AI Usage Log'!$F$5:$F$204,$A37) -> 0
A38: GitHub Copilot | B38: =COUNTIF('AI Usage Log'!$F$5:$F$204,$A38) -> 0 | C38: =COUNTIFS('AI Usage Log'!$F$5:$F$204,$A38,'AI Usage Log'!$J$5:$J$204,"Rejected")+COUNTIFS('AI Usage Log'!$F$5:$F$204,$A38,'AI Usage Log'!$J$5:$J$204,"Accepted with edits") -> 0 | D38: =IFERROR($C38/$B38,0) -> 0 | E38: =COUNTIFS('AI Usage Log'!$F$5:$F$204,$A38,'AI Usage Log'!$K$5:$K$204,"Yes") -> 0 | F38: =SUMIFS('AI Usage Log'!$Q$5:$Q$204,'AI Usage Log'!$F$5:$F$204,$A38) -> 0
A39: Other | B39: =COUNTIF('AI Usage Log'!$F$5:$F$204,$A39) -> 0 | C39: =COUNTIFS('AI Usage Log'!$F$5:$F$204,$A39,'AI Usage Log'!$J$5:$J$204,"Rejected")+COUNTIFS('AI Usage Log'!$F$5:$F$204,$A39,'AI Usage Log'!$J$5:$J$204,"Accepted with edits") -> 0 | D39: =IFERROR($C39/$B39,0) -> 0 | E39: =COUNTIFS('AI Usage Log'!$F$5:$F$204,$A39,'AI Usage Log'!$K$5:$K$204,"Yes") -> 0 | F39: =SUMIFS('AI Usage Log'!$Q$5:$Q$204,'AI Usage Log'!$F$5:$F$204,$A39) -> 0

Sheet Decisions
A1: Decision register (ADR index)
A2: Brief §23 asks for important architecture decisions and trade-offs. Every row keeps the justification AND the rejected alternative — a decision without a rejected option is not a decision. Fill 'AI involvement' as you go; it feeds the AI usage story.
A4: ADR | B4: Title | C4: Status | D4: Decision | E4: Justification | F4: Rejected alternative | G4: Why rejected | H4: AI involvement | I4: Date
A5: 0001 | B5: Modular monolith over microservices | C5: Accepted | D5: One deployable with six hard-bounded modules; boundaries enforced by NetArchTest in CI. | E5: Microservices would cost days of infrastructure for zero assessment credit and make distributed-transaction bugs my problem. Enforced module boundaries still demonstrate separation of responsibility, which is what §26 actually grades. | F5: Microservices per bounded context | G5: One engineer, 21 days. Operational cost with no marginal grading benefit.
A6: 0002 | B6: .NET clean architecture layering | C6: Accepted | D6: Domain / Application / Infrastructure / Api, domain with zero framework references. | E6: The railway domain is rule-heavy — schedules, calendars, journey state machine. A framework-free domain layer lets those rules be unit-tested without a database, and the layering is legible to an assessor in seconds. | F6: Vertical-slice architecture | G6: Slices are excellent for CRUD-ish features but hide the shared domain invariants that are the interesting part of this problem.
A7: 0003 | B7: PostgreSQL with EF Core | C7: Accepted | D7: Relational store, jsonb for snapshot payloads. | E7: The timetable is a graph of stops and joins are the whole job. Free, Docker-friendly, and EF Core migrations keep the schema reproducible for the demo. | F7: MongoDB | G7: Document model fights the relational timetable; joins would move into code.
A8: 0004 | B8: SignalR for realtime | C8: Accepted | D8: WebSocket with automatic long-poll fallback, snapshot-then-delta protocol. | E8: First-class in .NET and one abstraction serves web, displays, terminal and Flutter. The fallback matters because §16 requires behaviour under unreliable connectivity. | F8: Polling every 10s | G8: Kept as the documented fallback if SignalR costs too much time — but polling cannot meet the 5s freshness target for 200 displays.
A9: 0005 | B9: Redis for live journey state | C9: Accepted | D9: Current positions, ETAs and display snapshots held in Redis; Postgres holds material changes. | E9: Journey progress is hot, small and expendable. Keeping it out of the Postgres write path stops telemetry ingestion competing with the public read endpoints. | F9: Everything in Postgres | G9: Write amplification from per-ping updates on the busiest table.
A10: 0006 | B10: Three-source live tracking with explicit confidence | C10: Accepted | D10: Fuse driver-confirmed events, telemetry pings and schedule projection; every estimate carries a source and a confidence level surfaced in the UI. | E10: The brief deliberately leaves the mechanism to me (§5). Each source has different trust, and the worst failure of a passenger-information system is confident wrongness — so the confidence level is a product requirement, not an implementation detail. | F10: GPS only | G10: Goes blind in tunnels and weak-signal areas, which is precisely when passengers most need to know the system does not know.
A11: 0007 | B11: Outbox pattern instead of a message broker | C11: Accepted | D11: Transactional outbox plus a background dispatcher for webhooks and notifications. | E11: Gives at-least-once delivery to the catering provider without me operating RabbitMQ or Kafka. The reliability lesson is demonstrated; the ops burden is not incurred. | F11: RabbitMQ / Kafka | G11: Infrastructure time with no additional grading credit.
A12: 0008 | B12: Node.js for the external catering platform | C12: Accepted | D12: RailBite is a separate Node + Express app with its own database and its own ops UI. | E12: §12 requires the provider to remain external. A different runtime makes the boundary physically undeniable, exercises the Node track from §24, and forces a real contract — HMAC-signed webhooks and versioned DTOs — instead of a shared-type shortcut. | F12: A mocked module inside the monolith | G12: Would let types leak across the boundary and prove nothing about integration.
A13: 0009 | B13: One kiosk codebase, two modes | C13: Accepted | D13: Single React app with display and terminal modes. | E13: Displays and terminals share most of the data layer and all design tokens. Two codebases would be a scope error; 'one app, two interaction profiles' is defensible and satisfies both §6 and §7. | F13: Two separate applications | G13: Duplicate data layer for one engineer in 21 days.
A14: 0010 | B14: Flutter feature-based clean architecture | C14: Accepted | D14: Melos monorepo, two apps sharing core / design_system / api_client; Riverpod and Drift. | E14: Feature slices mirror the backend layering so one mental model explains both. Drift because the driver app needs a queryable offline action queue, not key-value storage. | F14: Separate repos per app | G14: Loses the shared design system and triples the CI surface.
A15: 0011 | B15: Permission-based authorization with scoped permissions | C15: Accepted | D15: Roles are bundles of permissions; scope-limited permissions such as station.edit:own are checked in the Application layer. | E15: §9 says explicitly not to treat operational users as one Administrator role. Permissions rather than roles in the code means adding a role is configuration, not a code change. | F15: Role checks at the controller | G15: Scatters authorization across endpoints and makes the negative tests impossible to enumerate.
A16: 0012 | B16: Device identity for unattended clients | C16: Accepted | D16: Displays and terminals get provisioned device tokens with read-only scope, heartbeat and revocation; a device registry backs the Station and Device Health screen. | E16: Not in the brief at all — discovered in gap analysis. An unattended screen has no human to log in, and a dead display is a customer-facing outage nobody notices without heartbeats. | F16: Shared API key across devices | G16: Cannot revoke one screen, cannot tell which screen is stale, and a key leak compromises every station.
... A19: 0015 | B19: Shared design tokens, divergent density profiles | C19: Accepted | D19: One tokens.json generating CSS variables and Dart constants; three type scales for passenger, operations and display. | E19: §15 asks whether the applications share a design language. They share tokens but must not share density: a display read at 8 metres and an operations console read at 60cm have opposite requirements. One source of truth prevents React/Flutter drift. | F19: One shared component library across all five apps | G19: Forces a compromise density that serves none of the three audiences well.

Sheet Risks
A1: Risk register
A2: Review every Friday. Score = Likelihood x Impact (High 3, Medium 2, Low 1).
A4: ID | B4: Risk | C4: Likelihood | D4: Impact | E4: Score | F4: Mitigation | G4: Trigger / early warning | H4: Status | I4: Last reviewed
A5: R1 | B5: Scope creep across six applications | C5: High | D5: High | E5: =IFERROR(MATCH($C5,{"Low";"Medium";"High"},0)*MATCH($D5,{"Low";"Medium";"High"},0),"") -> 9 | F5: D14 feature freeze; screen ceilings fixed in plan.md section 9; everything cut goes to the Deferred sheet | G5: A new screen appears in the WBS after D14 | H5: Open
A6: R2 | B6: Realtime plus offline mechanics consume days | C6: High | D6: High | E6: =IFERROR(MATCH($C6,{"Low";"Medium";"High"},0)*MATCH($D6,{"Low";"Medium";"High"},0),"") -> 9 | F6: Build the live spine D8-D9 while fresh; simulator makes it testable; fall back to polling if SignalR fights back | G6: 4.3.1 still open at end of D9 | H6: Open
A7: R3 | B7: Flutter and Android toolchain time sink | C7: Medium | D7: High | E7: =IFERROR(MATCH($C7,{"Low";"Medium";"High"},0)*MATCH($D7,{"Low";"Medium";"High"},0),"") -> 6 | F7: Validate emulator and FCM on D6 inside task 3.4.1, not on D12; iOS explicitly out of test scope | G7: 3.4.1 slips or emulator fails | H7: Open
A8: R4 | B8: Documentation left until week three | C8: Medium | D8: High | E8: =IFERROR(MATCH($C8,{"Low";"Medium";"High"},0)*MATCH($D8,{"Low";"Medium";"High"},0),"") -> 6 | F8: Docs produced daily alongside the work; D19 is consolidation only, not authoring | G8: Any phase-8 task starting before D19 is empty | H8: Open
A9: R5 | B9: AI usage evidence unconvincing | C9: Medium | D9: High | E9: =IFERROR(MATCH($C9,{"Low";"Medium";"High"},0)*MATCH($D9,{"Low";"Medium";"High"},0),"") -> 6 | F9: Log every contribution the same day; challenge rate and 'AI was wrong' count tracked on the AI Summary sheet | G9: AI Summary shows fewer than 8 wrong entries by D16 | H9: Open
A10: R6 | B10: Live demo breaks during the presentation | C10: Medium | D10: High | E10: =IFERROR(MATCH($C10,{"Low";"Medium";"High"},0)*MATCH($D10,{"Low";"Medium";"High"},0),"") -> 6 | F10: Deterministic seeded scenario, two rehearsals on D20, recorded fallback video | G10: First rehearsal fails | H10: Open
A11: R7 | B11: Cannot explain a generated module under questioning | C11: Medium | D11: High | E11: =IFERROR(MATCH($C11,{"Low";"Medium";"High"},0)*MATCH($D11,{"Low";"Medium";"High"},0),"") -> 6 | F11: Definition of done item 7 - explain-back note per slice; simplify rather than keep clever code | G11: Any merged file I cannot walk through cold | H11: Open
A12: R8 | B12: Integration flakiness with the catering provider | C12: Medium | D12: Medium | E12: =IFERROR(MATCH($C12,{"Low";"Medium";"High"},0)*MATCH($D12,{"Low";"Medium";"High"},0),"") -> 4 | F12: Fault-injection switch in RailBite, contract tests both directions, outbox plus dead letter queue | G12: E2E 4 intermittent in CI | H12: Open
A13: R9 | B13: Time lost to Docker and CI infrastructure | C13: Medium | D13: Medium | E13: =IFERROR(MATCH($C13,{"Low";"Medium";"High"},0)*MATCH($D13,{"Low";"Medium";"High"},0),"") -> 4 | F13: Compose and CI working by D7 or drop CI to a local script and move on | G13: 3.4.3 not green by end of D7 | H13: Open
A14: R10 | B14: Illness or external interruption | C14: Low | D14: High | E14: =IFERROR(MATCH($C14,{"Low";"Medium";"High"},0)*MATCH($D14,{"Low";"Medium";"High"},0),"") -> 3 | F14: D21 buffer task 8.4.1; week gates allow graceful degradation rather than collapse | G14: More than one full day lost | H14: Open

Sheet Defects
A1: Defect log
A2: A deliverable in its own right (brief section 23 QA). Log defects you caused and fixed too - an empty log reads as no testing. The grey row is an example; delete it.
A4: ID | B4: Date found | C4: Severity | D4: Area | E4: How found | F4: Steps to reproduce | G4: Expected | H4: Actual | I4: Root cause | J4: Fix commit | K4: Prevention test added | L4: Status | M4: Closed
A5: DEF-001 | B5: 2026-10-08 | C5: Major | D5: Live Operations | E5: E2E 1 draft run | F5: Delay a journey by 8 min at stop 3, then inspect stop 6 ETA | G5: Downstream ETAs shift by 8 min | H5: Stops 4 and 5 shift, stop 6 unchanged | I5: Propagation loop stopped at the first stop with a scheduled dwell buffer | J5: f7a91c2 | K5: Unit test: propagation across a stop with dwell buffer | L5: Fixed | M5: 2026-10-08

Sheet Deferred
A1: Deferred scope register
A2: Brief section 25 grades deferral as a skill. Every cut needs a reason, not just an exclusion. Add a row whenever you cut something mid-project.
A4: ID | B4: Deferred item | C4: Reason | D4: Decided on | E4: Would need
A5: X-01 | B5: Ticketing, fares and seat reservation | C5: Not in the brief. SmartRail is an information platform; adding commerce would double the domain and the compliance surface. | E5: Payment compliance, fare engine
A6: X-02 | B6: Real card payments | C6: Payment ownership assigned to the catering provider. SmartRail never sees a card number. Provider test mode only. | E6: PCI scope, provider live keys
A7: X-03 | B7: Knock-on delay propagation between trains | C7: Real railway behaviour, but needs a network capacity and conflict model. Named as known-and-excluded rather than missed. | E7: Track capacity model
A8: X-04 | B8: Train splitting, joining and coach composition | C8: Rare and hard to model. Documented as a domain extension point in the journey aggregate. | E8: Vehicle composition aggregate
A9: X-05 | B9: SMS and email notification channels | C9: Push plus in-app covers every demonstrated journey; adding a carrier is integration cost with no new architectural lesson. | E9: Carrier account, deliverability handling
A10: X-06 | B10: Kubernetes, multi-region and autoscaling | C10: Documented as a production path in the operations docs; not built. No assessment credit for the infrastructure time. | E10: Cluster, IaC, cost budget
A11: X-07 | B11: Full multilingual rollout | C11: i18n scaffolding plus one secondary language on passenger app and displays only. Ops console stays English - internal audience. | E11: Translation review per language
A12: X-08 | B12: Formal accessibility audit and certification | C12: WCAG 2.2 AA treated as a design and test target with axe plus manual checks. Certification is out of scope for a 3-week assessment. | E12: External auditor
A13: X-09 | B13: On-board catering delivery by staff | C13: Collection-at-station only. One fulfilment mode fully worked beats two half-modes. | E13: Crew handheld app, seat mapping
A14: X-10 | B14: ML-based ETA prediction | C14: The deterministic propagation model is explainable and defensible. An unexplainable model would violate brief section 28. | E14: Historical dataset, model ops

Sheet Lists
A1: Validation lists
A2: Referenced by dropdowns on other sheets. Add values at the bottom of a column; do not leave gaps.
A4: Status | B4: Workstream | C4: AI role | D4: AI verdict | E4: AI error type | F4: Validation method | G4: Severity | H4: Likelihood | I4: Impact | J4: Defect status | K4: Yes / No | L4: AI tool | M4: Use (policy) | N4: ADR status
A5: To do | B5: REQ | C5: requirements-analyst | D5: Accepted | E5: None | F5: Unit test | G5: Critical | H5: High | I5: High | J5: Open | K5: Yes | L5: ChatGPT | M5: Primary | N5: Proposed
A6: Doing | B6: ARCH | C6: stakeholder-persona | D6: Accepted with edits | E6: Hallucinated API | F6: Integration test | G6: Major | H6: Medium | I6: Medium | J6: In progress | K6: No | L6: Gemini | M6: Secondary | N6: Accepted
A7: Done | B7: SEC | C7: domain-modeller | D7: Rejected | E7: Wrong domain logic | F7: E2E test | G7: Minor | H7: Low | I7: Low | J7: Fixed | L7: Claude Code | M7: Review only | N7: Superseded
A8: Blocked | B8: UX | C8: architect | D8: Not used | E8: Over-engineered | F8: Ran it manually | G8: Trivial | J8: Won't fix | L8: Claude (chat) | M8: Not used | N8: Rejected
A9: Deferred | B9: BE | C9: ux-designer | E9: Security blind spot | F9: Manual code review | J9: Closed | L9: GitHub Copilot
B10: WEB | C10: implementer | E10: Outdated information | F10: Cross-checked documentation | L10: Other
B11: MOB | C11: reviewer | E11: Tautological test | F11: AI cross-review
B12: KIOSK | C12: test-engineer | E12: Missed edge case
B13: INT | C13: security-reviewer | E13: Ignored constraint
B14: QA | C14: technical-writer
B15: OPS
B16: DOC

Sheet How to use
A1: How to use this workbook
A2: Read once. Daily use is three cells.
A5: The daily loop (under 5 minutes)
A6: 1 | B6: Open WBS. Set Status to Doing on what you start.
A7: 2 | B7: When a task closes: Status = Done, and type the real hours into Act h.
A8: 3 | B8: Log every AI contribution on AI Usage Log the same day. Never save this for later.
A9: 4 | B9: Glance at Dashboard. If Slipped tasks is red, decide now: re-date, cut, or spend buffer.
A11: Which cells you edit
A12: Blue text | B12: Input cells. Safe to edit.
A13: Black text | B13: Formulas. Do not overwrite.
A14: Yellow fill | B14: Dashboard B3 only - the project start date. Change it and the whole plan reshifts.
A16: Sheets
A17: Dashboard | B17: Generated summary - progress, gates, §21 AI evidence coverage, work-package subtask progress, daily load. Screenshot this for status updates.
A18: WBS | B18: The plan. Three levels: phase, work package, task. Only task rows are edited; the two levels above roll up.
A19: Gantt | B19: Generated from WBS. Blue planned, amber in progress, green done, red blocked.
A20: AI Policy | B20: Which tools, what each is responsible for, and WHY that tool for that job. Covers §21 bullets 1 and 2. Written once; revise only with a dated note.
A21: AI Usage Log | B21: One row per AI contribution. The 'What I changed or why I rejected it' column is the one assessors read.
A22: Prompt Library | B22: §21 bullet 3. Prompts and workflows that changed the outcome - not every message.
A23: AI Failures | B23: §21 bullets 5 and 6. Target 8 entries. The highest-value sheet in the submission.
A24: Modified Impl | B24: §21 bullet 7. AI-generated code you substantively rewrote, and why.
A25: AI Summary | B25: Formulas over the log. Challenge rate by tool, and the 'AI was wrong' counter against the target of 8.
A26: Decisions | B26: ADR index. Every row keeps the justification AND the rejected alternative.
A27: Risks | B27: Review every Friday. Score colours itself.
A28: Defects | B28: QA deliverable. Log your own defects too - an empty log reads as no testing.
... A30: Lists | B30: Dropdown sources. Extend at the bottom of a column.
A32: Adding work mid-project
B33: Insert a row inside the WBS task block it belongs to, give it the next WBS code (e.g. 4.2.3), set Lvl to 3, then copy the formulas in columns G, H, M and T down from the row above. Set _parent and _root (hidden columns R and S) to the parent and phase codes or the rollups will miss it.
A35: Capturing AI usage without extra work
B36: Run: git config commit.template .gitmessage
B37: Each commit then prompts for Task, AI-Role, AI-Verdict and AI-Note trailers. Those are your receipts - timestamped in git history, so the record is evidence rather than something written from memory at the end. Paste them into the AI Usage Log at the end of each day.
A39: Why the challenge rate matters
B40: Brief section 21 says explicitly that using AI successfully does not mean accepting everything it generates. A project claiming heavy AI use with a 5% challenge rate reads as unexamined. Write notes specific enough to defend out loud: 'rejected its Include chain, N+1 across JourneyStop' beats 'fixed AI code'.
